Workbook
Name FILTER: MONITORING!$E:$AG

Sheet Recipients REF
A1: =IFERROR(__xludf.DUMMYFUNCTION("IMPORTRANGE(""https://docs.google.com/spreadsheets/d/1SbJSGn0EFbAIXgek3pE0WQkKMu5cg3viyDcV21CNd-w/edit?gid=0#gid=0"",""Tractor!A:T"")"),"") | B1: =IFERROR(__xludf.DUMMYFUNCTION("""COMPUTED_VALUE"""),"FOUR WHEEL TRACTOR WITH IMPLEMENTS") -> FOUR WHEEL TRACTOR WITH IMPLEMENTS | E1: =IFERROR(__xludf.DUMMYFUNCTION("""COMPUTED_VALUE"""),4.0) -> 4
A2: =IFERROR(__xludf.DUMMYFUNCTION("""COMPUTED_VALUE"""),"NO") -> NO | C2: =IFERROR(__xludf.DUMMYFUNCTION("""COMPUTED_VALUE"""),"Address") -> Address | D2: =IFERROR(__xludf.DUMMYFUNCTION("""COMPUTED_VALUE"""),"CONTACT PERSON") -> CONTACT PERSON | E2: =IFERROR(__xludf.DUMMYFUNCTION("""COMPUTED_VALUE"""),"CONTACT NUMBER") -> CONTACT NUMBER | F2: =IFERROR(__xludf.DUMMYFUNCTION("""COMPUTED_VALUE"""),"Project REF") -> Project REF | H2: =IFERROR(__xludf.DUMMYFUNCTION("""COMPUTED_VALUE"""),"DR NO.") -> DR NO. | I2: =IFERROR(__xludf.DUMMYFUNCTION("""COMPUTED_VALUE"""),"Tractor SN") -> Tractor SN | J2: =IFERROR(__xludf.DUMMYFUNCTION("""COMPUTED_VALUE"""),"Tractor EN") -> Tractor EN | K2: =IFERROR(__xludf.DUMMYFUNCTION("""COMPUTED_VALUE"""),"Front Loader SN") -> Front Loader SN | L2: =IFERROR(__xludf.DUMMYFUNCTION("""COMPUTED_VALUE"""),"Rotavator SN") -> Rotavator SN | M2: =IFERROR(__xludf.DUMMYFUNCTION("""COMPUTED_VALUE"""),"Disc Plow SN") -> Disc Plow SN | O2: =IFERROR(__xludf.DUMMYFUNCTION("""COMPUTED_VALUE"""),"Barangay") -> Barangay | Q2: =IFERROR(__xludf.DUMMYFUNCTION("""COMPUTED_VALUE"""),"Province") -> Province | R2: =IFERROR(__xludf.DUMMYFUNCTION("""COMPUTED_VALUE"""),"REGION") -> REGION
A3: =IFERROR(__xludf.DUMMYFUNCTION("""COMPUTED_VALUE"""),1.0) -> 1 | B3: =IFERROR(__xludf.DUMMYFUNCTION("""COMPUTED_VALUE"""),"TUBUAN-TANZA IRRIGATORS ASSOCIATION, INC.") -> TUBUAN-TANZA IRRIGATORS ASSOCIATION, INC. | C3: =IFERROR(__xludf.DUMMYFUNCTION("""COMPUTED_VALUE"""),"TUBUAN, PILA, LAGUNA") -> TUBUAN, PILA, LAGUNA | D3: =IFERROR(__xludf.DUMMYFUNCTION("""COMPUTED_VALUE"""),"Virgilio Cortes") -> Virgilio Cortes | E3: =IFERROR(__xludf.DUMMYFUNCTION("""COMPUTED_VALUE"""),"0935 4386 214") -> 0935 4386 214 | F3: =IFERROR(__xludf.DUMMYFUNCTION("""COMPUTED_VALUE"""),"RCEF 23-08-20 Rebidding") -> RCEF 23-08-20 Rebidding | G3: =IFERROR(__xludf.DUMMYFUNCTION("""COMPUTED_VALUE"""),1.0) -> 1 | H3: =IFERROR(__xludf.DUMMYFUNCTION("""COMPUTED_VALUE"""),16765.0) -> 16765 | I3: =IFERROR(__xludf.DUMMYFUNCTION("""COMPUTED_VALUE"""),"KMC5825AAPFPV0036") -> KMC5825AAPFPV0036 | J3: =IFERROR(__xludf.DUMMYFUNCTION("""COMPUTED_VALUE"""),"PTS100033") -> PTS100033 | K3: =IFERROR(__xludf.DUMMYFUNCTION("""COMPUTED_VALUE"""),"R-SERIES 001 PH") -> R-SERIES 001 PH | L3: =IFERROR(__xludf.DUMMYFUNCTION("""COMPUTED_VALUE"""),"WR LSGW 0001") -> WR LSGW 0001 | M3: =IFERROR(__xludf.DUMMYFUNCTION("""COMPUTED_VALUE"""),"WR WDP 0001") -> WR WDP 0001 | O3: =IFERROR(__xludf.DUMMYFUNCTION("""COMPUTED_VALUE"""),"Tubuan") -> Tubuan | P3: =IFERROR(__xludf.DUMMYFUNCTION("""COMPUTED_VALUE"""),"Pila") -> Pila | Q3: =IFERROR(__xludf.DUMMYFUNCTION("""COMPUTED_VALUE"""),"Laguna") -> Laguna | R3: =IFERROR(__xludf.DUMMYFUNCTION("""COMPUTED_VALUE"""),"4A") -> 4A
A4: =IFERROR(__xludf.DUMMYFUNCTION("""COMPUTED_VALUE"""),2.0) -> 2 | B4: =IFERROR(__xludf.DUMMYFUNCTION("""COMPUTED_VALUE"""),"PILA LAGUNA AGRICULTURE COOPERATIVE (PILAC)") -> PILA LAGUNA AGRICULTURE COOPERATIVE (PILAC) | C4: =IFERROR(__xludf.DUMMYFUNCTION("""COMPUTED_VALUE"""),"PANSOL, PILA, LAGUNA") -> PANSOL, PILA, LAGUNA | D4: =IFERROR(__xludf.DUMMYFUNCTION("""COMPUTED_VALUE"""),"BENJAMIN MANUAL") -> BENJAMIN MANUAL | E4: =IFERROR(__xludf.DUMMYFUNCTION("""COMPUTED_VALUE"""),9.750884823E9) -> 9750884823 | F4: =IFERROR(__xludf.DUMMYFUNCTION("""COMPUTED_VALUE"""),"RCEF 23-08-20 Rebidding") -> RCEF 23-08-20 Rebidding | G4: =IFERROR(__xludf.DUMMYFUNCTION("""COMPUTED_VALUE"""),1.0) -> 1 | H4: =IFERROR(__xludf.DUMMYFUNCTION("""COMPUTED_VALUE"""),16767.0) -> 16767 | I4: =IFERROR(__xludf.DUMMYFUNCTION("""COMPUTED_VALUE"""),"KMC5825ALPFPV0037") -> KMC5825ALPFPV0037 | J4: =IFERROR(__xludf.DUMMYFUNCTION("""COMPUTED_VALUE"""),"PTS100030") -> PTS100030 | K4: =IFERROR(__xludf.DUMMYFUNCTION("""COMPUTED_VALUE"""),"R-SERIES 005 PH") -> R-SERIES 005 PH | L4: =IFERROR(__xludf.DUMMYFUNCTION("""COMPUTED_VALUE"""),"WR LSGW 0003") -> WR LSGW 0003 | M4: =IFERROR(__xludf.DUMMYFUNCTION("""COMPUTED_VALUE"""),"WR WDP 0003") -> WR WDP 0003 | O4: =IFERROR(__xludf.DUMMYFUNCTION("""COMPUTED_VALUE"""),"Pansol") -> Pansol | P4: =IFERROR(__xludf.DUMMYFUNCTION("""COMPUTED_VALUE"""),"Pila") -> Pila | Q4: =IFERROR(__xludf.DUMMYFUNCTION("""COMPUTED_VALUE"""),"Laguna") -> Laguna | R4: =IFERROR(__xludf.DUMMYFUNCTION("""COMPUTED_VALUE"""),"4A") -> 4A
A5: =IFERROR(__xludf.DUMMYFUNCTION("""COMPUTED_VALUE"""),3.0) -> 3 | B5: =IFERROR(__xludf.DUMMYFUNCTION("""COMPUTED_VALUE"""),"STO. DOMINGO-MAITIM IRRIGATORS ASSOCIATION, INC.") -> STO. DOMINGO-MAITIM IRRIGATORS ASSOCIATION, INC. | C5: =IFERROR(__xludf.DUMMYFUNCTION("""COMPUTED_VALUE"""),"MAITIM, BAY, LAGUNA") -> MAITIM, BAY, LAGUNA | D5: =IFERROR(__xludf.DUMMYFUNCTION("""COMPUTED_VALUE"""),"#N/A") -> #N/A | E5: =IFERROR(__xludf.DUMMYFUNCTION("""COMPUTED_VALUE"""),"#N/A") -> #N/A | F5: =IFERROR(__xludf.DUMMYFUNCTION("""COMPUTED_VALUE"""),"RCEF 23-08-20 Rebidding") -> RCEF 23-08-20 Rebidding | G5: =IFERROR(__xludf.DUMMYFUNCTION("""COMPUTED_VALUE"""),1.0) -> 1 | H5: =IFERROR(__xludf.DUMMYFUNCTION("""COMPUTED_VALUE"""),16768.0) -> 16768 | I5: =IFERROR(__xludf.DUMMYFUNCTION("""COMPUTED_VALUE"""),"KMC5825AEPFPV0039") -> KMC5825AEPFPV0039 | J5: =IFERROR(__xludf.DUMMYFUNCTION("""COMPUTED_VALUE"""),"PTS100001") -> PTS100001 | K5: =IFERROR(__xludf.DUMMYFUNCTION("""COMPUTED_VALUE"""),"R-SERIES 019 PH") -> R-SERIES 019 PH | L5: =IFERROR(__xludf.DUMMYFUNCTION("""COMPUTED_VALUE"""),"WR LSGW 0002") -> WR LSGW 0002 | M5: =IFERROR(__xludf.DUMMYFUNCTION("""COMPUTED_VALUE"""),"WR WDP 0002") -> WR WDP 0002 | O5: =IFERROR(__xludf.DUMMYFUNCTION("""COMPUTED_VALUE"""),"Maitim") -> Maitim | P5: =IFERROR(__xludf.DUMMYFUNCTION("""COMPUTED_VALUE"""),"Bay") -> Bay | Q5: =IFERROR(__xludf.DUMMYFUNCTION("""COMPUTED_VALUE"""),"Laguna") -> Laguna | R5: =IFERROR(__xludf.DUMMYFUNCTION("""COMPUTED_VALUE"""),"4A") -> 4A
A6: =IFERROR(__xludf.DUMMYFUNCTION("""COMPUTED_VALUE"""),4.0) -> 4 | B6: =IFERROR(__xludf.DUMMYFUNCTION("""COMPUTED_VALUE"""),"BAGONG SAMAHAN NG MAGSASAKA NG PILA, LAGUNA, INC.") -> BAGONG SAMAHAN NG MAGSASAKA NG PILA, LAGUNA, INC. | C6: =IFERROR(__xludf.DUMMYFUNCTION("""COMPUTED_VALUE"""),"STA CLARA SUR, PILA, LAGUNA") -> STA CLARA SUR, PILA, LAGUNA | D6: =IFERROR(__xludf.DUMMYFUNCTION("""COMPUTED_VALUE"""),"Ernesto S. Napao") -> Ernesto S. Napao | E6: =IFERROR(__xludf.DUMMYFUNCTION("""COMPUTED_VALUE"""),9.338124621E9) -> 9338124621 | F6: =IFERROR(__xludf.DUMMYFUNCTION("""COMPUTED_VALUE"""),"RCEF 23-08-20 Rebidding") -> RCEF 23-08-20 Rebidding | G6: =IFERROR(__xludf.DUMMYFUNCTION("""COMPUTED_VALUE"""),1.0) -> 1 | H6: =IFERROR(__xludf.DUMMYFUNCTION("""COMPUTED_VALUE"""),16769.0) -> 16769 | I6: =IFERROR(__xludf.DUMMYFUNCTION("""COMPUTED_VALUE"""),"KMC5825AJPFPV0016") -> KMC5825AJPFPV0016 | J6: =IFERROR(__xludf.DUMMYFUNCTION("""COMPUTED_VALUE"""),"PTS100028") -> PTS100028 | K6: =IFERROR(__xludf.DUMMYFUNCTION("""COMPUTED_VALUE"""),"R-SERIES 010 PH") -> R-SERIES 010 PH | L6: =IFERROR(__xludf.DUMMYFUNCTION("""COMPUTED_VALUE"""),"WR LSGW 0004") -> WR LSGW 0004 | M6: =IFERROR(__xludf.DUMMYFUNCTION("""COMPUTED_VALUE"""),"WR WDP 0004") -> WR WDP 0004 | O6: =IFERROR(__xludf.DUMMYFUNCTION("""COMPUTED_VALUE"""),"Sta Clara Sur") -> Sta Clara Sur | P6: =IFERROR(__xludf.DUMMYFUNCTION("""COMPUTED_VALUE"""),"Pila") -> Pila | Q6: =IFERROR(__xludf.DUMMYFUNCTION("""COMPUTED_VALUE"""),"Laguna") -> Laguna | R6: =IFERROR(__xludf.DUMMYFUNCTION("""COMPUTED_VALUE"""),"4A") -> 4A
A7: =IFERROR(__xludf.DUMMYFUNCTION("""COMPUTED_VALUE"""),5.0) -> 5 | B7: =IFERROR(__xludf.DUMMYFUNCTION("""COMPUTED_VALUE"""),"BANCA-BANCA, SAN FRANCISCO, SAN FELIX, SAN ROQUE IRRIGATORS ASSOCIATION, INC.") -> BANCA-BANCA, SAN FRANCISCO, SAN FELIX, SAN ROQUE IRRIGATORS ASSOCIATION, INC. | C7: =IFERROR(__xludf.DUMMYFUNCTION("""COMPUTED_VALUE"""),"SAN FRANCISCO, VICTORIA, LAGUNA") -> SAN FRANCISCO, VICTORIA, LAGUNA | D7: =IFERROR(__xludf.DUMMYFUNCTION("""COMPUTED_VALUE"""),"Francisco Gonzales") -> Francisco Gonzales | E7: =IFERROR(__xludf.DUMMYFUNCTION("""COMPUTED_VALUE"""),"0968 664 7688") -> 0968 664 7688 | F7: =IFERROR(__xludf.DUMMYFUNCTION("""COMPUTED_VALUE"""),"RCEF 23-08-20 Rebidding") -> RCEF 23-08-20 Rebidding | G7: =IFERROR(__xludf.DUMMYFUNCTION("""COMPUTED_VALUE"""),1.0) -> 1 | H7: =IFERROR(__xludf.DUMMYFUNCTION("""COMPUTED_VALUE"""),16770.0) -> 16770 | I7: =IFERROR(__xludf.DUMMYFUNCTION("""COMPUTED_VALUE"""),"KMC5825AHPFPV0010") -> KMC5825AHPFPV0010 | J7: =IFERROR(__xludf.DUMMYFUNCTION("""COMPUTED_VALUE"""),"PTS100002") -> PTS100002 | K7: =IFERROR(__xludf.DUMMYFUNCTION("""COMPUTED_VALUE"""),"R-SERIES 008 PH") -> R-SERIES 008 PH | L7: =IFERROR(__xludf.DUMMYFUNCTION("""COMPUTED_VALUE"""),"WR LSGW 0005") -> WR LSGW 0005 | M7: =IFERROR(__xludf.DUMMYFUNCTION("""COMPUTED_VALUE"""),"WR WDP 0005") -> WR WDP 0005 | O7: =IFERROR(__xludf.DUMMYFUNCTION("""COMPUTED_VALUE"""),"San Francisco") -> San Francisco | P7: =IFERROR(__xludf.DUMMYFUNCTION("""COMPUTED_VALUE"""),"Victoria") -> Victoria | Q7: =IFERROR(__xludf.DUMMYFUNCTION("""COMPUTED_VALUE"""),"Laguna") -> Laguna | R7: =IFERROR(__xludf.DUMMYFUNCTION("""COMPUTED_VALUE"""),"4A") -> 4A
A8: =IFERROR(__xludf.DUMMYFUNCTION("""COMPUTED_VALUE"""),6.0) -> 6 | B8: =IFERROR(__xludf.DUMMYFUNCTION("""COMPUTED_VALUE"""),"POBLACION-NEW DAGUPAN FARMER-IRRIGATORS' ASSOCIATION (PONDAFIA) INC.") -> POBLACION-NEW DAGUPAN FARMER-IRRIGATORS' ASSOCIATION (PONDAFIA) INC. | C8: =IFERROR(__xludf.DUMMYFUNCTION("""COMPUTED_VALUE"""),"POBLACION, CALinTAAN, OCCIDENTAL MINDORO") -> POBLACION, CALinTAAN, OCCIDENTAL MINDORO | D8: =IFERROR(__xludf.DUMMYFUNCTION("""COMPUTED_VALUE"""),"Manuel A. Francisco") -> Manuel A. Francisco | E8: =IFERROR(__xludf.DUMMYFUNCTION("""COMPUTED_VALUE"""),"0935 417 5163") -> 0935 417 5163 | F8: =IFERROR(__xludf.DUMMYFUNCTION("""COMPUTED_VALUE"""),"RCEF 23-08-20 Rebidding") -> RCEF 23-08-20 Rebidding | G8: =IFERROR(__xludf.DUMMYFUNCTION("""COMPUTED_VALUE"""),1.0) -> 1 | H8: =IFERROR(__xludf.DUMMYFUNCTION("""COMPUTED_VALUE"""),16771.0) -> 16771 | I8: =IFERROR(__xludf.DUMMYFUNCTION("""COMPUTED_VALUE"""),"KMC 5825 ACPFPV0003") -> KMC 5825 ACPFPV0003 | J8: =IFERROR(__xludf.DUMMYFUNCTION("""COMPUTED_VALUE"""),"PTS100013") -> PTS100013 | K8: =IFERROR(__xludf.DUMMYFUNCTION("""COMPUTED_VALUE"""),"R-SERIES 009 PH") -> R-SERIES 009 PH | L8: =IFERROR(__xludf.DUMMYFUNCTION("""COMPUTED_VALUE"""),"WR LSGW 0006") -> WR LSGW 0006 | M8: =IFERROR(__xludf.DUMMYFUNCTION("""COMPUTED_VALUE"""),"WR WDP 0006") -> WR WDP 0006 | O8: =IFERROR(__xludf.DUMMYFUNCTION("""COMPUTED_VALUE"""),"Poblacion") -> Poblacion | P8: =IFERROR(__xludf.DUMMYFUNCTION("""COMPUTED_VALUE"""),"Calintaan") -> Calintaan | Q8: =IFERROR(__xludf.DUMMYFUNCTION("""COMPUTED_VALUE"""),"Occidental Mindoro") -> Occidental Mindoro | R8: =IFERROR(__xludf.DUMMYFUNCTION("""COMPUTED_VALUE"""),"4B") -> 4B
A9: =IFERROR(__xludf.DUMMYFUNCTION("""COMPUTED_VALUE"""),7.0) -> 7 | B9: =IFERROR(__xludf.DUMMYFUNCTION("""COMPUTED_VALUE"""),"BUGTONG BURI FARMERS ASSOCIATION, INC.") -> BUGTONG BURI FARMERS ASSOCIATION, INC. | C9: =IFERROR(__xludf.DUMMYFUNCTION("""COMPUTED_VALUE"""),"POBLACION, MAGSAYSAY, OCCIDENTAL MINDORO") -> POBLACION, MAGSAYSAY, OCCIDENTAL MINDORO | D9: =IFERROR(__xludf.DUMMYFUNCTION("""COMPUTED_VALUE"""),"Gloria G. Operio") -> Gloria G. Operio | E9: =IFERROR(__xludf.DUMMYFUNCTION("""COMPUTED_VALUE"""),"0930 925 4686") -> 0930 925 4686 | F9: =IFERROR(__xludf.DUMMYFUNCTION("""COMPUTED_VALUE"""),"RCEF 23-08-20 Rebidding") -> RCEF 23-08-20 Rebidding | G9: =IFERROR(__xludf.DUMMYFUNCTION("""COMPUTED_VALUE"""),1.0) -> 1 | H9: =IFERROR(__xludf.DUMMYFUNCTION("""COMPUTED_VALUE"""),16772.0) -> 16772 | I9: =IFERROR(__xludf.DUMMYFUNCTION("""COMPUTED_VALUE"""),"KMC 5825 APPFPV0014") -> KMC 5825 APPFPV0014 | J9: =IFERROR(__xludf.DUMMYFUNCTION("""COMPUTED_VALUE"""),"PTS100016") -> PTS100016 | K9: =IFERROR(__xludf.DUMMYFUNCTION("""COMPUTED_VALUE"""),"R-SERIES 006 PH") -> R-SERIES 006 PH | L9: =IFERROR(__xludf.DUMMYFUNCTION("""COMPUTED_VALUE"""),"WR LSGW 0007") -> WR LSGW 0007 | M9: =IFERROR(__xludf.DUMMYFUNCTION("""COMPUTED_VALUE"""),"WR WDP 0007") -> WR WDP 0007 | O9: =IFERROR(__xludf.DUMMYFUNCTION("""COMPUTED_VALUE"""),"Poblacion") -> Poblacion | P9: =IFERROR(__xludf.DUMMYFUNCTION("""COMPUTED_VALUE"""),"Magsaysay") -> Magsaysay | Q9: =IFERROR(__xludf.DUMMYFUNCTION("""COMPUTED_VALUE"""),"Occidental Mindoro") -> Occidental Mindoro | R9: =IFERROR(__xludf.DUMMYFUNCTION("""COMPUTED_VALUE"""),"4B") -> 4B
A10: =IFERROR(__xludf.DUMMYFUNCTION("""COMPUTED_VALUE"""),8.0) -> 8 | B10: =IFERROR(__xludf.DUMMYFUNCTION("""COMPUTED_VALUE"""),"SAMARICA OCCIDENTAL MINDORO FARMERS ASSOCIATION INC.") -> SAMARICA OCCIDENTAL MINDORO FARMERS ASSOCIATION INC. | C10: =IFERROR(__xludf.DUMMYFUNCTION("""COMPUTED_VALUE"""),"ADELA, RIZAL, OCCIDENTAL MINDORO") -> ADELA, RIZAL, OCCIDENTAL MINDORO | D10: =IFERROR(__xludf.DUMMYFUNCTION("""COMPUTED_VALUE"""),"Josie M. Maramot") -> Josie M. Maramot | E10: =IFERROR(__xludf.DUMMYFUNCTION("""COMPUTED_VALUE"""),"0949 933 1443") -> 0949 933 1443 | F10: =IFERROR(__xludf.DUMMYFUNCTION("""COMPUTED_VALUE"""),"RCEF 23-08-20 Rebidding") -> RCEF 23-08-20 Rebidding | G10: =IFERROR(__xludf.DUMMYFUNCTION("""COMPUTED_VALUE"""),1.0) -> 1 | H10: =IFERROR(__xludf.DUMMYFUNCTION("""COMPUTED_VALUE"""),16774.0) -> 16774 | I10: =IFERROR(__xludf.DUMMYFUNCTION("""COMPUTED_VALUE"""),"KMC 5825 AVPFPV0004") -> KMC 5825 AVPFPV0004 | J10: =IFERROR(__xludf.DUMMYFUNCTION("""COMPUTED_VALUE"""),"PTS100020") -> PTS100020 | K10: =IFERROR(__xludf.DUMMYFUNCTION("""COMPUTED_VALUE"""),"R-SERIES 018 PH") -> R-SERIES 018 PH | L10: =IFERROR(__xludf.DUMMYFUNCTION("""COMPUTED_VALUE"""),"WR LSGW 0009") -> WR LSGW 0009 | M10: =IFERROR(__xludf.DUMMYFUNCTION("""COMPUTED_VALUE"""),"WR WDP 0009") -> WR WDP 0009 | O10: =IFERROR(__xludf.DUMMYFUNCTION("""COMPUTED_VALUE"""),"Adela") -> Adela | P10: =IFERROR(__xludf.DUMMYFUNCTION("""COMPUTED_VALUE"""),"Rizal") -> Rizal | Q10: =IFERROR(__xludf.DUMMYFUNCTION("""COMPUTED_VALUE"""),"Occidental Mindoro") -> Occidental Mindoro | R10: =IFERROR(__xludf.DUMMYFUNCTION("""COMPUTED_VALUE"""),"4B") -> 4B
A11: =IFERROR(__xludf.DUMMYFUNCTION("""COMPUTED_VALUE"""),9.0) -> 9 | B11: =IFERROR(__xludf.DUMMYFUNCTION("""COMPUTED_VALUE"""),"SALVACION UNITED FARMERS MULTI-PURPOSE COOPERATIVE") -> SALVACION UNITED FARMERS MULTI-PURPOSE COOPERATIVE | C11: =IFERROR(__xludf.DUMMYFUNCTION("""COMPUTED_VALUE"""),"SALVACION, RIZAL, OCCIDENTAL MINDORO") -> SALVACION, RIZAL, OCCIDENTAL MINDORO | D11: =IFERROR(__xludf.DUMMYFUNCTION("""COMPUTED_VALUE"""),"Birtsan A. Montales") -> Birtsan A. Montales | E11: =IFERROR(__xludf.DUMMYFUNCTION("""COMPUTED_VALUE"""),"0930 838 7003") -> 0930 838 7003 | F11: =IFERROR(__xludf.DUMMYFUNCTION("""COMPUTED_VALUE"""),"RCEF 23-08-20 Rebidding") -> RCEF 23-08-20 Rebidding | G11: =IFERROR(__xludf.DUMMYFUNCTION("""COMPUTED_VALUE"""),1.0) -> 1 | H11: =IFERROR(__xludf.DUMMYFUNCTION("""COMPUTED_VALUE"""),16775.0) -> 16775 | I11: =IFERROR(__xludf.DUMMYFUNCTION("""COMPUTED_VALUE"""),"KMC 5825 AJPFPV0033") -> KMC 5825 AJPFPV0033 | J11: =IFERROR(__xludf.DUMMYFUNCTION("""COMPUTED_VALUE"""),"PTS100031") -> PTS100031 | K11: =IFERROR(__xludf.DUMMYFUNCTION("""COMPUTED_VALUE"""),"R-SERIES 023 PH") -> R-SERIES 023 PH | L11: =IFERROR(__xludf.DUMMYFUNCTION("""COMPUTED_VALUE"""),"WR LSGW 0010") -> WR LSGW 0010 | M11: =IFERROR(__xludf.DUMMYFUNCTION("""COMPUTED_VALUE"""),"WR WDP 0010") -> WR WDP 0010 | O11: =IFERROR(__xludf.DUMMYFUNCTION("""COMPUTED_VALUE"""),"Salvacion") -> Salvacion | P11: =IFERROR(__xludf.DUMMYFUNCTION("""COMPUTED_VALUE"""),"Rizal") -> Rizal | Q11: =IFERROR(__xludf.DUMMYFUNCTION("""COMPUTED_VALUE"""),"Occidental Mindoro") -> Occidental Mindoro | R11: =IFERROR(__xludf.DUMMYFUNCTION("""COMPUTED_VALUE"""),"4B") -> 4B
A12: =IFERROR(__xludf.DUMMYFUNCTION("""COMPUTED_VALUE"""),10.0) -> 10 | B12: =IFERROR(__xludf.DUMMYFUNCTION("""COMPUTED_VALUE"""),"MATABIAGA MALAWAAN IRRIGATORS ASSOCIATION, INC.") -> MATABIAGA MALAWAAN IRRIGATORS ASSOCIATION, INC. | C12: =IFERROR(__xludf.DUMMYFUNCTION("""COMPUTED_VALUE"""),"MALAWAAN, RIZAL, OCCIDENTAL MINDORO") -> MALAWAAN, RIZAL, OCCIDENTAL MINDORO | D12: =IFERROR(__xludf.DUMMYFUNCTION("""COMPUTED_VALUE"""),"Ernie Urbina") -> Ernie Urbina | E12: =IFERROR(__xludf.DUMMYFUNCTION("""COMPUTED_VALUE"""),"0909 354 0587") -> 0909 354 0587 | F12: =IFERROR(__xludf.DUMMYFUNCTION("""COMPUTED_VALUE"""),"RCEF 23-08-20 Rebidding") -> RCEF 23-08-20 Rebidding | G12: =IFERROR(__xludf.DUMMYFUNCTION("""COMPUTED_VALUE"""),1.0) -> 1 | H12: =IFERROR(__xludf.DUMMYFUNCTION("""COMPUTED_VALUE"""),16776.0) -> 16776 | I12: =IFERROR(__xludf.DUMMYFUNCTION("""COMPUTED_VALUE"""),"KMC 5825 AEPFPV0008") -> KMC 5825 AEPFPV0008 | J12: =IFERROR(__xludf.DUMMYFUNCTION("""COMPUTED_VALUE"""),"PTS100005") -> PTS100005 | K12: =IFERROR(__xludf.DUMMYFUNCTION("""COMPUTED_VALUE"""),"R-SERIES 015 PH") -> R-SERIES 015 PH | L12: =IFERROR(__xludf.DUMMYFUNCTION("""COMPUTED_VALUE"""),"WR LSGW 0011") -> WR LSGW 0011 | M12: =IFERROR(__xludf.DUMMYFUNCTION("""COMPUTED_VALUE"""),"WR WDP 0011") -> WR WDP 0011 | O12: =IFERROR(__xludf.DUMMYFUNCTION("""COMPUTED_VALUE"""),"Malawaan") -> Malawaan | P12: =IFERROR(__xludf.DUMMYFUNCTION("""COMPUTED_VALUE"""),"Rizal") -> Rizal | Q12: =IFERROR(__xludf.DUMMYFUNCTION("""COMPUTED_VALUE"""),"Occidental Mindoro") -> Occidental Mindoro | R12: =IFERROR(__xludf.DUMMYFUNCTION("""COMPUTED_VALUE"""),"4B") -> 4B
A13: =IFERROR(__xludf.DUMMYFUNCTION("""COMPUTED_VALUE"""),11.0) -> 11 | B13: =IFERROR(__xludf.DUMMYFUNCTION("""COMPUTED_VALUE"""),"BARANGAY BATONG BUHAY FARMER'S ASSOCIATION") -> BARANGAY BATONG BUHAY FARMER'S ASSOCIATION | C13: =IFERROR(__xludf.DUMMYFUNCTION("""COMPUTED_VALUE"""),"BATONG BUHAY, SABLAYAN, OCCIDENTAL MINDORO") -> BATONG BUHAY, SABLAYAN, OCCIDENTAL MINDORO | D13: =IFERROR(__xludf.DUMMYFUNCTION("""COMPUTED_VALUE"""),"Mark Anthony Silao") -> Mark Anthony Silao | E13: =IFERROR(__xludf.DUMMYFUNCTION("""COMPUTED_VALUE"""),"0966 359 5285") -> 0966 359 5285 | F13: =IFERROR(__xludf.DUMMYFUNCTION("""COMPUTED_VALUE"""),"RCEF 23-08-20 Rebidding") -> RCEF 23-08-20 Rebidding | G13: =IFERROR(__xludf.DUMMYFUNCTION("""COMPUTED_VALUE"""),1.0) -> 1 | H13: =IFERROR(__xludf.DUMMYFUNCTION("""COMPUTED_VALUE"""),16777.0) -> 16777 | I13: =IFERROR(__xludf.DUMMYFUNCTION("""COMPUTED_VALUE"""),"KMC 5825 ATPFPV0013") -> KMC 5825 ATPFPV0013 | J13: =IFERROR(__xludf.DUMMYFUNCTION("""COMPUTED_VALUE"""),"PTS100027") -> PTS100027 | K13: =IFERROR(__xludf.DUMMYFUNCTION("""COMPUTED_VALUE"""),"R-SERIES 022 PH") -> R-SERIES 022 PH | L13: =IFERROR(__xludf.DUMMYFUNCTION("""COMPUTED_VALUE"""),"WR LSGW 0012") -> WR LSGW 0012 | M13: =IFERROR(__xludf.DUMMYFUNCTION("""COMPUTED_VALUE"""),"WR WDP 0012") -> WR WDP 0012 | O13: =IFERROR(__xludf.DUMMYFUNCTION("""COMPUTED_VALUE"""),"Batong Buhay") -> Batong Buhay | P13: =IFERROR(__xludf.DUMMYFUNCTION("""COMPUTED_VALUE"""),"Sablayan") -> Sablayan | Q13: =IFERROR(__xludf.DUMMYFUNCTION("""COMPUTED_VALUE"""),"Occidental Mindoro") -> Occidental Mindoro | R13: =IFERROR(__xludf.DUMMYFUNCTION("""COMPUTED_VALUE"""),"4B") -> 4B
A14: =IFERROR(__xludf.DUMMYFUNCTION("""COMPUTED_VALUE"""),12.0) -> 12 | B14: =IFERROR(__xludf.DUMMYFUNCTION("""COMPUTED_VALUE"""),"KAINGIN TAGUMPAY FARMERS AND IRRIGATORS ASSOCIATION (KATFAIA)") -> KAINGIN TAGUMPAY FARMERS AND IRRIGATORS ASSOCIATION (KATFAIA) | C14: =IFERROR(__xludf.DUMMYFUNCTION("""COMPUTED_VALUE"""),"TAGUMPAY, SABLAYAN, OCCIDENTAL MINDORO") -> TAGUMPAY, SABLAYAN, OCCIDENTAL MINDORO | D14: =IFERROR(__xludf.DUMMYFUNCTION("""COMPUTED_VALUE"""),"Robert Navalta") -> Robert Navalta | E14: =IFERROR(__xludf.DUMMYFUNCTION("""COMPUTED_VALUE"""),"0975 537 0138") -> 0975 537 0138 | F14: =IFERROR(__xludf.DUMMYFUNCTION("""COMPUTED_VALUE"""),"RCEF 23-08-20 Rebidding") -> RCEF 23-08-20 Rebidding | G14: =IFERROR(__xludf.DUMMYFUNCTION("""COMPUTED_VALUE"""),1.0) -> 1 | H14: =IFERROR(__xludf.DUMMYFUNCTION("""COMPUTED_VALUE"""),16778.0) -> 16778 | I14: =IFERROR(__xludf.DUMMYFUNCTION("""COMPUTED_VALUE"""),"KMC 5825 AVPFPV0021") -> KMC 5825 AVPFPV0021 | J14: =IFERROR(__xludf.DUMMYFUNCTION("""COMPUTED_VALUE"""),"PTS100025") -> PTS100025 | K14: =IFERROR(__xludf.DUMMYFUNCTION("""COMPUTED_VALUE"""),"R-SERIES016 PH") -> R-SERIES016 PH | L14: =IFERROR(__xludf.DUMMYFUNCTION("""COMPUTED_VALUE"""),"WR LSGW 0013") -> WR LSGW 0013 | M14: =IFERROR(__xludf.DUMMYFUNCTION("""COMPUTED_VALUE"""),"WR WDP 0013") -> WR WDP 0013 | O14: =IFERROR(__xludf.DUMMYFUNCTION("""COMPUTED_VALUE"""),"Tagumpay") -> Tagumpay | P14: =IFERROR(__xludf.DUMMYFUNCTION("""COMPUTED_VALUE"""),"Sablayan") -> Sablayan | Q14: =IFERROR(__xludf.DUMMYFUNCTION("""COMPUTED_VALUE"""),"Occidental Mindoro") -> Occidental Mindoro | R14: =IFERROR(__xludf.DUMMYFUNCTION("""COMPUTED_VALUE"""),"4B") -> 4B
A15: =IFERROR(__xludf.DUMMYFUNCTION("""COMPUTED_VALUE"""),13.0) -> 13 | B15: =IFERROR(__xludf.DUMMYFUNCTION("""COMPUTED_VALUE"""),"SITIO ESPERANZA SAN ISIDRO FARMERS ASSOCIATION") -> SITIO ESPERANZA SAN ISIDRO FARMERS ASSOCIATION | C15: =IFERROR(__xludf.DUMMYFUNCTION("""COMPUTED_VALUE"""),"SAN ISIDRO, SAN JOSE, OCCIDENTAL MINDORO") -> SAN ISIDRO, SAN JOSE, OCCIDENTAL MINDORO | D15: =IFERROR(__xludf.DUMMYFUNCTION("""COMPUTED_VALUE"""),"Catalina Monterola") -> Catalina Monterola | E15: =IFERROR(__xludf.DUMMYFUNCTION("""COMPUTED_VALUE"""),"0929 367 9563") -> 0929 367 9563 | F15: =IFERROR(__xludf.DUMMYFUNCTION("""COMPUTED_VALUE"""),"RCEF 23-08-20 Rebidding") -> RCEF 23-08-20 Rebidding | G15: =IFERROR(__xludf.DUMMYFUNCTION("""COMPUTED_VALUE"""),1.0) -> 1 | H15: =IFERROR(__xludf.DUMMYFUNCTION("""COMPUTED_VALUE"""),16779.0) -> 16779 | I15: =IFERROR(__xludf.DUMMYFUNCTION("""COMPUTED_VALUE"""),"KMC 5825 ALPFPV0023") -> KMC 5825 ALPFPV0023 | J15: =IFERROR(__xludf.DUMMYFUNCTION("""COMPUTED_VALUE"""),"PTS100010") -> PTS100010 | K15: =IFERROR(__xludf.DUMMYFUNCTION("""COMPUTED_VALUE"""),"R-SERIES 013 PH") -> R-SERIES 013 PH | L15: =IFERROR(__xludf.DUMMYFUNCTION("""COMPUTED_VALUE"""),"WR LSGW 0014") -> WR LSGW 0014 | M15: =IFERROR(__xludf.DUMMYFUNCTION("""COMPUTED_VALUE"""),"WR WDP 0014") -> WR WDP 0014 | O15: =IFERROR(__xludf.DUMMYFUNCTION("""COMPUTED_VALUE"""),"San Isidro") -> San Isidro | P15: =IFERROR(__xludf.DUMMYFUNCTION("""COMPUTED_VALUE"""),"San Jose") -> San Jose | Q15: =IFERROR(__xludf.DUMMYFUNCTION("""COMPUTED_VALUE"""),"Occidental Mindoro") -> Occidental Mindoro | R15: =IFERROR(__xludf.DUMMYFUNCTION("""COMPUTED_VALUE"""),"4B") -> 4B
A16: =IFERROR(__xludf.DUMMYFUNCTION("""COMPUTED_VALUE"""),14.0) -> 14 | B16: =IFERROR(__xludf.DUMMYFUNCTION("""COMPUTED_VALUE"""),"CAMANDANG IRRIGATORS ASSOCIATION") -> CAMANDANG IRRIGATORS ASSOCIATION | C16: =IFERROR(__xludf.DUMMYFUNCTION("""COMPUTED_VALUE"""),"MONTECLARO, SAN JOSE, OCCIDENTAL MINDORO") -> MONTECLARO, SAN JOSE, OCCIDENTAL MINDORO | D16: =IFERROR(__xludf.DUMMYFUNCTION("""COMPUTED_VALUE"""),"Eduardo Toquero Jr.") -> Eduardo Toquero Jr. | E16: =IFERROR(__xludf.DUMMYFUNCTION("""COMPUTED_VALUE"""),"0965 897 7577") -> 0965 897 7577 | F16: =IFERROR(__xludf.DUMMYFUNCTION("""COMPUTED_VALUE"""),"RCEF 23-08-20 Rebidding") -> RCEF 23-08-20 Rebidding | G16: =IFERROR(__xludf.DUMMYFUNCTION("""COMPUTED_VALUE"""),1.0) -> 1 | H16: =IFERROR(__xludf.DUMMYFUNCTION("""COMPUTED_VALUE"""),16780.0) -> 16780 | I16: =IFERROR(__xludf.DUMMYFUNCTION("""COMPUTED_VALUE"""),"KMC 5825 ATPFPV0030") -> KMC 5825 ATPFPV0030 | J16: =IFERROR(__xludf.DUMMYFUNCTION("""COMPUTED_VALUE"""),"PTS100014") -> PTS100014 | K16: =IFERROR(__xludf.DUMMYFUNCTION("""COMPUTED_VALUE"""),"R-SERIES 024 PH") -> R-SERIES 024 PH | L16: =IFERROR(__xludf.DUMMYFUNCTION("""COMPUTED_VALUE"""),"WR LSGW 0015") -> WR LSGW 0015 | M16: =IFERROR(__xludf.DUMMYFUNCTION("""COMPUTED_VALUE"""),"WR WDP 0015") -> WR WDP 0015 | O16: =IFERROR(__xludf.DUMMYFUNCTION("""COMPUTED_VALUE"""),"Monteclaro") -> Monteclaro | P16: =IFERROR(__xludf.DUMMYFUNCTION("""COMPUTED_VALUE"""),"San Jose") -> San Jose | Q16: =IFERROR(__xludf.DUMMYFUNCTION("""COMPUTED_VALUE"""),"Occidental Mindoro") -> Occidental Mindoro | R16: =IFERROR(__xludf.DUMMYFUNCTION("""COMPUTED_VALUE"""),"4B") -> 4B
A17: =IFERROR(__xludf.DUMMYFUNCTION("""COMPUTED_VALUE"""),15.0) -> 15 | B17: =IFERROR(__xludf.DUMMYFUNCTION("""COMPUTED_VALUE"""),"SAMAHAN NG MAGSASAKA SA PALANGHIRAN") -> SAMAHAN NG MAGSASAKA SA PALANGHIRAN | C17: =IFERROR(__xludf.DUMMYFUNCTION("""COMPUTED_VALUE"""),"MAPAYA, SAN JOSE, OCCIDENTAL MINDORO") -> MAPAYA, SAN JOSE, OCCIDENTAL MINDORO | D17: =IFERROR(__xludf.DUMMYFUNCTION("""COMPUTED_VALUE"""),"Ricardo E. Dela Cruz") -> Ricardo E. Dela Cruz | E17: =IFERROR(__xludf.DUMMYFUNCTION("""COMPUTED_VALUE"""),"0912 631 8700") -> 0912 631 8700 | F17: =IFERROR(__xludf.DUMMYFUNCTION("""COMPUTED_VALUE"""),"RCEF 23-08-20 Rebidding") -> RCEF 23-08-20 Rebidding | G17: =IFERROR(__xludf.DUMMYFUNCTION("""COMPUTED_VALUE"""),1.0) -> 1 | H17: =IFERROR(__xludf.DUMMYFUNCTION("""COMPUTED_VALUE"""),16781.0) -> 16781 | I17: =IFERROR(__xludf.DUMMYFUNCTION("""COMPUTED_VALUE"""),"KMC 5825 AKPFPV0032") -> KMC 5825 AKPFPV0032 | J17: =IFERROR(__xludf.DUMMYFUNCTION("""COMPUTED_VALUE"""),"PTS100039") -> PTS100039 | K17: =IFERROR(__xludf.DUMMYFUNCTION("""COMPUTED_VALUE"""),"R-SERIES 007 PH") -> R-SERIES 007 PH | L17: =IFERROR(__xludf.DUMMYFUNCTION("""COMPUTED_VALUE"""),"WR LSGW 0016") -> WR LSGW 0016 | M17: =IFERROR(__xludf.DUMMYFUNCTION("""COMPUTED_VALUE"""),"WR WDP 0016") -> WR WDP 0016 | O17: =IFERROR(__xludf.DUMMYFUNCTION("""COMPUTED_VALUE"""),"Mapaya") -> Mapaya | P17: =IFERROR(__xludf.DUMMYFUNCTION("""COMPUTED_VALUE"""),"San Jose") -> San Jose | Q17: =IFERROR(__xludf.DUMMYFUNCTION("""COMPUTED_VALUE"""),"Occidental Mindoro") -> Occidental Mindoro | R17: =IFERROR(__xludf.DUMMYFUNCTION("""COMPUTED_VALUE"""),"4B") -> 4B
A18: =IFERROR(__xludf.DUMMYFUNCTION("""COMPUTED_VALUE"""),16.0) -> 16 | B18: =IFERROR(__xludf.DUMMYFUNCTION("""COMPUTED_VALUE"""),"NAGKAKAISANG LAKAS MULTI-PURPOSE COOPERATIVE") -> NAGKAKAISANG LAKAS MULTI-PURPOSE COOPERATIVE | C18: =IFERROR(__xludf.DUMMYFUNCTION("""COMPUTED_VALUE"""),"LABANGAN POBLACION, SAN JOSE, OCCIDENTAL MINDORO") -> LABANGAN POBLACION, SAN JOSE, OCCIDENTAL MINDORO | D18: =IFERROR(__xludf.DUMMYFUNCTION("""COMPUTED_VALUE"""),"Josephine Mallari") -> Josephine Mallari | E18: =IFERROR(__xludf.DUMMYFUNCTION("""COMPUTED_VALUE"""),"(0917) 839 4280") -> (0917) 839 4280 | F18: =IFERROR(__xludf.DUMMYFUNCTION("""COMPUTED_VALUE"""),"RCEF 23-08-20 Rebidding") -> RCEF 23-08-20 Rebidding | G18: =IFERROR(__xludf.DUMMYFUNCTION("""COMPUTED_VALUE"""),1.0) -> 1 | H18: =IFERROR(__xludf.DUMMYFUNCTION("""COMPUTED_VALUE"""),16782.0) -> 16782 | I18: =IFERROR(__xludf.DUMMYFUNCTION("""COMPUTED_VALUE"""),"KMC 5825 AKPFPV0029") -> KMC 5825 AKPFPV0029 | J18: =IFERROR(__xludf.DUMMYFUNCTION("""COMPUTED_VALUE"""),"PTS100022") -> PTS100022 | K18: =IFERROR(__xludf.DUMMYFUNCTION("""COMPUTED_VALUE"""),"R-SERIES 025 PH") -> R-SERIES 025 PH | L18: =IFERROR(__xludf.DUMMYFUNCTION("""COMPUTED_VALUE"""),"WR LSGW 0017") -> WR LSGW 0017 | M18: =IFERROR(__xludf.DUMMYFUNCTION("""COMPUTED_VALUE"""),"WR WDP 0017") -> WR WDP 0017 | O18: =IFERROR(__xludf.DUMMYFUNCTION("""COMPUTED_VALUE"""),"Labangan Poblacion") -> Labangan Poblacion | P18: =IFERROR(__xludf.DUMMYFUNCTION("""COMPUTED_VALUE"""),"San Jose") -> San Jose | Q18: =IFERROR(__xludf.DUMMYFUNCTION("""COMPUTED_VALUE"""),"Occidental Mindoro") -> Occidental Mindoro | R18: =IFERROR(__xludf.DUMMYFUNCTION("""COMPUTED_VALUE"""),"4B") -> 4B
A19: =IFERROR(__xludf.DUMMYFUNCTION("""COMPUTED_VALUE"""),17.0) -> 17 | B19: =IFERROR(__xludf.DUMMYFUNCTION("""COMPUTED_VALUE"""),"GINTONG BUTIL FARMERS ASSOCIATION") -> GINTONG BUTIL FARMERS ASSOCIATION | C19: =IFERROR(__xludf.DUMMYFUNCTION("""COMPUTED_VALUE"""),"PINAGTURIHAN, SANTA CRUZ, OCCIDENTAL MINDORO") -> PINAGTURIHAN, SANTA CRUZ, OCCIDENTAL MINDORO | D19: =IFERROR(__xludf.DUMMYFUNCTION("""COMPUTED_VALUE"""),"Rodolfo Patal, Jr.") -> Rodolfo Patal, Jr. | E19: =IFERROR(__xludf.DUMMYFUNCTION("""COMPUTED_VALUE"""),"0935-879-0354") -> 0935-879-0354 | F19: =IFERROR(__xludf.DUMMYFUNCTION("""COMPUTED_VALUE"""),"RCEF 23-08-20 Rebidding") -> RCEF 23-08-20 Rebidding | G19: =IFERROR(__xludf.DUMMYFUNCTION("""COMPUTED_VALUE"""),1.0) -> 1 | H19: =IFERROR(__xludf.DUMMYFUNCTION("""COMPUTED_VALUE"""),16783.0) -> 16783 | I19: =IFERROR(__xludf.DUMMYFUNCTION("""COMPUTED_VALUE"""),"KMC 5825 AEPFPV0019") -> KMC 5825 AEPFPV0019 | J19: =IFERROR(__xludf.DUMMYFUNCTION("""COMPUTED_VALUE"""),"PTS100040") -> PTS100040 | K19: =IFERROR(__xludf.DUMMYFUNCTION("""COMPUTED_VALUE"""),"R-SERIES 011 PH") -> R-SERIES 011 PH | L19: =IFERROR(__xludf.DUMMYFUNCTION("""COMPUTED_VALUE"""),"WR LSGW 0018") -> WR LSGW 0018 | M19: =IFERROR(__xludf.DUMMYFUNCTION("""COMPUTED_VALUE"""),"WR WDP 0018") -> WR WDP 0018 | O19: =IFERROR(__xludf.DUMMYFUNCTION("""COMPUTED_VALUE"""),"Pinagturihan") -> Pinagturihan | P19: =IFERROR(__xludf.DUMMYFUNCTION("""COMPUTED_VALUE"""),"Santa Cruz") -> Santa Cruz | Q19: =IFERROR(__xludf.DUMMYFUNCTION("""COMPUTED_VALUE"""),"Occidental Mindoro") -> Occidental Mindoro | R19: =IFERROR(__xludf.DUMMYFUNCTION("""COMPUTED_VALUE"""),"4B") -> 4B
A20: =IFERROR(__xludf.DUMMYFUNCTION("""COMPUTED_VALUE"""),18.0) -> 18 | B20: =IFERROR(__xludf.DUMMYFUNCTION("""COMPUTED_VALUE"""),"MUNICIPAL LOCAL GOVERNMENT UNIT OF RIZAL") -> MUNICIPAL LOCAL GOVERNMENT UNIT OF RIZAL | C20: =IFERROR(__xludf.DUMMYFUNCTION("""COMPUTED_VALUE"""),"RUMBANG, RIZAL, OCCIDENTAL MINDORO") -> RUMBANG, RIZAL, OCCIDENTAL MINDORO | D20: =IFERROR(__xludf.DUMMYFUNCTION("""COMPUTED_VALUE"""),"#N/A") -> #N/A | E20: =IFERROR(__xludf.DUMMYFUNCTION("""COMPUTED_VALUE"""),"#N/A") -> #N/A | F20: =IFERROR(__xludf.DUMMYFUNCTION("""COMPUTED_VALUE"""),"RCEF 23-08-20 Rebidding") -> RCEF 23-08-20 Rebidding | G20: =IFERROR(__xludf.DUMMYFUNCTION("""COMPUTED_VALUE"""),1.0) -> 1 | H20: =IFERROR(__xludf.DUMMYFUNCTION("""COMPUTED_VALUE"""),16786.0) -> 16786 | I20: =IFERROR(__xludf.DUMMYFUNCTION("""COMPUTED_VALUE"""),"KMC 5825 AJPFPV0002") -> KMC 5825 AJPFPV0002 | J20: =IFERROR(__xludf.DUMMYFUNCTION("""COMPUTED_VALUE"""),"PTS100018") -> PTS100018 | K20: =IFERROR(__xludf.DUMMYFUNCTION("""COMPUTED_VALUE"""),"R-SERIES 003 PH") -> R-SERIES 003 PH | L20: =IFERROR(__xludf.DUMMYFUNCTION("""COMPUTED_VALUE"""),"WR LSGW 0008") -> WR LSGW 0008 | M20: =IFERROR(__xludf.DUMMYFUNCTION("""COMPUTED_VALUE"""),"WR WDP 0008") -> WR WDP 0008 | O20: =IFERROR(__xludf.DUMMYFUNCTION("""COMPUTED_VALUE"""),"Rumbang") -> Rumbang | P20: =IFERROR(__xludf.DUMMYFUNCTION("""COMPUTED_VALUE"""),"Rizal") -> Rizal | Q20: =IFERROR(__xludf.DUMMYFUNCTION("""COMPUTED_VALUE"""),"Occidental Mindoro") -> Occidental Mindoro | R20: =IFERROR(__xludf.DUMMYFUNCTION("""COMPUTED_VALUE"""),"4B") -> 4B
A21: =IFERROR(__xludf.DUMMYFUNCTION("""COMPUTED_VALUE"""),19.0) -> 19 | B21: =IFERROR(__xludf.DUMMYFUNCTION("""COMPUTED_VALUE"""),"MALAPAD FARMERS ASSOCIATION") -> MALAPAD FARMERS ASSOCIATION | C21: =IFERROR(__xludf.DUMMYFUNCTION("""COMPUTED_VALUE"""),"Malapad, Baco, Oriental Mindoro") -> Malapad, Baco, Oriental Mindoro | D21: =IFERROR(__xludf.DUMMYFUNCTION("""COMPUTED_VALUE"""),"ROLANDO MANDITA") -> ROLANDO MANDITA | E21: =IFERROR(__xludf.DUMMYFUNCTION("""COMPUTED_VALUE"""),"0955 378 7221") -> 0955 378 7221 | F21: =IFERROR(__xludf.DUMMYFUNCTION("""COMPUTED_VALUE"""),"RCEF 23-08-20 Rebidding") -> RCEF 23-08-20 Rebidding | G21: =IFERROR(__xludf.DUMMYFUNCTION("""COMPUTED_VALUE"""),1.0) -> 1 | H21: =IFERROR(__xludf.DUMMYFUNCTION("""COMPUTED_VALUE"""),17379.0) -> 17379 | I21: =IFERROR(__xludf.DUMMYFUNCTION("""COMPUTED_VALUE"""),"KMC 5825 AAPFPV0005") -> KMC 5825 AAPFPV0005 | J21: =IFERROR(__xludf.DUMMYFUNCTION("""COMPUTED_VALUE"""),"PTS100012") -> PTS100012 | K21: =IFERROR(__xludf.DUMMYFUNCTION("""COMPUTED_VALUE"""),"R-SERIES 028 PH") -> R-SERIES 028 PH | L21: =IFERROR(__xludf.DUMMYFUNCTION("""COMPUTED_VALUE"""),"LSGW1750-RMP-2312036") -> LSGW1750-RMP-2312036 | M21: =IFERROR(__xludf.DUMMYFUNCTION("""COMPUTED_VALUE"""),"WDP40-RMP-2312069") -> WDP40-RMP-2312069 | O21: =IFERROR(__xludf.DUMMYFUNCTION("""COMPUTED_VALUE"""),"Malapad") -> Malapad | P21: =IFERROR(__xludf.DUMMYFUNCTION("""COMPUTED_VALUE"""),"Baco") -> Baco | Q21: =IFERROR(__xludf.DUMMYFUNCTION("""COMPUTED_VALUE"""),"Oriental Mindoro") -> Oriental Mindoro | R21: =IFERROR(__xludf.DUMMYFUNCTION("""COMPUTED_VALUE"""),"4B") -> 4B
A22: =IFERROR(__xludf.DUMMYFUNCTION("""COMPUTED_VALUE"""),20.0) -> 20 | B22: =IFERROR(__xludf.DUMMYFUNCTION("""COMPUTED_VALUE"""),"SAMAHAN NG MGA MAGSASAKA NG BARANGAY BAYANAN II") -> SAMAHAN NG MGA MAGSASAKA NG BARANGAY BAYANAN II | C22: =IFERROR(__xludf.DUMMYFUNCTION("""COMPUTED_VALUE"""),"Bayanan II, Calapan City, Oriental Mindoro") -> Bayanan II, Calapan City, Oriental Mindoro | D22: =IFERROR(__xludf.DUMMYFUNCTION("""COMPUTED_VALUE"""),"EDGAR C. BALMES") -> EDGAR C. BALMES | E22: =IFERROR(__xludf.DUMMYFUNCTION("""COMPUTED_VALUE"""),"0936 940 1320") -> 0936 940 1320 | F22: =IFERROR(__xludf.DUMMYFUNCTION("""COMPUTED_VALUE"""),"RCEF 23-08-20 Rebidding") -> RCEF 23-08-20 Rebidding | G22: =IFERROR(__xludf.DUMMYFUNCTION("""COMPUTED_VALUE"""),1.0) -> 1 | H22: =IFERROR(__xludf.DUMMYFUNCTION("""COMPUTED_VALUE"""),17380.0) -> 17380 | I22: =IFERROR(__xludf.DUMMYFUNCTION("""COMPUTED_VALUE"""),"KMC 5825 AVPFPV0035") -> KMC 5825 AVPFPV0035 | J22: =IFERROR(__xludf.DUMMYFUNCTION("""COMPUTED_VALUE"""),"PTS100034") -> PTS100034 | K22: =IFERROR(__xludf.DUMMYFUNCTION("""COMPUTED_VALUE"""),"R-SERIES 013 PH") -> R-SERIES 013 PH | L22: =IFERROR(__xludf.DUMMYFUNCTION("""COMPUTED_VALUE"""),"LSGW1750-RMP-2312024") -> LSGW1750-RMP-2312024 | M22: =IFERROR(__xludf.DUMMYFUNCTION("""COMPUTED_VALUE"""),"WDP40-RMP-2312072") -> WDP40-RMP-2312072 | O22: =IFERROR(__xludf.DUMMYFUNCTION("""COMPUTED_VALUE"""),"Bayanan Ii") -> Bayanan Ii | P22: =IFERROR(__xludf.DUMMYFUNCTION("""COMPUTED_VALUE"""),"Calapan City") -> Calapan City | Q22: =IFERROR(__xludf.DUMMYFUNCTION("""COMPUTED_VALUE"""),"Oriental Mindoro") -> Oriental Mindoro | R22: =IFERROR(__xludf.DUMMYFUNCTION("""COMPUTED_VALUE"""),"4B") -> 4B
A23: =IFERROR(__xludf.DUMMYFUNCTION("""COMPUTED_VALUE"""),21.0) -> 21 | B23: =IFERROR(__xludf.DUMMYFUNCTION("""COMPUTED_VALUE"""),"GULOD FARMERS ASSOCIATION") -> GULOD FARMERS ASSOCIATION | C23: =IFERROR(__xludf.DUMMYFUNCTION("""COMPUTED_VALUE"""),"Gulod, Calapan City, Oriental Mindoro") -> Gulod, Calapan City, Oriental Mindoro | D23: =IFERROR(__xludf.DUMMYFUNCTION("""COMPUTED_VALUE"""),"CELEDONIO GONZALES") -> CELEDONIO GONZALES | E23: =IFERROR(__xludf.DUMMYFUNCTION("""COMPUTED_VALUE"""),"0960 919 4546 0915 389 7698") -> 0960 919 4546 0915 389 7698 | F23: =IFERROR(__xludf.DUMMYFUNCTION("""COMPUTED_VALUE"""),"RCEF 23-08-20 Rebidding") -> RCEF 23-08-20 Rebidding | G23: =IFERROR(__xludf.DUMMYFUNCTION("""COMPUTED_VALUE"""),1.0) -> 1 | H23: =IFERROR(__xludf.DUMMYFUNCTION("""COMPUTED_VALUE"""),17381.0) -> 17381 | I23: =IFERROR(__xludf.DUMMYFUNCTION("""COMPUTED_VALUE"""),"KMC 5825 ACPFPV0009") -> KMC 5825 ACPFPV0009 | J23: =IFERROR(__xludf.DUMMYFUNCTION("""COMPUTED_VALUE"""),"PTS100006") -> PTS100006 | K23: =IFERROR(__xludf.DUMMYFUNCTION("""COMPUTED_VALUE"""),"R-SERIES 042 PH") -> R-SERIES 042 PH | L23: =IFERROR(__xludf.DUMMYFUNCTION("""COMPUTED_VALUE"""),"LSGW1750-RMP-2312016") -> LSGW1750-RMP-2312016 | M23: =IFERROR(__xludf.DUMMYFUNCTION("""COMPUTED_VALUE"""),"WDP40-RMP-2312053") -> WDP40-RMP-2312053 | O23: =IFERROR(__xludf.DUMMYFUNCTION("""COMPUTED_VALUE"""),"Gulod") -> Gulod | P23: =IFERROR(__xludf.DUMMYFUNCTION("""COMPUTED_VALUE"""),"Calapan City") -> Calapan City | Q23: =IFERROR(__xludf.DUMMYFUNCTION("""COMPUTED_VALUE"""),"Oriental Mindoro") -> Oriental Mindoro | R23: =IFERROR(__xludf.DUMMYFUNCTION("""COMPUTED_VALUE"""),"4B") -> 4B
A24: =IFERROR(__xludf.DUMMYFUNCTION("""COMPUTED_VALUE"""),22.0) -> 22 | B24: =IFERROR(__xludf.DUMMYFUNCTION("""COMPUTED_VALUE"""),"BALINGAYAN FARMERS ASSOCIATION") -> BALINGAYAN FARMERS ASSOCIATION | C24: =IFERROR(__xludf.DUMMYFUNCTION("""COMPUTED_VALUE"""),"Balingayan, Calapan City, Oriental Mindoro") -> Balingayan, Calapan City, Oriental Mindoro | D24: =IFERROR(__xludf.DUMMYFUNCTION("""COMPUTED_VALUE"""),"C ROBERTO S. BRUCAL") -> C ROBERTO S. BRUCAL | E24: =IFERROR(__xludf.DUMMYFUNCTION("""COMPUTED_VALUE"""),"0917 270 7772 0968 622 4404") -> 0917 270 7772 0968 622 4404 | F24: =IFERROR(__xludf.DUMMYFUNCTION("""COMPUTED_VALUE"""),"RCEF 23-08-20 Rebidding") -> RCEF 23-08-20 Rebidding | G24: =IFERROR(__xludf.DUMMYFUNCTION("""COMPUTED_VALUE"""),1.0) -> 1 | H24: =IFERROR(__xludf.DUMMYFUNCTION("""COMPUTED_VALUE"""),17382.0) -> 17382 | I24: =IFERROR(__xludf.DUMMYFUNCTION("""COMPUTED_VALUE"""),"KMC 5825 AHPFPV0007") -> KMC 5825 AHPFPV0007 | J24: =IFERROR(__xludf.DUMMYFUNCTION("""COMPUTED_VALUE"""),"PTS100008") -> PTS100008 | K24: =IFERROR(__xludf.DUMMYFUNCTION("""COMPUTED_VALUE"""),"R-SERIES 021 PH") -> R-SERIES 021 PH | L24: =IFERROR(__xludf.DUMMYFUNCTION("""COMPUTED_VALUE"""),"LSGW1750-RMP-2312014") -> LSGW1750-RMP-2312014 | M24: =IFERROR(__xludf.DUMMYFUNCTION("""COMPUTED_VALUE"""),"WDP40-RMP-2312056") -> WDP40-RMP-2312056 | O24: =IFERROR(__xludf.DUMMYFUNCTION("""COMPUTED_VALUE"""),"Balingayan") -> Balingayan | P24: =IFERROR(__xludf.DUMMYFUNCTION("""COMPUTED_VALUE"""),"Calapan City") -> Calapan City | Q24: =IFERROR(__xludf.DUMMYFUNCTION("""COMPUTED_VALUE"""),"Oriental Mindoro") -> Oriental Mindoro | R24: =IFERROR(__xludf.DUMMYFUNCTION("""COMPUTED_VALUE"""),"4B") -> 4B
A25: =IFERROR(__xludf.DUMMYFUNCTION("""COMPUTED_VALUE"""),23.0) -> 23 | B25: =IFERROR(__xludf.DUMMYFUNCTION("""COMPUTED_VALUE"""),"BARANGAY MALINAO FARMERS' ASSOCIATION") -> BARANGAY MALINAO FARMERS' ASSOCIATION | C25: =IFERROR(__xludf.DUMMYFUNCTION("""COMPUTED_VALUE"""),"Malinao, Naujan, Oriental Mindoro") -> Malinao, Naujan, Oriental Mindoro | D25: =IFERROR(__xludf.DUMMYFUNCTION("""COMPUTED_VALUE"""),"ERVIN D. GARILLO") -> ERVIN D. GARILLO | E25: =IFERROR(__xludf.DUMMYFUNCTION("""COMPUTED_VALUE"""),"0956 911 1213") -> 0956 911 1213 | F25: =IFERROR(__xludf.DUMMYFUNCTION("""COMPUTED_VALUE"""),"RCEF 23-08-20 Rebidding") -> RCEF 23-08-20 Rebidding | G25: =IFERROR(__xludf.DUMMYFUNCTION("""COMPUTED_VALUE"""),1.0) -> 1 | H25: =IFERROR(__xludf.DUMMYFUNCTION("""COMPUTED_VALUE"""),17383.0) -> 17383 | I25: =IFERROR(__xludf.DUMMYFUNCTION("""COMPUTED_VALUE"""),"KMC 5825 ACPFPV0012") -> KMC 5825 ACPFPV0012 | J25: =IFERROR(__xludf.DUMMYFUNCTION("""COMPUTED_VALUE"""),"PTS100019") -> PTS100019 | K25: =IFERROR(__xludf.DUMMYFUNCTION("""COMPUTED_VALUE"""),"R-SERIES 049 PH") -> R-SERIES 049 PH | L25: =IFERROR(__xludf.DUMMYFUNCTION("""COMPUTED_VALUE"""),"LSGW1750-RMP-2312003") -> LSGW1750-RMP-2312003 | M25: =IFERROR(__xludf.DUMMYFUNCTION("""COMPUTED_VALUE"""),"WDP40-RMP-2312063") -> WDP40-RMP-2312063 | O25: =IFERROR(__xludf.DUMMYFUNCTION("""COMPUTED_VALUE"""),"Malinao") -> Malinao | P25: =IFERROR(__xludf.DUMMYFUNCTION("""COMPUTED_VALUE"""),"Naujan") -> Naujan | Q25: =IFERROR(__xludf.DUMMYFUNCTION("""COMPUTED_VALUE"""),"Oriental Mindoro") -> Oriental Mindoro | R25: =IFERROR(__xludf.DUMMYFUNCTION("""COMPUTED_VALUE"""),"4B") -> 4B
A26: =IFERROR(__xludf.DUMMYFUNCTION("""COMPUTED_VALUE"""),24.0) -> 24 | B26: =IFERROR(__xludf.DUMMYFUNCTION("""COMPUTED_VALUE"""),"BAGONG BUHAY FARMERS ASSOCIATION") -> BAGONG BUHAY FARMERS ASSOCIATION | C26: =IFERROR(__xludf.DUMMYFUNCTION("""COMPUTED_VALUE"""),"Bagong Buhay, naujan, Oriental Mindoro") -> Bagong Buhay, naujan, Oriental Mindoro | D26: =IFERROR(__xludf.DUMMYFUNCTION("""COMPUTED_VALUE"""),"ERLIN G. PARAY") -> ERLIN G. PARAY | E26: =IFERROR(__xludf.DUMMYFUNCTION("""COMPUTED_VALUE"""),"0907 645 9942") -> 0907 645 9942 | F26: =IFERROR(__xludf.DUMMYFUNCTION("""COMPUTED_VALUE"""),"RCEF 23-08-20 Rebidding") -> RCEF 23-08-20 Rebidding | G26: =IFERROR(__xludf.DUMMYFUNCTION("""COMPUTED_VALUE"""),1.0) -> 1 | H26: =IFERROR(__xludf.DUMMYFUNCTION("""COMPUTED_VALUE"""),17384.0) -> 17384 | I26: =IFERROR(__xludf.DUMMYFUNCTION("""COMPUTED_VALUE"""),"KMC 5825 AHPFPV0038") -> KMC 5825 AHPFPV0038 | J26: =IFERROR(__xludf.DUMMYFUNCTION("""COMPUTED_VALUE"""),"PTS100003") -> PTS100003 | K26: =IFERROR(__xludf.DUMMYFUNCTION("""COMPUTED_VALUE"""),"R-SERIES 034 PH") -> R-SERIES 034 PH | L26: =IFERROR(__xludf.DUMMYFUNCTION("""COMPUTED_VALUE"""),"LSGW1750-RMP-2312034") -> LSGW1750-RMP-2312034 | M26: =IFERROR(__xludf.DUMMYFUNCTION("""COMPUTED_VALUE"""),"WDP40-RMP-2312062") -> WDP40-RMP-2312062 | O26: =IFERROR(__xludf.DUMMYFUNCTION("""COMPUTED_VALUE"""),"Bagong Buhay") -> Bagong Buhay | P26: =IFERROR(__xludf.DUMMYFUNCTION("""COMPUTED_VALUE"""),"Naujan") -> Naujan | Q26: =IFERROR(__xludf.DUMMYFUNCTION("""COMPUTED_VALUE"""),"Oriental Mindoro") -> Oriental Mindoro | R26: =IFERROR(__xludf.DUMMYFUNCTION("""COMPUTED_VALUE"""),"4B") -> 4B
A27: =IFERROR(__xludf.DUMMYFUNCTION("""COMPUTED_VALUE"""),25.0) -> 25 | B27: =IFERROR(__xludf.DUMMYFUNCTION("""COMPUTED_VALUE"""),"SANDIGAN NG MGA MANGGAGAWA SA AGRIKULTURA SA KANAYUNAN (SAMAKA)") -> SANDIGAN NG MGA MANGGAGAWA SA AGRIKULTURA SA KANAYUNAN (SAMAKA) | C27: =IFERROR(__xludf.DUMMYFUNCTION("""COMPUTED_VALUE"""),"Calucmoy, Socorro, Oriental Mindoro") -> Calucmoy, Socorro, Oriental Mindoro | D27: =IFERROR(__xludf.DUMMYFUNCTION("""COMPUTED_VALUE"""),"Edilberto Saez") -> Edilberto Saez | E27: =IFERROR(__xludf.DUMMYFUNCTION("""COMPUTED_VALUE"""),"0948 412 7045") -> 0948 412 7045 | F27: =IFERROR(__xludf.DUMMYFUNCTION("""COMPUTED_VALUE"""),"RCEF 23-08-20 Rebidding") -> RCEF 23-08-20 Rebidding | G27: =IFERROR(__xludf.DUMMYFUNCTION("""COMPUTED_VALUE"""),1.0) -> 1 | H27: =IFERROR(__xludf.DUMMYFUNCTION("""COMPUTED_VALUE"""),17385.0) -> 17385 | I27: =IFERROR(__xludf.DUMMYFUNCTION("""COMPUTED_VALUE"""),"KMC 5825 AVPFPV0018") -> KMC 5825 AVPFPV0018 | J27: =IFERROR(__xludf.DUMMYFUNCTION("""COMPUTED_VALUE"""),"PTS100037") -> PTS100037 | K27: =IFERROR(__xludf.DUMMYFUNCTION("""COMPUTED_VALUE"""),"R-SERIES 005 PH") -> R-SERIES 005 PH | L27: =IFERROR(__xludf.DUMMYFUNCTION("""COMPUTED_VALUE"""),"LSGW1750-RMP-2312012") -> LSGW1750-RMP-2312012 | M27: =IFERROR(__xludf.DUMMYFUNCTION("""COMPUTED_VALUE"""),"WDP40-RMP-2312057") -> WDP40-RMP-2312057 | O27: =IFERROR(__xludf.DUMMYFUNCTION("""COMPUTED_VALUE"""),"Calucmoy") -> Calucmoy | P27: =IFERROR(__xludf.DUMMYFUNCTION("""COMPUTED_VALUE"""),"Socorro") -> Socorro | Q27: =IFERROR(__xludf.DUMMYFUNCTION("""COMPUTED_VALUE"""),"Oriental Mindoro") -> Oriental Mindoro | R27: =IFERROR(__xludf.DUMMYFUNCTION("""COMPUTED_VALUE"""),"4B") -> 4B
A28: =IFERROR(__xludf.DUMMYFUNCTION("""COMPUTED_VALUE"""),26.0) -> 26 | B28: =IFERROR(__xludf.DUMMYFUNCTION("""COMPUTED_VALUE"""),"MACATOC FARMERS ASSOCIATION") -> MACATOC FARMERS ASSOCIATION | C28: =IFERROR(__xludf.DUMMYFUNCTION("""COMPUTED_VALUE"""),"Macatoc, Victoria, Oriental Mindoro") -> Macatoc, Victoria, Oriental Mindoro | D28: =IFERROR(__xludf.DUMMYFUNCTION("""COMPUTED_VALUE"""),"DENVER J. PERICO") -> DENVER J. PERICO | E28: =IFERROR(__xludf.DUMMYFUNCTION("""COMPUTED_VALUE"""),"0909 489 2967") -> 0909 489 2967 | F28: =IFERROR(__xludf.DUMMYFUNCTION("""COMPUTED_VALUE"""),"RCEF 23-08-20 Rebidding") -> RCEF 23-08-20 Rebidding | G28: =IFERROR(__xludf.DUMMYFUNCTION("""COMPUTED_VALUE"""),1.0) -> 1 | H28: =IFERROR(__xludf.DUMMYFUNCTION("""COMPUTED_VALUE"""),17386.0) -> 17386 | I28: =IFERROR(__xludf.DUMMYFUNCTION("""COMPUTED_VALUE"""),"KMC 5825 ALPFPV0040") -> KMC 5825 ALPFPV0040 | J28: =IFERROR(__xludf.DUMMYFUNCTION("""COMPUTED_VALUE"""),"PTS100011") -> PTS100011 | K28: =IFERROR(__xludf.DUMMYFUNCTION("""COMPUTED_VALUE"""),"R-SERIES 018 PH") -> R-SERIES 018 PH | L28: =IFERROR(__xludf.DUMMYFUNCTION("""COMPUTED_VALUE"""),"LSGW1750-RMP-2312002") -> LSGW1750-RMP-2312002 | M28: =IFERROR(__xludf.DUMMYFUNCTION("""COMPUTED_VALUE"""),"WDP40-RMP-2312058") -> WDP40-RMP-2312058 | O28: =IFERROR(__xludf.DUMMYFUNCTION("""COMPUTED_VALUE"""),"Macatoc") -> Macatoc | P28: =IFERROR(__xludf.DUMMYFUNCTION("""COMPUTED_VALUE"""),"Victoria") -> Victoria | Q28: =IFERROR(__xludf.DUMMYFUNCTION("""COMPUTED_VALUE"""),"Oriental Mindoro") -> Oriental Mindoro | R28: =IFERROR(__xludf.DUMMYFUNCTION("""COMPUTED_VALUE"""),"4B") -> 4B
A29: =IFERROR(__xludf.DUMMYFUNCTION("""COMPUTED_VALUE"""),27.0) -> 27 | B29: =IFERROR(__xludf.DUMMYFUNCTION("""COMPUTED_VALUE"""),"SAN NICOLAS SMALL WATER IRRIGATION SYSTEM ASSOCIATION") -> SAN NICOLAS SMALL WATER IRRIGATION SYSTEM ASSOCIATION | C29: =IFERROR(__xludf.DUMMYFUNCTION("""COMPUTED_VALUE"""),"Rosacara, Bansud, Oriental Mindoro") -> Rosacara, Bansud, Oriental Mindoro | D29: =IFERROR(__xludf.DUMMYFUNCTION("""COMPUTED_VALUE"""),"EDGARDO M. CASAPAO") -> EDGARDO M. CASAPAO | E29: =IFERROR(__xludf.DUMMYFUNCTION("""COMPUTED_VALUE"""),9.071476723E9) -> 9071476723 | F29: =IFERROR(__xludf.DUMMYFUNCTION("""COMPUTED_VALUE"""),"RCEF 23-08-20 Rebidding") -> RCEF 23-08-20 Rebidding | G29: =IFERROR(__xludf.DUMMYFUNCTION("""COMPUTED_VALUE"""),1.0) -> 1 | H29: =IFERROR(__xludf.DUMMYFUNCTION("""COMPUTED_VALUE"""),17387.0) -> 17387 | I29: =IFERROR(__xludf.DUMMYFUNCTION("""COMPUTED_VALUE"""),"KMC 5825 APPFPV0028") -> KMC 5825 APPFPV0028 | J29: =IFERROR(__xludf.DUMMYFUNCTION("""COMPUTED_VALUE"""),"PTS100021") -> PTS100021 | K29: =IFERROR(__xludf.DUMMYFUNCTION("""COMPUTED_VALUE"""),"R-SERIES 025 PH") -> R-SERIES 025 PH | L29: =IFERROR(__xludf.DUMMYFUNCTION("""COMPUTED_VALUE"""),"LSGW1750-RMP-2312027") -> LSGW1750-RMP-2312027 | M29: =IFERROR(__xludf.DUMMYFUNCTION("""COMPUTED_VALUE"""),"WDP40-RMP-2312038") -> WDP40-RMP-2312038 | O29: =IFERROR(__xludf.DUMMYFUNCTION("""COMPUTED_VALUE"""),"Rosacara") -> Rosacara | P29: =IFERROR(__xludf.DUMMYFUNCTION("""COMPUTED_VALUE"""),"Bansud") -> Bansud | Q29: =IFERROR(__xludf.DUMMYFUNCTION("""COMPUTED_VALUE"""),"Oriental Mindoro") -> Oriental Mindoro | R29: =IFERROR(__xludf.DUMMYFUNCTION("""COMPUTED_VALUE"""),"4B") -> 4B
A30: =IFERROR(__xludf.DUMMYFUNCTION("""COMPUTED_VALUE"""),28.0) -> 28 | B30: =IFERROR(__xludf.DUMMYFUNCTION("""COMPUTED_VALUE"""),"ALCADESMA GROUP OF FARMERS ASSOCIATION(AGFA)") -> ALCADESMA GROUP OF FARMERS ASSOCIATION(AGFA) | C30: =IFERROR(__xludf.DUMMYFUNCTION("""COMPUTED_VALUE"""),"Alcadesma, Bansud, Oriental Mindoro") -> Alcadesma, Bansud, Oriental Mindoro | D30: =IFERROR(__xludf.DUMMYFUNCTION("""COMPUTED_VALUE"""),"ROMEO R. YAP") -> ROMEO R. YAP | E30: =IFERROR(__xludf.DUMMYFUNCTION("""COMPUTED_VALUE"""),"0920 540 2742") -> 0920 540 2742 | F30: =IFERROR(__xludf.DUMMYFUNCTION("""COMPUTED_VALUE"""),"RCEF 23-08-20 Rebidding") -> RCEF 23-08-20 Rebidding | G30: =IFERROR(__xludf.DUMMYFUNCTION("""COMPUTED_VALUE"""),1.0) -> 1 | H30: =IFERROR(__xludf.DUMMYFUNCTION("""COMPUTED_VALUE"""),17388.0) -> 17388 | I30: =IFERROR(__xludf.DUMMYFUNCTION("""COMPUTED_VALUE"""),"KMC 5825 ACPFPV0020") -> KMC 5825 ACPFPV0020 | J30: =IFERROR(__xludf.DUMMYFUNCTION("""COMPUTED_VALUE"""),"PTS100036") -> PTS100036 | K30: =IFERROR(__xludf.DUMMYFUNCTION("""COMPUTED_VALUE"""),"R-SERIES 012 PH") -> R-SERIES 012 PH | L30: =IFERROR(__xludf.DUMMYFUNCTION("""COMPUTED_VALUE"""),"LSGW1750-RMP-2312013") -> LSGW1750-RMP-2312013 | M30: =IFERROR(__xludf.DUMMYFUNCTION("""COMPUTED_VALUE"""),"WDP40-RMP-2312049") -> WDP40-RMP-2312049 | O30: =IFERROR(__xludf.DUMMYFUNCTION("""COMPUTED_VALUE"""),"Alcadesma") -> Alcadesma | P30: =IFERROR(__xludf.DUMMYFUNCTION("""COMPUTED_VALUE"""),"Bansud") -> Bansud | Q30: =IFERROR(__xludf.DUMMYFUNCTION("""COMPUTED_VALUE"""),"Oriental Mindoro") -> Oriental Mindoro | R30: =IFERROR(__xludf.DUMMYFUNCTION("""COMPUTED_VALUE"""),"4B") -> 4B
A31: =IFERROR(__xludf.DUMMYFUNCTION("""COMPUTED_VALUE"""),29.0) -> 29 | B31: =IFERROR(__xludf.DUMMYFUNCTION("""COMPUTED_VALUE"""),"A. BONIFACIO FARMERS ASSOCIATION") -> A. BONIFACIO FARMERS ASSOCIATION | C31: =IFERROR(__xludf.DUMMYFUNCTION("""COMPUTED_VALUE"""),"A. Bonifacio, Gloria, Oriental Mindoro") -> A. Bonifacio, Gloria, Oriental Mindoro | D31: =IFERROR(__xludf.DUMMYFUNCTION("""COMPUTED_VALUE"""),"GILBERT R. MALANOG") -> GILBERT R. MALANOG | E31: =IFERROR(__xludf.DUMMYFUNCTION("""COMPUTED_VALUE"""),"0912 838 9639") -> 0912 838 9639 | F31: =IFERROR(__xludf.DUMMYFUNCTION("""COMPUTED_VALUE"""),"RCEF 23-08-20 Rebidding") -> RCEF 23-08-20 Rebidding | G31: =IFERROR(__xludf.DUMMYFUNCTION("""COMPUTED_VALUE"""),1.0) -> 1 | H31: =IFERROR(__xludf.DUMMYFUNCTION("""COMPUTED_VALUE"""),17389.0) -> 17389 | I31: =IFERROR(__xludf.DUMMYFUNCTION("""COMPUTED_VALUE"""),"KMC 5825 ACPFPV0079") -> KMC 5825 ACPFPV0079 | J31: =IFERROR(__xludf.DUMMYFUNCTION("""COMPUTED_VALUE"""),"PTS100081") -> PTS100081 | K31: =IFERROR(__xludf.DUMMYFUNCTION("""COMPUTED_VALUE"""),"R-SERIES 020 PH") -> R-SERIES 020 PH | L31: =IFERROR(__xludf.DUMMYFUNCTION("""COMPUTED_VALUE"""),"LSGW1750-RMP-2312001") -> LSGW1750-RMP-2312001 | M31: =IFERROR(__xludf.DUMMYFUNCTION("""COMPUTED_VALUE"""),"WDP40-RMP-2312065") -> WDP40-RMP-2312065 | O31: =IFERROR(__xludf.DUMMYFUNCTION("""COMPUTED_VALUE"""),"A. Bonifacio") -> A. Bonifacio | P31: =IFERROR(__xludf.DUMMYFUNCTION("""COMPUTED_VALUE"""),"Gloria") -> Gloria | Q31: =IFERROR(__xludf.DUMMYFUNCTION("""COMPUTED_VALUE"""),"Oriental Mindoro") -> Oriental Mindoro | R31: =IFERROR(__xludf.DUMMYFUNCTION("""COMPUTED_VALUE"""),"4B") -> 4B
A32: =IFERROR(__xludf.DUMMYFUNCTION("""COMPUTED_VALUE"""),30.0) -> 30 | B32: =IFERROR(__xludf.DUMMYFUNCTION("""COMPUTED_VALUE"""),"BARANGAY NABUSLOT PINAMALAYAN FARMERS ASSOCIATION INC.") -> BARANGAY NABUSLOT PINAMALAYAN FARMERS ASSOCIATION INC. | C32: =IFERROR(__xludf.DUMMYFUNCTION("""COMPUTED_VALUE"""),"Nabuslot, Pinamalayan, Oriental Mindoro") -> Nabuslot, Pinamalayan, Oriental Mindoro | D32: =IFERROR(__xludf.DUMMYFUNCTION("""COMPUTED_VALUE"""),"NICANOR J. LUMALANG") -> NICANOR J. LUMALANG | E32: =IFERROR(__xludf.DUMMYFUNCTION("""COMPUTED_VALUE"""),"0917 563 3431") -> 0917 563 3431 | F32: =IFERROR(__xludf.DUMMYFUNCTION("""COMPUTED_VALUE"""),"RCEF 23-08-20 Rebidding") -> RCEF 23-08-20 Rebidding | G32: =IFERROR(__xludf.DUMMYFUNCTION("""COMPUTED_VALUE"""),1.0) -> 1 | H32: =IFERROR(__xludf.DUMMYFUNCTION("""COMPUTED_VALUE"""),17390.0) -> 17390 | I32: =IFERROR(__xludf.DUMMYFUNCTION("""COMPUTED_VALUE"""),"KMC 5825 AHPFPV0024") -> KMC 5825 AHPFPV0024 | J32: =IFERROR(__xludf.DUMMYFUNCTION("""COMPUTED_VALUE"""),"PTS100035") -> PTS100035 | K32: =IFERROR(__xludf.DUMMYFUNCTION("""COMPUTED_VALUE"""),"R-SERIES 017 PH") -> R-SERIES 017 PH | L32: =IFERROR(__xludf.DUMMYFUNCTION("""COMPUTED_VALUE"""),"LSGW1750-RMP-2312026") -> LSGW1750-RMP-2312026 | M32: =IFERROR(__xludf.DUMMYFUNCTION("""COMPUTED_VALUE"""),"WDP40-RMP-2312061") -> WDP40-RMP-2312061 | O32: =IFERROR(__xludf.DUMMYFUNCTION("""COMPUTED_VALUE"""),"Nabuslot") -> Nabuslot | P32: =IFERROR(__xludf.DUMMYFUNCTION("""COMPUTED_VALUE"""),"Pinamalayan") -> Pinamalayan | Q32: =IFERROR(__xludf.DUMMYFUNCTION("""COMPUTED_VALUE"""),"Oriental Mindoro") -> Oriental Mindoro | R32: =IFERROR(__xludf.DUMMYFUNCTION("""COMPUTED_VALUE"""),"4B") -> 4B
A33: =IFERROR(__xludf.DUMMYFUNCTION("""COMPUTED_VALUE"""),31.0) -> 31 | B33: =IFERROR(__xludf.DUMMYFUNCTION("""COMPUTED_VALUE"""),"CANTIL FARMERS ASSOCIATION") -> CANTIL FARMERS ASSOCIATION | C33: =IFERROR(__xludf.DUMMYFUNCTION("""COMPUTED_VALUE"""),"Cantil, Roxas, Oriental Mindoro") -> Cantil, Roxas, Oriental Mindoro | D33: =IFERROR(__xludf.DUMMYFUNCTION("""COMPUTED_VALUE"""),"ANGELO S. ANDRES") -> ANGELO S. ANDRES | E33: =IFERROR(__xludf.DUMMYFUNCTION("""COMPUTED_VALUE"""),"0938 348 2989") -> 0938 348 2989 | F33: =IFERROR(__xludf.DUMMYFUNCTION("""COMPUTED_VALUE"""),"RCEF 23-08-20 Rebidding") -> RCEF 23-08-20 Rebidding | G33: =IFERROR(__xludf.DUMMYFUNCTION("""COMPUTED_VALUE"""),1.0) -> 1 | H33: =IFERROR(__xludf.DUMMYFUNCTION("""COMPUTED_VALUE"""),17391.0) -> 17391 | I33: =IFERROR(__xludf.DUMMYFUNCTION("""COMPUTED_VALUE"""),"KMC 5825 AAPFPV0022") -> KMC 5825 AAPFPV0022 | J33: =IFERROR(__xludf.DUMMYFUNCTION("""COMPUTED_VALUE"""),"PTS100026") -> PTS100026 | K33: =IFERROR(__xludf.DUMMYFUNCTION("""COMPUTED_VALUE"""),"R-SERIES 024 PH") -> R-SERIES 024 PH | L33: =IFERROR(__xludf.DUMMYFUNCTION("""COMPUTED_VALUE"""),"LSGW1750-RMP-2312025") -> LSGW1750-RMP-2312025 | M33: =IFERROR(__xludf.DUMMYFUNCTION("""COMPUTED_VALUE"""),"WDP40-RMP-2312066") -> WDP40-RMP-2312066 | O33: =IFERROR(__xludf.DUMMYFUNCTION("""COMPUTED_VALUE"""),"Cantil") -> Cantil | P33: =IFERROR(__xludf.DUMMYFUNCTION("""COMPUTED_VALUE"""),"Roxas") -> Roxas | Q33: =IFERROR(__xludf.DUMMYFUNCTION("""COMPUTED_VALUE"""),"Oriental Mindoro") -> Oriental Mindoro | R33: =IFERROR(__xludf.DUMMYFUNCTION("""COMPUTED_VALUE"""),"4B") -> 4B
A34: =IFERROR(__xludf.DUMMYFUNCTION("""COMPUTED_VALUE"""),32.0) -> 32 | B34: =IFERROR(__xludf.DUMMYFUNCTION("""COMPUTED_VALUE"""),"BAGUMBAYAN ROXAS ORIENTAL MINDORO FARMERS ASSOCIATION") -> BAGUMBAYAN ROXAS ORIENTAL MINDORO FARMERS ASSOCIATION | C34: =IFERROR(__xludf.DUMMYFUNCTION("""COMPUTED_VALUE"""),"Bagumbayan, Roxas, Oriental Mindoro") -> Bagumbayan, Roxas, Oriental Mindoro | D34: =IFERROR(__xludf.DUMMYFUNCTION("""COMPUTED_VALUE"""),"GIOVANI A. GAA") -> GIOVANI A. GAA | E34: =IFERROR(__xludf.DUMMYFUNCTION("""COMPUTED_VALUE"""),"0930 479 0163") -> 0930 479 0163 | F34: =IFERROR(__xludf.DUMMYFUNCTION("""COMPUTED_VALUE"""),"RCEF 23-08-20 Rebidding") -> RCEF 23-08-20 Rebidding | G34: =IFERROR(__xludf.DUMMYFUNCTION("""COMPUTED_VALUE"""),1.0) -> 1 | H34: =IFERROR(__xludf.DUMMYFUNCTION("""COMPUTED_VALUE"""),17392.0) -> 17392 | I34: =IFERROR(__xludf.DUMMYFUNCTION("""COMPUTED_VALUE"""),"KMC 5825 ACPFPV0017") -> KMC 5825 ACPFPV0017 | J34: =IFERROR(__xludf.DUMMYFUNCTION("""COMPUTED_VALUE"""),"PTS100032") -> PTS100032 | K34: =IFERROR(__xludf.DUMMYFUNCTION("""COMPUTED_VALUE"""),"R-SERIES 001 PH") -> R-SERIES 001 PH | L34: =IFERROR(__xludf.DUMMYFUNCTION("""COMPUTED_VALUE"""),"LSGW1750-RMP-2312015") -> LSGW1750-RMP-2312015 | M34: =IFERROR(__xludf.DUMMYFUNCTION("""COMPUTED_VALUE"""),"WDP40-RMP-2312059") -> WDP40-RMP-2312059 | O34: =IFERROR(__xludf.DUMMYFUNCTION("""COMPUTED_VALUE"""),"Bagumbayan") -> Bagumbayan | P34: =IFERROR(__xludf.DUMMYFUNCTION("""COMPUTED_VALUE"""),"Roxas") -> Roxas | Q34: =IFERROR(__xludf.DUMMYFUNCTION("""COMPUTED_VALUE"""),"Oriental Mindoro") -> Oriental Mindoro | R34: =IFERROR(__xludf.DUMMYFUNCTION("""COMPUTED_VALUE"""),"4B") -> 4B
A35: =IFERROR(__xludf.DUMMYFUNCTION("""COMPUTED_VALUE"""),33.0) -> 33 | B35: =IFERROR(__xludf.DUMMYFUNCTION("""COMPUTED_VALUE"""),"Municipal Local Government Unit of Cavinti") -> Municipal Local Government Unit of Cavinti | C35: =IFERROR(__xludf.DUMMYFUNCTION("""COMPUTED_VALUE"""),"Poblacion, Cavinti, Laguna") -> Poblacion, Cavinti, Laguna | D35: =IFERROR(__xludf.DUMMYFUNCTION("""COMPUTED_VALUE"""),"Hon. Milbert L. Olivares") -> Hon. Milbert L. Olivares | E35: =IFERROR(__xludf.DUMMYFUNCTION("""COMPUTED_VALUE"""),"0919 002 7529") -> 0919 002 7529 | F35: =IFERROR(__xludf.DUMMYFUNCTION("""COMPUTED_VALUE"""),"RCEF 23-08-20 Rebidding") -> RCEF 23-08-20 Rebidding | G35: =IFERROR(__xludf.DUMMYFUNCTION("""COMPUTED_VALUE"""),1.0) -> 1 | H35: =IFERROR(__xludf.DUMMYFUNCTION("""COMPUTED_VALUE"""),17706.0) -> 17706 | I35: =IFERROR(__xludf.DUMMYFUNCTION("""COMPUTED_VALUE"""),"KMC 5825 ACPFPV0141") -> KMC 5825 ACPFPV0141 | J35: =IFERROR(__xludf.DUMMYFUNCTION("""COMPUTED_VALUE"""),"PTS100076") -> PTS100076 | K35: =IFERROR(__xludf.DUMMYFUNCTION("""COMPUTED_VALUE"""),"R-SERIES 002 PH") -> R-SERIES 002 PH | L35: =IFERROR(__xludf.DUMMYFUNCTION("""COMPUTED_VALUE"""),"LSGW1750-RMP-2312177") -> LSGW1750-RMP-2312177 | M35: =IFERROR(__xludf.DUMMYFUNCTION("""COMPUTED_VALUE"""),"WDP40-RMP-2312113") -> WDP40-RMP-2312113 | O35: =IFERROR(__xludf.DUMMYFUNCTION("""COMPUTED_VALUE"""),"Poblacion") -> Poblacion | P35: =IFERROR(__xludf.DUMMYFUNCTION("""COMPUTED_VALUE"""),"Cavinti") -> Cavinti | Q35: =IFERROR(__xludf.DUMMYFUNCTION("""COMPUTED_VALUE"""),"Laguna") -> Laguna | R35: =IFERROR(__xludf.DUMMYFUNCTION("""COMPUTED_VALUE"""),"4A") -> 4A
A36: =IFERROR(__xludf.DUMMYFUNCTION("""COMPUTED_VALUE"""),34.0) -> 34 | B36: =IFERROR(__xludf.DUMMYFUNCTION("""COMPUTED_VALUE"""),"Municipal Local Government Unit of Kalayaan") -> Municipal Local Government Unit of Kalayaan | C36: =IFERROR(__xludf.DUMMYFUNCTION("""COMPUTED_VALUE"""),"San Juan, Kalayaan, Laguna") -> San Juan, Kalayaan, Laguna | D36: =IFERROR(__xludf.DUMMYFUNCTION("""COMPUTED_VALUE"""),"Hon. Sandy P. Laganapan") -> Hon. Sandy P. Laganapan | E36: =IFERROR(__xludf.DUMMYFUNCTION("""COMPUTED_VALUE"""),"0926 242 9624") -> 0926 242 9624 | F36: =IFERROR(__xludf.DUMMYFUNCTION("""COMPUTED_VALUE"""),"RCEF 23-08-20 Rebidding") -> RCEF 23-08-20 Rebidding | G36: =IFERROR(__xludf.DUMMYFUNCTION("""COMPUTED_VALUE"""),1.0) -> 1 | H36: =IFERROR(__xludf.DUMMYFUNCTION("""COMPUTED_VALUE"""),17707.0) -> 17707 | I36: =IFERROR(__xludf.DUMMYFUNCTION("""COMPUTED_VALUE"""),"KMC 5825 AAPFPV0067") -> KMC 5825 AAPFPV0067 | J36: =IFERROR(__xludf.DUMMYFUNCTION("""COMPUTED_VALUE"""),"PTS100150") -> PTS100150 | K36: =IFERROR(__xludf.DUMMYFUNCTION("""COMPUTED_VALUE"""),"R-SERIES 008 PH") -> R-SERIES 008 PH | L36: =IFERROR(__xludf.DUMMYFUNCTION("""COMPUTED_VALUE"""),"LSGW1750-RMP-2312079") -> LSGW1750-RMP-2312079 | M36: =IFERROR(__xludf.DUMMYFUNCTION("""COMPUTED_VALUE"""),"WDP40-RMP-2312074") -> WDP40-RMP-2312074 | O36: =IFERROR(__xludf.DUMMYFUNCTION("""COMPUTED_VALUE"""),"San Juan") -> San Juan | P36: =IFERROR(__xludf.DUMMYFUNCTION("""COMPUTED_VALUE"""),"Kalayaan") -> Kalayaan | Q36: =IFERROR(__xludf.DUMMYFUNCTION("""COMPUTED_VALUE"""),"Laguna") -> Laguna | R36: =IFERROR(__xludf.DUMMYFUNCTION("""COMPUTED_VALUE"""),"4A") -> 4A
A37: =IFERROR(__xludf.DUMMYFUNCTION("""COMPUTED_VALUE"""),35.0) -> 35 | B37: =IFERROR(__xludf.DUMMYFUNCTION("""COMPUTED_VALUE"""),"SAMAHAN NG MAGSASAKA NG BARANGAY NANGUMA (SAMABANA)") -> SAMAHAN NG MAGSASAKA NG BARANGAY NANGUMA (SAMABANA) | C37: =IFERROR(__xludf.DUMMYFUNCTION("""COMPUTED_VALUE"""),"Nanguma, Mabitac, Laguna") -> Nanguma, Mabitac, Laguna | D37: =IFERROR(__xludf.DUMMYFUNCTION("""COMPUTED_VALUE"""),"LORETO D. PEREZ") -> LORETO D. PEREZ | E37: =IFERROR(__xludf.DUMMYFUNCTION("""COMPUTED_VALUE"""),"0927-910-0483") -> 0927-910-0483 | F37: =IFERROR(__xludf.DUMMYFUNCTION("""COMPUTED_VALUE"""),"RCEF 23-08-20 Rebidding") -> RCEF 23-08-20 Rebidding | G37: =IFERROR(__xludf.DUMMYFUNCTION("""COMPUTED_VALUE"""),1.0) -> 1 | H37: =IFERROR(__xludf.DUMMYFUNCTION("""COMPUTED_VALUE"""),17708.0) -> 17708 | I37: =IFERROR(__xludf.DUMMYFUNCTION("""COMPUTED_VALUE"""),"KMC 5825 ATPFPV0111") -> KMC 5825 ATPFPV0111 | J37: =IFERROR(__xludf.DUMMYFUNCTION("""COMPUTED_VALUE"""),"PTS100093") -> PTS100093 | K37: =IFERROR(__xludf.DUMMYFUNCTION("""COMPUTED_VALUE"""),"R-SERIES 017 PH") -> R-SERIES 017 PH | L37: =IFERROR(__xludf.DUMMYFUNCTION("""COMPUTED_VALUE"""),"LSGW1750-RMP-2312161") -> LSGW1750-RMP-2312161 | M37: =IFERROR(__xludf.DUMMYFUNCTION("""COMPUTED_VALUE"""),"WDP40-RMP-2401005") -> WDP40-RMP-2401005 | O37: =IFERROR(__xludf.DUMMYFUNCTION("""COMPUTED_VALUE"""),"Nanguma") -> Nanguma | P37: =IFERROR(__xludf.DUMMYFUNCTION("""COMPUTED_VALUE"""),"Mabitac") -> Mabitac | Q37: =IFERROR(__xludf.DUMMYFUNCTION("""COMPUTED_VALUE"""),"Laguna") -> Laguna | R37: =IFERROR(__xludf.DUMMYFUNCTION("""COMPUTED_VALUE"""),"4A") -> 4A
A38: =IFERROR(__xludf.DUMMYFUNCTION("""COMPUTED_VALUE"""),36.0) -> 36 | B38: =IFERROR(__xludf.DUMMYFUNCTION("""COMPUTED_VALUE"""),"SAMAHANG MAGPAPATUBIG NG DAMBO-ASUFRE PANGIL, LAGUNA INC.") -> SAMAHANG MAGPAPATUBIG NG DAMBO-ASUFRE PANGIL, LAGUNA INC. | C38: =IFERROR(__xludf.DUMMYFUNCTION("""COMPUTED_VALUE"""),"Dambo, Pangil, Laguna") -> Dambo, Pangil, Laguna | D38: =IFERROR(__xludf.DUMMYFUNCTION("""COMPUTED_VALUE"""),"Jonathan B. De Guia") -> Jonathan B. De Guia | E38: =IFERROR(__xludf.DUMMYFUNCTION("""COMPUTED_VALUE"""),"0935-519-1312") -> 0935-519-1312 | F38: =IFERROR(__xludf.DUMMYFUNCTION("""COMPUTED_VALUE"""),"RCEF 23-08-20 Rebidding") -> RCEF 23-08-20 Rebidding | G38: =IFERROR(__xludf.DUMMYFUNCTION("""COMPUTED_VALUE"""),1.0) -> 1 | H38: =IFERROR(__xludf.DUMMYFUNCTION("""COMPUTED_VALUE"""),17709.0) -> 17709 | I38: =IFERROR(__xludf.DUMMYFUNCTION("""COMPUTED_VALUE"""),"KMC 5825 ALRFPV0011") -> KMC 5825 ALRFPV0011 | J38: =IFERROR(__xludf.DUMMYFUNCTION("""COMPUTED_VALUE"""),"PTS100182") -> PTS100182 | K38: =IFERROR(__xludf.DUMMYFUNCTION("""COMPUTED_VALUE"""),"R-SERIES 038 PH") -> R-SERIES 038 PH | L38: =IFERROR(__xludf.DUMMYFUNCTION("""COMPUTED_VALUE"""),"LSGW1750-RMP-2312074") -> LSGW1750-RMP-2312074 | M38: =IFERROR(__xludf.DUMMYFUNCTION("""COMPUTED_VALUE"""),"WDP40-RMP-2312077") -> WDP40-RMP-2312077 | O38: =IFERROR(__xludf.DUMMYFUNCTION("""COMPUTED_VALUE"""),"Dambo") -> Dambo | P38: =IFERROR(__xludf.DUMMYFUNCTION("""COMPUTED_VALUE"""),"Pangil") -> Pangil | Q38: =IFERROR(__xludf.DUMMYFUNCTION("""COMPUTED_VALUE"""),"Laguna") -> Laguna | R38: =IFERROR(__xludf.DUMMYFUNCTION("""COMPUTED_VALUE"""),"4A") -> 4A
A39: =IFERROR(__xludf.DUMMYFUNCTION("""COMPUTED_VALUE"""),37.0) -> 37 | B39: =IFERROR(__xludf.DUMMYFUNCTION("""COMPUTED_VALUE"""),"STA. CRUZ RIVER IRRIGATION SYSTEM IRRIGATORS ASSOCIATION, INC.") -> STA. CRUZ RIVER IRRIGATION SYSTEM IRRIGATORS ASSOCIATION, INC. | C39: =IFERROR(__xludf.DUMMYFUNCTION("""COMPUTED_VALUE"""),"Gatid, Santa Cruz, Laguna") -> Gatid, Santa Cruz, Laguna | D39: =IFERROR(__xludf.DUMMYFUNCTION("""COMPUTED_VALUE"""),"Roberto Ramos") -> Roberto Ramos | E39: =IFERROR(__xludf.DUMMYFUNCTION("""COMPUTED_VALUE"""),"0968 606 0896") -> 0968 606 0896 | F39: =IFERROR(__xludf.DUMMYFUNCTION("""COMPUTED_VALUE"""),"RCEF 23-08-20 Rebidding") -> RCEF 23-08-20 Rebidding | G39: =IFERROR(__xludf.DUMMYFUNCTION("""COMPUTED_VALUE"""),1.0) -> 1 | H39: =IFERROR(__xludf.DUMMYFUNCTION("""COMPUTED_VALUE"""),17710.0) -> 17710 | I39: =IFERROR(__xludf.DUMMYFUNCTION("""COMPUTED_VALUE"""),"KMC 5825 AHPFPV0012") -> KMC 5825 AHPFPV0012 | J39: =IFERROR(__xludf.DUMMYFUNCTION("""COMPUTED_VALUE"""),"PTS100169") -> PTS100169 | K39: =IFERROR(__xludf.DUMMYFUNCTION("""COMPUTED_VALUE"""),"R-SERIES 147 PH") -> R-SERIES 147 PH | L39: =IFERROR(__xludf.DUMMYFUNCTION("""COMPUTED_VALUE"""),"LSGW1750-RMP-2312162") -> LSGW1750-RMP-2312162 | M39: =IFERROR(__xludf.DUMMYFUNCTION("""COMPUTED_VALUE"""),"WDP40-RMP-2312108") -> WDP40-RMP-2312108 | O39: =IFERROR(__xludf.DUMMYFUNCTION("""COMPUTED_VALUE"""),"Gatid") -> Gatid | P39: =IFERROR(__xludf.DUMMYFUNCTION("""COMPUTED_VALUE"""),"Santa Cruz") -> Santa Cruz | Q39: =IFERROR(__xludf.DUMMYFUNCTION("""COMPUTED_VALUE"""),"Laguna") -> Laguna | R39: =IFERROR(__xludf.DUMMYFUNCTION("""COMPUTED_VALUE"""),"4A") -> 4A
A40: =IFERROR(__xludf.DUMMYFUNCTION("""COMPUTED_VALUE"""),38.0) -> 38 | B40: =IFERROR(__xludf.DUMMYFUNCTION("""COMPUTED_VALUE"""),"BAGUMBAYAN ORGANIC FARMER’S ASSOCIATION") -> BAGUMBAYAN ORGANIC FARMER’S ASSOCIATION | C40: =IFERROR(__xludf.DUMMYFUNCTION("""COMPUTED_VALUE"""),"Bagumbayan, Santa Maria, Laguna") -> Bagumbayan, Santa Maria, Laguna | E40: =IFERROR(__xludf.DUMMYFUNCTION("""COMPUTED_VALUE"""),9.672085261E9) -> 9672085261 | F40: =IFERROR(__xludf.DUMMYFUNCTION("""COMPUTED_VALUE"""),"RCEF 23-08-20 Rebidding") -> RCEF 23-08-20 Rebidding | G40: =IFERROR(__xludf.DUMMYFUNCTION("""COMPUTED_VALUE"""),1.0) -> 1 | H40: =IFERROR(__xludf.DUMMYFUNCTION("""COMPUTED_VALUE"""),17711.0) -> 17711 | I40: =IFERROR(__xludf.DUMMYFUNCTION("""COMPUTED_VALUE"""),"KMC 5825 AAKFPV0007") -> KMC 5825 AAKFPV0007 | J40: =IFERROR(__xludf.DUMMYFUNCTION("""COMPUTED_VALUE"""),"PTS100274") -> PTS100274 | K40: =IFERROR(__xludf.DUMMYFUNCTION("""COMPUTED_VALUE"""),"R-SERIES 013 PH") -> R-SERIES 013 PH | L40: =IFERROR(__xludf.DUMMYFUNCTION("""COMPUTED_VALUE"""),"LSGW1750-RMP-2312175") -> LSGW1750-RMP-2312175 | M40: =IFERROR(__xludf.DUMMYFUNCTION("""COMPUTED_VALUE"""),"WDP40-RMP-2312136") -> WDP40-RMP-2312136 | O40: =IFERROR(__xludf.DUMMYFUNCTION("""COMPUTED_VALUE"""),"Bagumbayan") -> Bagumbayan | P40: =IFERROR(__xludf.DUMMYFUNCTION("""COMPUTED_VALUE"""),"Santa Maria") -> Santa Maria | Q40: =IFERROR(__xludf.DUMMYFUNCTION("""COMPUTED_VALUE"""),"Laguna") -> Laguna | R40: =IFERROR(__xludf.DUMMYFUNCTION("""COMPUTED_VALUE"""),"4A") -> 4A
A41: =IFERROR(__xludf.DUMMYFUNCTION("""COMPUTED_VALUE"""),39.0) -> 39 | B41: =IFERROR(__xludf.DUMMYFUNCTION("""COMPUTED_VALUE"""),"BARANGAY BANUGAO FARMERS ASSOCIATION") -> BARANGAY BANUGAO FARMERS ASSOCIATION | C41: =IFERROR(__xludf.DUMMYFUNCTION("""COMPUTED_VALUE"""),"Banugao, Infanta, Quezon") -> Banugao, Infanta, Quezon | D41: =IFERROR(__xludf.DUMMYFUNCTION("""COMPUTED_VALUE"""),"Catalino Mostoles") -> Catalino Mostoles | E41: =IFERROR(__xludf.DUMMYFUNCTION("""COMPUTED_VALUE"""),"0920 733 8911") -> 0920 733 8911 | F41: =IFERROR(__xludf.DUMMYFUNCTION("""COMPUTED_VALUE"""),"RCEF 23-08-20 Rebidding") -> RCEF 23-08-20 Rebidding | G41: =IFERROR(__xludf.DUMMYFUNCTION("""COMPUTED_VALUE"""),1.0) -> 1 | H41: =IFERROR(__xludf.DUMMYFUNCTION("""COMPUTED_VALUE"""),17712.0) -> 17712 | I41: =IFERROR(__xludf.DUMMYFUNCTION("""COMPUTED_VALUE"""),"KMC5825 ACRFPV0392") -> KMC5825 ACRFPV0392 | J41: =IFERROR(__xludf.DUMMYFUNCTION("""COMPUTED_VALUE"""),"RTS100157") -> RTS100157 | K41: =IFERROR(__xludf.DUMMYFUNCTION("""COMPUTED_VALUE"""),"R-SERIES 132 PH") -> R-SERIES 132 PH | L41: =IFERROR(__xludf.DUMMYFUNCTION("""COMPUTED_VALUE"""),"LSGW1750 RMP 2312149") -> LSGW1750 RMP 2312149 | M41: =IFERROR(__xludf.DUMMYFUNCTION("""COMPUTED_VALUE"""),"WDP40 RMP 24020188") -> WDP40 RMP 24020188 | O41: =IFERROR(__xludf.DUMMYFUNCTION("""COMPUTED_VALUE"""),"Banugao") -> Banugao | P41: =IFERROR(__xludf.DUMMYFUNCTION("""COMPUTED_VALUE"""),"Infanta") -> Infanta | Q41: =IFERROR(__xludf.DUMMYFUNCTION("""COMPUTED_VALUE"""),"Quezon") -> Quezon | R41: =IFERROR(__xludf.DUMMYFUNCTION("""COMPUTED_VALUE"""),"4A") -> 4A
A42: =IFERROR(__xludf.DUMMYFUNCTION("""COMPUTED_VALUE"""),40.0) -> 40 | B42: =IFERROR(__xludf.DUMMYFUNCTION("""COMPUTED_VALUE"""),"MAUBAN FARMERS ASSOCIATION") -> MAUBAN FARMERS ASSOCIATION | C42: =IFERROR(__xludf.DUMMYFUNCTION("""COMPUTED_VALUE"""),"Rizaliana, Mauban, Quezon") -> Rizaliana, Mauban, Quezon | D42: =IFERROR(__xludf.DUMMYFUNCTION("""COMPUTED_VALUE"""),"Sergio D. Conchada Jr.") -> Sergio D. Conchada Jr. | E42: =IFERROR(__xludf.DUMMYFUNCTION("""COMPUTED_VALUE"""),"0908-872-9939") -> 0908-872-9939 | F42: =IFERROR(__xludf.DUMMYFUNCTION("""COMPUTED_VALUE"""),"RCEF 23-08-20 Rebidding") -> RCEF 23-08-20 Rebidding | G42: =IFERROR(__xludf.DUMMYFUNCTION("""COMPUTED_VALUE"""),1.0) -> 1 | H42: =IFERROR(__xludf.DUMMYFUNCTION("""COMPUTED_VALUE"""),17713.0) -> 17713 | I42: =IFERROR(__xludf.DUMMYFUNCTION("""COMPUTED_VALUE"""),"KMC 5825 ACPFPV0129") -> KMC 5825 ACPFPV0129 | J42: =IFERROR(__xludf.DUMMYFUNCTION("""COMPUTED_VALUE"""),"PTS100117") -> PTS100117 | K42: =IFERROR(__xludf.DUMMYFUNCTION("""COMPUTED_VALUE"""),"R-SERIES 110 PH") -> R-SERIES 110 PH | L42: =IFERROR(__xludf.DUMMYFUNCTION("""COMPUTED_VALUE"""),"LSGW1750-RMP-2312135") -> LSGW1750-RMP-2312135 | M42: =IFERROR(__xludf.DUMMYFUNCTION("""COMPUTED_VALUE"""),"WDP40-RMP-2312012") -> WDP40-RMP-2312012 | O42: =IFERROR(__xludf.DUMMYFUNCTION("""COMPUTED_VALUE"""),"Rizaliana") -> Rizaliana | P42: =IFERROR(__xludf.DUMMYFUNCTION("""COMPUTED_VALUE"""),"Mauban") -> Mauban | Q42: =IFERROR(__xludf.DUMMYFUNCTION("""COMPUTED_VALUE"""),"Quezon") -> Quezon | R42: =IFERROR(__xludf.DUMMYFUNCTION("""COMPUTED_VALUE"""),"4A") -> 4A
A43: =IFERROR(__xludf.DUMMYFUNCTION("""COMPUTED_VALUE"""),41.0) -> 41 | B43: =IFERROR(__xludf.DUMMYFUNCTION("""COMPUTED_VALUE"""),"NAGKAKAISANG MAGSASAKA NG BANTIGUE IRRIGATORS ASSN., INC.") -> NAGKAKAISANG MAGSASAKA NG BANTIGUE IRRIGATORS ASSN., INC. | C43: =IFERROR(__xludf.DUMMYFUNCTION("""COMPUTED_VALUE"""),"Bantigue, Pagbilao, Quezon") -> Bantigue, Pagbilao, Quezon | D43: =IFERROR(__xludf.DUMMYFUNCTION("""COMPUTED_VALUE"""),"Juanito L. Gutierrez") -> Juanito L. Gutierrez | E43: =IFERROR(__xludf.DUMMYFUNCTION("""COMPUTED_VALUE"""),"0951 235 8285") -> 0951 235 8285 | F43: =IFERROR(__xludf.DUMMYFUNCTION("""COMPUTED_VALUE"""),"RCEF 23-08-20 Rebidding") -> RCEF 23-08-20 Rebidding | G43: =IFERROR(__xludf.DUMMYFUNCTION("""COMPUTED_VALUE"""),1.0) -> 1 | H43: =IFERROR(__xludf.DUMMYFUNCTION("""COMPUTED_VALUE"""),17714.0) -> 17714 | I43: =IFERROR(__xludf.DUMMYFUNCTION("""COMPUTED_VALUE"""),"KMC 5825 ACPFPV0043") -> KMC 5825 ACPFPV0043 | J43: =IFERROR(__xludf.DUMMYFUNCTION("""COMPUTED_VALUE"""),"PTS100126") -> PTS100126 | K43: =IFERROR(__xludf.DUMMYFUNCTION("""COMPUTED_VALUE"""),"R-SERIES 109 PH") -> R-SERIES 109 PH | L43: =IFERROR(__xludf.DUMMYFUNCTION("""COMPUTED_VALUE"""),"LSGW1750-RMP-2312127") -> LSGW1750-RMP-2312127 | M43: =IFERROR(__xludf.DUMMYFUNCTION("""COMPUTED_VALUE"""),"WDP40-RMP-2312021") -> WDP40-RMP-2312021 | O43: =IFERROR(__xludf.DUMMYFUNCTION("""COMPUTED_VALUE"""),"Bantigue") -> Bantigue | P43: =IFERROR(__xludf.DUMMYFUNCTION("""COMPUTED_VALUE"""),"Pagbilao") -> Pagbilao | Q43: =IFERROR(__xludf.DUMMYFUNCTION("""COMPUTED_VALUE"""),"Quezon") -> Quezon | R43: =IFERROR(__xludf.DUMMYFUNCTION("""COMPUTED_VALUE"""),"4A") -> 4A
A44: =IFERROR(__xludf.DUMMYFUNCTION("""COMPUTED_VALUE"""),42.0) -> 42 | B44: =IFERROR(__xludf.DUMMYFUNCTION("""COMPUTED_VALUE"""),"Alupaye Farmers Central Irrigators Association, Inc.") -> Alupaye Farmers Central Irrigators Association, Inc. | C44: =IFERROR(__xludf.DUMMYFUNCTION("""COMPUTED_VALUE"""),"Alupaye, Pagbilao, Quezon") -> Alupaye, Pagbilao, Quezon | D44: =IFERROR(__xludf.DUMMYFUNCTION("""COMPUTED_VALUE"""),"Clarence Gatus") -> Clarence Gatus | E44: =IFERROR(__xludf.DUMMYFUNCTION("""COMPUTED_VALUE"""),"0939 763 5038") -> 0939 763 5038 | F44: =IFERROR(__xludf.DUMMYFUNCTION("""COMPUTED_VALUE"""),"RCEF 23-08-20 Rebidding") -> RCEF 23-08-20 Rebidding | G44: =IFERROR(__xludf.DUMMYFUNCTION("""COMPUTED_VALUE"""),1.0) -> 1 | H44: =IFERROR(__xludf.DUMMYFUNCTION("""COMPUTED_VALUE"""),17715.0) -> 17715 | I44: =IFERROR(__xludf.DUMMYFUNCTION("""COMPUTED_VALUE"""),"KMC 5825 ATPFPV0058") -> KMC 5825 ATPFPV0058 | J44: =IFERROR(__xludf.DUMMYFUNCTION("""COMPUTED_VALUE"""),"PTS100137") -> PTS100137 | K44: =IFERROR(__xludf.DUMMYFUNCTION("""COMPUTED_VALUE"""),"R-SERIES 023 PH") -> R-SERIES 023 PH | L44: =IFERROR(__xludf.DUMMYFUNCTION("""COMPUTED_VALUE"""),"LSGW1750-RMP-2312131") -> LSGW1750-RMP-2312131 | M44: =IFERROR(__xludf.DUMMYFUNCTION("""COMPUTED_VALUE"""),"WDP40-RMP-2312033") -> WDP40-RMP-2312033 | O44: =IFERROR(__xludf.DUMMYFUNCTION("""COMPUTED_VALUE"""),"Alupaye") -> Alupaye | P44: =IFERROR(__xludf.DUMMYFUNCTION("""COMPUTED_VALUE"""),"Pagbilao") -> Pagbilao | Q44: =IFERROR(__xludf.DUMMYFUNCTION("""COMPUTED_VALUE"""),"Quezon") -> Quezon | R44: =IFERROR(__xludf.DUMMYFUNCTION("""COMPUTED_VALUE"""),"4A") -> 4A
A45: =IFERROR(__xludf.DUMMYFUNCTION("""COMPUTED_VALUE"""),43.0) -> 43 | B45: =IFERROR(__xludf.DUMMYFUNCTION("""COMPUTED_VALUE"""),"MAPAGONG FARMERS IRROGATORS ASSN. INC.") -> MAPAGONG FARMERS IRROGATORS ASSN. INC. | C45: =IFERROR(__xludf.DUMMYFUNCTION("""COMPUTED_VALUE"""),"Mapagong, Pagbilao, Quezon") -> Mapagong, Pagbilao, Quezon | D45: =IFERROR(__xludf.DUMMYFUNCTION("""COMPUTED_VALUE"""),"Renato D. De Rama") -> Renato D. De Rama | E45: =IFERROR(__xludf.DUMMYFUNCTION("""COMPUTED_VALUE"""),"0912 525 4000") -> 0912 525 4000 | F45: =IFERROR(__xludf.DUMMYFUNCTION("""COMPUTED_VALUE"""),"RCEF 23-08-20 Rebidding") -> RCEF 23-08-20 Rebidding | G45: =IFERROR(__xludf.DUMMYFUNCTION("""COMPUTED_VALUE"""),1.0) -> 1 | H45: =IFERROR(__xludf.DUMMYFUNCTION("""COMPUTED_VALUE"""),17716.0) -> 17716 | I45: =IFERROR(__xludf.DUMMYFUNCTION("""COMPUTED_VALUE"""),"KMC 5825 AHPFPV0069") -> KMC 5825 AHPFPV0069 | J45: =IFERROR(__xludf.DUMMYFUNCTION("""COMPUTED_VALUE"""),"PTS100159") -> PTS100159 | K45: =IFERROR(__xludf.DUMMYFUNCTION("""COMPUTED_VALUE"""),"R-SERIES 113 PH") -> R-SERIES 113 PH | L45: =IFERROR(__xludf.DUMMYFUNCTION("""COMPUTED_VALUE"""),"LSGW1750-RMP-2312118") -> LSGW1750-RMP-2312118 | M45: =IFERROR(__xludf.DUMMYFUNCTION("""COMPUTED_VALUE"""),"WDP40-RMP-2312019") -> WDP40-RMP-2312019 | O45: =IFERROR(__xludf.DUMMYFUNCTION("""COMPUTED_VALUE"""),"Mapagong") -> Mapagong | P45: =IFERROR(__xludf.DUMMYFUNCTION("""COMPUTED_VALUE"""),"Pagbilao") -> Pagbilao | Q45: =IFERROR(__xludf.DUMMYFUNCTION("""COMPUTED_VALUE"""),"Quezon") -> Quezon | R45: =IFERROR(__xludf.DUMMYFUNCTION("""COMPUTED_VALUE"""),"4A") -> 4A
A46: =IFERROR(__xludf.DUMMYFUNCTION("""COMPUTED_VALUE"""),44.0) -> 44 | B46: =IFERROR(__xludf.DUMMYFUNCTION("""COMPUTED_VALUE"""),"TUBIG BIYAYA IRRIGATORS' ASSOCIATION, INC.") -> TUBIG BIYAYA IRRIGATORS' ASSOCIATION, INC. | C46: =IFERROR(__xludf.DUMMYFUNCTION("""COMPUTED_VALUE"""),"Binahaan, Pagbilao, Quezon") -> Binahaan, Pagbilao, Quezon | D46: =IFERROR(__xludf.DUMMYFUNCTION("""COMPUTED_VALUE"""),"Primitiva C. Memorando") -> Primitiva C. Memorando | E46: =IFERROR(__xludf.DUMMYFUNCTION("""COMPUTED_VALUE"""),"0998-881-3869") -> 0998-881-3869 | F46: =IFERROR(__xludf.DUMMYFUNCTION("""COMPUTED_VALUE"""),"RCEF 23-08-20 Rebidding") -> RCEF 23-08-20 Rebidding | G46: =IFERROR(__xludf.DUMMYFUNCTION("""COMPUTED_VALUE"""),1.0) -> 1 | H46: =IFERROR(__xludf.DUMMYFUNCTION("""COMPUTED_VALUE"""),17717.0) -> 17717 | I46: =IFERROR(__xludf.DUMMYFUNCTION("""COMPUTED_VALUE"""),"KMC 5825 ATPFPV0108") -> KMC 5825 ATPFPV0108 | J46: =IFERROR(__xludf.DUMMYFUNCTION("""COMPUTED_VALUE"""),"PTS100086") -> PTS100086 | K46: =IFERROR(__xludf.DUMMYFUNCTION("""COMPUTED_VALUE"""),"R-SERIES 085 PH") -> R-SERIES 085 PH | L46: =IFERROR(__xludf.DUMMYFUNCTION("""COMPUTED_VALUE"""),"LSGW1750-RMP-2312134") -> LSGW1750-RMP-2312134 | M46: =IFERROR(__xludf.DUMMYFUNCTION("""COMPUTED_VALUE"""),"WDP40-RMP-2312029") -> WDP40-RMP-2312029 | O46: =IFERROR(__xludf.DUMMYFUNCTION("""COMPUTED_VALUE"""),"Binahaan") -> Binahaan | P46: =IFERROR(__xludf.DUMMYFUNCTION("""COMPUTED_VALUE"""),"Pagbilao") -> Pagbilao | Q46: =IFERROR(__xludf.DUMMYFUNCTION("""COMPUTED_VALUE"""),"Quezon") -> Quezon | R46: =IFERROR(__xludf.DUMMYFUNCTION("""COMPUTED_VALUE"""),"4A") -> 4A
A47: =IFERROR(__xludf.DUMMYFUNCTION("""COMPUTED_VALUE"""),45.0) -> 45 | B47: =IFERROR(__xludf.DUMMYFUNCTION("""COMPUTED_VALUE"""),"Taluong -Quedanom Irrigators Association") -> Taluong -Quedanom Irrigators Association | C47: =IFERROR(__xludf.DUMMYFUNCTION("""COMPUTED_VALUE"""),"Taluong, Polillo, Quezon") -> Taluong, Polillo, Quezon | D47: =IFERROR(__xludf.DUMMYFUNCTION("""COMPUTED_VALUE"""),"Joanamel G. Azarias") -> Joanamel G. Azarias | E47: =IFERROR(__xludf.DUMMYFUNCTION("""COMPUTED_VALUE"""),"0908 538 6020") -> 0908 538 6020 | F47: =IFERROR(__xludf.DUMMYFUNCTION("""COMPUTED_VALUE"""),"RCEF 23-08-20 Rebidding") -> RCEF 23-08-20 Rebidding | G47: =IFERROR(__xludf.DUMMYFUNCTION("""COMPUTED_VALUE"""),1.0) -> 1 | H47: =IFERROR(__xludf.DUMMYFUNCTION("""COMPUTED_VALUE"""),17718.0) -> 17718 | I47: =IFERROR(__xludf.DUMMYFUNCTION("""COMPUTED_VALUE"""),"KMC5825 AVRFPV0412") -> KMC5825 AVRFPV0412 | J47: =IFERROR(__xludf.DUMMYFUNCTION("""COMPUTED_VALUE"""),"RTS100292") -> RTS100292 | K47: =IFERROR(__xludf.DUMMYFUNCTION("""COMPUTED_VALUE"""),"R-SERIES 047 PH") -> R-SERIES 047 PH | L47: =IFERROR(__xludf.DUMMYFUNCTION("""COMPUTED_VALUE"""),"LSGW1750 RMP 2312168") -> LSGW1750 RMP 2312168 | M47: =IFERROR(__xludf.DUMMYFUNCTION("""COMPUTED_VALUE"""),"WDP40 RMP 24020202") -> WDP40 RMP 24020202 | O47: =IFERROR(__xludf.DUMMYFUNCTION("""COMPUTED_VALUE"""),"Taluong") -> Taluong | P47: =IFERROR(__xludf.DUMMYFUNCTION("""COMPUTED_VALUE"""),"Polillo") -> Polillo | Q47: =IFERROR(__xludf.DUMMYFUNCTION("""COMPUTED_VALUE"""),"Quezon") -> Quezon | R47: =IFERROR(__xludf.DUMMYFUNCTION("""COMPUTED_VALUE"""),"4A") -> 4A
A48: =IFERROR(__xludf.DUMMYFUNCTION("""COMPUTED_VALUE"""),46.0) -> 46 | B48: =IFERROR(__xludf.DUMMYFUNCTION("""COMPUTED_VALUE"""),"SAMAHAN NG MGA MAGSASAKA NG PAHINGA NORTE") -> SAMAHAN NG MGA MAGSASAKA NG PAHINGA NORTE | C48: =IFERROR(__xludf.DUMMYFUNCTION("""COMPUTED_VALUE"""),"Pahinga Norte, Candelaria, Quezon") -> Pahinga Norte, Candelaria, Quezon | D48: =IFERROR(__xludf.DUMMYFUNCTION("""COMPUTED_VALUE"""),"Roberto Ebora") -> Roberto Ebora | E48: =IFERROR(__xludf.DUMMYFUNCTION("""COMPUTED_VALUE"""),"0936-915-6875") -> 0936-915-6875 | F48: =IFERROR(__xludf.DUMMYFUNCTION("""COMPUTED_VALUE"""),"RCEF 23-08-20 Rebidding") -> RCEF 23-08-20 Rebidding | G48: =IFERROR(__xludf.DUMMYFUNCTION("""COMPUTED_VALUE"""),1.0) -> 1 | H48: =IFERROR(__xludf.DUMMYFUNCTION("""COMPUTED_VALUE"""),17719.0) -> 17719 | I48: =IFERROR(__xludf.DUMMYFUNCTION("""COMPUTED_VALUE"""),"KMC5825 AKRFPV0390") -> KMC5825 AKRFPV0390 | J48: =IFERROR(__xludf.DUMMYFUNCTION("""COMPUTED_VALUE"""),"RTS100257") -> RTS100257 | K48: =IFERROR(__xludf.DUMMYFUNCTION("""COMPUTED_VALUE"""),"R-SERIES 439 PH") -> R-SERIES 439 PH | L48: =IFERROR(__xludf.DUMMYFUNCTION("""COMPUTED_VALUE"""),"LSGW1750 RMP 24020456") -> LSGW1750 RMP 24020456 | M48: =IFERROR(__xludf.DUMMYFUNCTION("""COMPUTED_VALUE"""),"WDP40 RMP 24020239") -> WDP40 RMP 24020239 | O48: =IFERROR(__xludf.DUMMYFUNCTION("""COMPUTED_VALUE"""),"Pahinga Norte") -> Pahinga Norte | P48: =IFERROR(__xludf.DUMMYFUNCTION("""COMPUTED_VALUE"""),"Candelaria") -> Candelaria | Q48: =IFERROR(__xludf.DUMMYFUNCTION("""COMPUTED_VALUE"""),"Quezon") -> Quezon | R48: =IFERROR(__xludf.DUMMYFUNCTION("""COMPUTED_VALUE"""),"4A") -> 4A
A49: =IFERROR(__xludf.DUMMYFUNCTION("""COMPUTED_VALUE"""),47.0) -> 47 | B49: =IFERROR(__xludf.DUMMYFUNCTION("""COMPUTED_VALUE"""),"SAN ISIDRO-CANDELARIA FARMERS ASSOCIATION") -> SAN ISIDRO-CANDELARIA FARMERS ASSOCIATION | C49: =IFERROR(__xludf.DUMMYFUNCTION("""COMPUTED_VALUE"""),"San Isidro, Candelaria, Quezon") -> San Isidro, Candelaria, Quezon | D49: =IFERROR(__xludf.DUMMYFUNCTION("""COMPUTED_VALUE"""),"Dante D. Florante") -> Dante D. Florante | E49: =IFERROR(__xludf.DUMMYFUNCTION("""COMPUTED_VALUE"""),"0912 127 6601") -> 0912 127 6601 | F49: =IFERROR(__xludf.DUMMYFUNCTION("""COMPUTED_VALUE"""),"RCEF 23-08-20 Rebidding") -> RCEF 23-08-20 Rebidding | G49: =IFERROR(__xludf.DUMMYFUNCTION("""COMPUTED_VALUE"""),1.0) -> 1 | H49: =IFERROR(__xludf.DUMMYFUNCTION("""COMPUTED_VALUE"""),17720.0) -> 17720 | I49: =IFERROR(__xludf.DUMMYFUNCTION("""COMPUTED_VALUE"""),"KMC5825 APRFPV0307") -> KMC5825 APRFPV0307 | J49: =IFERROR(__xludf.DUMMYFUNCTION("""COMPUTED_VALUE"""),"RTS100205") -> RTS100205 | K49: =IFERROR(__xludf.DUMMYFUNCTION("""COMPUTED_VALUE"""),"R-SERIES 405 PH") -> R-SERIES 405 PH | L49: =IFERROR(__xludf.DUMMYFUNCTION("""COMPUTED_VALUE"""),"LSGW1750 RMP 24020450") -> LSGW1750 RMP 24020450 | M49: =IFERROR(__xludf.DUMMYFUNCTION("""COMPUTED_VALUE"""),"WDP40 RMP 24020218") -> WDP40 RMP 24020218 | O49: =IFERROR(__xludf.DUMMYFUNCTION("""COMPUTED_VALUE"""),"San Isidro") -> San Isidro | P49: =IFERROR(__xludf.DUMMYFUNCTION("""COMPUTED_VALUE"""),"Candelaria") -> Candelaria | Q49: =IFERROR(__xludf.DUMMYFUNCTION("""COMPUTED_VALUE"""),"Quezon") -> Quezon | R49: =IFERROR(__xludf.DUMMYFUNCTION("""COMPUTED_VALUE"""),"4A") -> 4A
A50: =IFERROR(__xludf.DUMMYFUNCTION("""COMPUTED_VALUE"""),48.0) -> 48 | B50: =IFERROR(__xludf.DUMMYFUNCTION("""COMPUTED_VALUE"""),"Yakap at Halik Multi-Purpose Cooperative Quezon 1 (YHMPCQ1)") -> Yakap at Halik Multi-Purpose Cooperative Quezon 1 (YHMPCQ1) | C50: =IFERROR(__xludf.DUMMYFUNCTION("""COMPUTED_VALUE"""),"Poblacion, Candelaria, Quezon") -> Poblacion, Candelaria, Quezon | D50: =IFERROR(__xludf.DUMMYFUNCTION("""COMPUTED_VALUE"""),"Robert Diala") -> Robert Diala | E50: =IFERROR(__xludf.DUMMYFUNCTION("""COMPUTED_VALUE"""),"0923 027 0837") -> 0923 027 0837 | F50: =IFERROR(__xludf.DUMMYFUNCTION("""COMPUTED_VALUE"""),"RCEF 23-08-20 Rebidding") -> RCEF 23-08-20 Rebidding | G50: =IFERROR(__xludf.DUMMYFUNCTION("""COMPUTED_VALUE"""),1.0) -> 1 | H50: =IFERROR(__xludf.DUMMYFUNCTION("""COMPUTED_VALUE"""),17722.0) -> 17722 | I50: =IFERROR(__xludf.DUMMYFUNCTION("""COMPUTED_VALUE"""),"KMC5825 ACRFPV0389") -> KMC5825 ACRFPV0389 | J50: =IFERROR(__xludf.DUMMYFUNCTION("""COMPUTED_VALUE"""),"RTS100272") -> RTS100272 | K50: =IFERROR(__xludf.DUMMYFUNCTION("""COMPUTED_VALUE"""),"R-SERIES 411 PH") -> R-SERIES 411 PH | L50: =IFERROR(__xludf.DUMMYFUNCTION("""COMPUTED_VALUE"""),"LSGW1750 RMP 24020454") -> LSGW1750 RMP 24020454 | M50: =IFERROR(__xludf.DUMMYFUNCTION("""COMPUTED_VALUE"""),"WDP40 RMP 24020244") -> WDP40 RMP 24020244 | O50: =IFERROR(__xludf.DUMMYFUNCTION("""COMPUTED_VALUE"""),"Poblacion") -> Poblacion | P50: =IFERROR(__xludf.DUMMYFUNCTION("""COMPUTED_VALUE"""),"Candelaria") -> Candelaria | Q50: =IFERROR(__xludf.DUMMYFUNCTION("""COMPUTED_VALUE"""),"Quezon") -> Quezon | R50: =IFERROR(__xludf.DUMMYFUNCTION("""COMPUTED_VALUE"""),"4A") -> 4A
A51: =IFERROR(__xludf.DUMMYFUNCTION("""COMPUTED_VALUE"""),49.0) -> 49 | B51: =IFERROR(__xludf.DUMMYFUNCTION("""COMPUTED_VALUE"""),"DAKILANG SULOK FARMERS' ASSOCIATION, INC.") -> DAKILANG SULOK FARMERS' ASSOCIATION, INC. | C51: =IFERROR(__xludf.DUMMYFUNCTION("""COMPUTED_VALUE"""),"Mayao Castillo, Lucena City, Quezon") -> Mayao Castillo, Lucena City, Quezon | D51: =IFERROR(__xludf.DUMMYFUNCTION("""COMPUTED_VALUE"""),"Dominador Pornasdoro") -> Dominador Pornasdoro | E51: =IFERROR(__xludf.DUMMYFUNCTION("""COMPUTED_VALUE"""),"0933 869 5027") -> 0933 869 5027 | F51: =IFERROR(__xludf.DUMMYFUNCTION("""COMPUTED_VALUE"""),"RCEF 23-08-20 Rebidding") -> RCEF 23-08-20 Rebidding | G51: =IFERROR(__xludf.DUMMYFUNCTION("""COMPUTED_VALUE"""),1.0) -> 1 | H51: =IFERROR(__xludf.DUMMYFUNCTION("""COMPUTED_VALUE"""),17723.0) -> 17723 | I51: =IFERROR(__xludf.DUMMYFUNCTION("""COMPUTED_VALUE"""),"KMC5825 AERDV0321") -> KMC5825 AERDV0321 | J51: =IFERROR(__xludf.DUMMYFUNCTION("""COMPUTED_VALUE"""),"RTS100197") -> RTS100197 | K51: =IFERROR(__xludf.DUMMYFUNCTION("""COMPUTED_VALUE"""),"R-SERIES 412 PH") -> R-SERIES 412 PH | L51: =IFERROR(__xludf.DUMMYFUNCTION("""COMPUTED_VALUE"""),"LSGW1750 RMP 24020427") -> LSGW1750 RMP 24020427 | M51: =IFERROR(__xludf.DUMMYFUNCTION("""COMPUTED_VALUE"""),"WDP40 RMP 24020227") -> WDP40 RMP 24020227 | O51: =IFERROR(__xludf.DUMMYFUNCTION("""COMPUTED_VALUE"""),"Mayao Castillo") -> Mayao Castillo | P51: =IFERROR(__xludf.DUMMYFUNCTION("""COMPUTED_VALUE"""),"Lucena City") -> Lucena City | Q51: =IFERROR(__xludf.DUMMYFUNCTION("""COMPUTED_VALUE"""),"Quezon") -> Quezon | R51: =IFERROR(__xludf.DUMMYFUNCTION("""COMPUTED_VALUE"""),"4A") -> 4A
A52: =IFERROR(__xludf.DUMMYFUNCTION("""COMPUTED_VALUE"""),50.0) -> 50 | B52: =IFERROR(__xludf.DUMMYFUNCTION("""COMPUTED_VALUE"""),"Lucena City Farmers Federation Multi-Purpose Cooperative") -> Lucena City Farmers Federation Multi-Purpose Cooperative | C52: =IFERROR(__xludf.DUMMYFUNCTION("""COMPUTED_VALUE"""),"Salinas, Lucena City, Quezon") -> Salinas, Lucena City, Quezon | D52: =IFERROR(__xludf.DUMMYFUNCTION("""COMPUTED_VALUE"""),"Gregorio S. Vecinal") -> Gregorio S. Vecinal | E52: =IFERROR(__xludf.DUMMYFUNCTION("""COMPUTED_VALUE"""),"0998 322 8339") -> 0998 322 8339 | F52: =IFERROR(__xludf.DUMMYFUNCTION("""COMPUTED_VALUE"""),"RCEF 23-08-20 Rebidding") -> RCEF 23-08-20 Rebidding | G52: =IFERROR(__xludf.DUMMYFUNCTION("""COMPUTED_VALUE"""),1.0) -> 1 | H52: =IFERROR(__xludf.DUMMYFUNCTION("""COMPUTED_VALUE"""),17724.0) -> 17724 | I52: =IFERROR(__xludf.DUMMYFUNCTION("""COMPUTED_VALUE"""),"KMC5825 AARFPV0329") -> KMC5825 AARFPV0329 | J52: =IFERROR(__xludf.DUMMYFUNCTION("""COMPUTED_VALUE"""),"RTS100179") -> RTS100179 | K52: =IFERROR(__xludf.DUMMYFUNCTION("""COMPUTED_VALUE"""),"R-SERIES 154 PH") -> R-SERIES 154 PH | L52: =IFERROR(__xludf.DUMMYFUNCTION("""COMPUTED_VALUE"""),"LSGW1750 RMP 24020415") -> LSGW1750 RMP 24020415 | M52: =IFERROR(__xludf.DUMMYFUNCTION("""COMPUTED_VALUE"""),"WDP40 RMP 24020217") -> WDP40 RMP 24020217 | O52: =IFERROR(__xludf.DUMMYFUNCTION("""COMPUTED_VALUE"""),"Salinas") -> Salinas | P52: =IFERROR(__xludf.DUMMYFUNCTION("""COMPUTED_VALUE"""),"Lucena City") -> Lucena City | Q52: =IFERROR(__xludf.DUMMYFUNCTION("""COMPUTED_VALUE"""),"Quezon") -> Quezon | R52: =IFERROR(__xludf.DUMMYFUNCTION("""COMPUTED_VALUE"""),"4A") -> 4A
A53: =IFERROR(__xludf.DUMMYFUNCTION("""COMPUTED_VALUE"""),51.0) -> 51 | B53: =IFERROR(__xludf.DUMMYFUNCTION("""COMPUTED_VALUE"""),"TUMBAGA I BUCAL IRRIGATORS ASSOCIATION, INC.") -> TUMBAGA I BUCAL IRRIGATORS ASSOCIATION, INC. | C53: =IFERROR(__xludf.DUMMYFUNCTION("""COMPUTED_VALUE"""),"Tumbaga I, Sariaya, Quezon") -> Tumbaga I, Sariaya, Quezon | D53: =IFERROR(__xludf.DUMMYFUNCTION("""COMPUTED_VALUE"""),"Rogelio D. Mendoza") -> Rogelio D. Mendoza | E53: =IFERROR(__xludf.DUMMYFUNCTION("""COMPUTED_VALUE"""),"0917 597 5537") -> 0917 597 5537 | F53: =IFERROR(__xludf.DUMMYFUNCTION("""COMPUTED_VALUE"""),"RCEF 23-08-20 Rebidding") -> RCEF 23-08-20 Rebidding | G53: =IFERROR(__xludf.DUMMYFUNCTION("""COMPUTED_VALUE"""),1.0) -> 1 | H53: =IFERROR(__xludf.DUMMYFUNCTION("""COMPUTED_VALUE"""),17725.0) -> 17725 | I53: =IFERROR(__xludf.DUMMYFUNCTION("""COMPUTED_VALUE"""),"KMC5825 ACRFPV0448") -> KMC5825 ACRFPV0448 | J53: =IFERROR(__xludf.DUMMYFUNCTION("""COMPUTED_VALUE"""),"RTS100364") -> RTS100364 | K53: =IFERROR(__xludf.DUMMYFUNCTION("""COMPUTED_VALUE"""),"R-SERIES 415 PH") -> R-SERIES 415 PH | L53: =IFERROR(__xludf.DUMMYFUNCTION("""COMPUTED_VALUE"""),"LSGW1750 RMP 24020457") -> LSGW1750 RMP 24020457 | M53: =IFERROR(__xludf.DUMMYFUNCTION("""COMPUTED_VALUE"""),"WDP40 RMP 24020142") -> WDP40 RMP 24020142 | O53: =IFERROR(__xludf.DUMMYFUNCTION("""COMPUTED_VALUE"""),"Tumbaga I") -> Tumbaga I | P53: =IFERROR(__xludf.DUMMYFUNCTION("""COMPUTED_VALUE"""),"Sariaya") -> Sariaya | Q53: =IFERROR(__xludf.DUMMYFUNCTION("""COMPUTED_VALUE"""),"Quezon") -> Quezon | R53: =IFERROR(__xludf.DUMMYFUNCTION("""COMPUTED_VALUE"""),"4A") -> 4A
A54: =IFERROR(__xludf.DUMMYFUNCTION("""COMPUTED_VALUE"""),52.0) -> 52 | B54: =IFERROR(__xludf.DUMMYFUNCTION("""COMPUTED_VALUE"""),"SAN ISIDRO FARMER'S ASSOCIATION") -> SAN ISIDRO FARMER'S ASSOCIATION | C54: =IFERROR(__xludf.DUMMYFUNCTION("""COMPUTED_VALUE"""),"San Isidro, Tiaong, Quezon") -> San Isidro, Tiaong, Quezon | D54: =IFERROR(__xludf.DUMMYFUNCTION("""COMPUTED_VALUE"""),"Eusebio I. Silang Sr.") -> Eusebio I. Silang Sr. | E54: =IFERROR(__xludf.DUMMYFUNCTION("""COMPUTED_VALUE"""),"0946 230 0989 (AT)") -> 0946 230 0989 (AT) | F54: =IFERROR(__xludf.DUMMYFUNCTION("""COMPUTED_VALUE"""),"RCEF 23-08-20 Rebidding") -> RCEF 23-08-20 Rebidding | G54: =IFERROR(__xludf.DUMMYFUNCTION("""COMPUTED_VALUE"""),1.0) -> 1 | H54: =IFERROR(__xludf.DUMMYFUNCTION("""COMPUTED_VALUE"""),17726.0) -> 17726 | I54: =IFERROR(__xludf.DUMMYFUNCTION("""COMPUTED_VALUE"""),"KMC5825 ATRFPV0323") -> KMC5825 ATRFPV0323 | J54: =IFERROR(__xludf.DUMMYFUNCTION("""COMPUTED_VALUE"""),"RTS100191") -> RTS100191 | K54: =IFERROR(__xludf.DUMMYFUNCTION("""COMPUTED_VALUE"""),"R-SERIES 414 PH") -> R-SERIES 414 PH | L54: =IFERROR(__xludf.DUMMYFUNCTION("""COMPUTED_VALUE"""),"LSGW1750 RMP 24020413") -> LSGW1750 RMP 24020413 | M54: =IFERROR(__xludf.DUMMYFUNCTION("""COMPUTED_VALUE"""),"WDP40 RMP 24020237") -> WDP40 RMP 24020237 | O54: =IFERROR(__xludf.DUMMYFUNCTION("""COMPUTED_VALUE"""),"San Isidro") -> San Isidro | P54: =IFERROR(__xludf.DUMMYFUNCTION("""COMPUTED_VALUE"""),"Tiaong") -> Tiaong | Q54: =IFERROR(__xludf.DUMMYFUNCTION("""COMPUTED_VALUE"""),"Quezon") -> Quezon | R54: =IFERROR(__xludf.DUMMYFUNCTION("""COMPUTED_VALUE"""),"4A") -> 4A
A55: =IFERROR(__xludf.DUMMYFUNCTION("""COMPUTED_VALUE"""),53.0) -> 53 | B55: =IFERROR(__xludf.DUMMYFUNCTION("""COMPUTED_VALUE"""),"LALIG FARMERS ASSOCIATION") -> LALIG FARMERS ASSOCIATION | C55: =IFERROR(__xludf.DUMMYFUNCTION("""COMPUTED_VALUE"""),"Lalig, Tiaong, Quezon") -> Lalig, Tiaong, Quezon | D55: =IFERROR(__xludf.DUMMYFUNCTION("""COMPUTED_VALUE"""),"Danilo L. Guevara") -> Danilo L. Guevara | E55: =IFERROR(__xludf.DUMMYFUNCTION("""COMPUTED_VALUE"""),"0928 255 9507") -> 0928 255 9507 | F55: =IFERROR(__xludf.DUMMYFUNCTION("""COMPUTED_VALUE"""),"RCEF 23-08-20 Rebidding") -> RCEF 23-08-20 Rebidding | G55: =IFERROR(__xludf.DUMMYFUNCTION("""COMPUTED_VALUE"""),1.0) -> 1 | H55: =IFERROR(__xludf.DUMMYFUNCTION("""COMPUTED_VALUE"""),17727.0) -> 17727 | I55: =IFERROR(__xludf.DUMMYFUNCTION("""COMPUTED_VALUE"""),"KMC5825 ACRFPV0353") -> KMC5825 ACRFPV0353 | J55: =IFERROR(__xludf.DUMMYFUNCTION("""COMPUTED_VALUE"""),"RTS100245") -> RTS100245 | K55: =IFERROR(__xludf.DUMMYFUNCTION("""COMPUTED_VALUE"""),"R-SERIES 417 PH") -> R-SERIES 417 PH | L55: =IFERROR(__xludf.DUMMYFUNCTION("""COMPUTED_VALUE"""),"LSGW1750 RMP 24020510") -> LSGW1750 RMP 24020510 | M55: =IFERROR(__xludf.DUMMYFUNCTION("""COMPUTED_VALUE"""),"WDP40 RMP 24020190") -> WDP40 RMP 24020190 | O55: =IFERROR(__xludf.DUMMYFUNCTION("""COMPUTED_VALUE"""),"Lalig") -> Lalig | P55: =IFERROR(__xludf.DUMMYFUNCTION("""COMPUTED_VALUE"""),"Tiaong") -> Tiaong | Q55: =IFERROR(__xludf.DUMMYFUNCTION("""COMPUTED_VALUE"""),"Quezon") -> Quezon | R55: =IFERROR(__xludf.DUMMYFUNCTION("""COMPUTED_VALUE"""),"4A") -> 4A
A56: =IFERROR(__xludf.DUMMYFUNCTION("""COMPUTED_VALUE"""),54.0) -> 54 | B56: =IFERROR(__xludf.DUMMYFUNCTION("""COMPUTED_VALUE"""),"PEDERASYON NG MGA SAMAHAN NG MAGSASAKA NG TIAONG, QUEZON") -> PEDERASYON NG MGA SAMAHAN NG MAGSASAKA NG TIAONG, QUEZON | C56: =IFERROR(__xludf.DUMMYFUNCTION("""COMPUTED_VALUE"""),"Poblacion 3, Tiaong, Quezon") -> Poblacion 3, Tiaong, Quezon | D56: =IFERROR(__xludf.DUMMYFUNCTION("""COMPUTED_VALUE"""),"Danilo l. Guevarra") -> Danilo l. Guevarra | E56: =IFERROR(__xludf.DUMMYFUNCTION("""COMPUTED_VALUE"""),"00908 889 1622 (MA)") -> 00908 889 1622 (MA) | F56: =IFERROR(__xludf.DUMMYFUNCTION("""COMPUTED_VALUE"""),"RCEF 23-08-20 Rebidding") -> RCEF 23-08-20 Rebidding | G56: =IFERROR(__xludf.DUMMYFUNCTION("""COMPUTED_VALUE"""),1.0) -> 1 | H56: =IFERROR(__xludf.DUMMYFUNCTION("""COMPUTED_VALUE"""),17728.0) -> 17728 | I56: =IFERROR(__xludf.DUMMYFUNCTION("""COMPUTED_VALUE"""),"KMC5825 AHRFPV0432") -> KMC5825 AHRFPV0432 | J56: =IFERROR(__xludf.DUMMYFUNCTION("""COMPUTED_VALUE"""),"RTS100334") -> RTS100334 | K56: =IFERROR(__xludf.DUMMYFUNCTION("""COMPUTED_VALUE"""),"R-SERIES 419 PH") -> R-SERIES 419 PH | L56: =IFERROR(__xludf.DUMMYFUNCTION("""COMPUTED_VALUE"""),"LSGW1750 RMP 24020420") -> LSGW1750 RMP 24020420 | M56: =IFERROR(__xludf.DUMMYFUNCTION("""COMPUTED_VALUE"""),"WDP40 RMP 24020220") -> WDP40 RMP 24020220 | O56: =IFERROR(__xludf.DUMMYFUNCTION("""COMPUTED_VALUE"""),"Poblacion 3") -> Poblacion 3 | P56: =IFERROR(__xludf.DUMMYFUNCTION("""COMPUTED_VALUE"""),"Tiaong") -> Tiaong | Q56: =IFERROR(__xludf.DUMMYFUNCTION("""COMPUTED_VALUE"""),"Quezon") -> Quezon | R56: =IFERROR(__xludf.DUMMYFUNCTION("""COMPUTED_VALUE"""),"4A") -> 4A
A57: =IFERROR(__xludf.DUMMYFUNCTION("""COMPUTED_VALUE"""),55.0) -> 55 | B57: =IFERROR(__xludf.DUMMYFUNCTION("""COMPUTED_VALUE"""),"MULANAY RICE FARMERS FEDERATION") -> MULANAY RICE FARMERS FEDERATION | C57: =IFERROR(__xludf.DUMMYFUNCTION("""COMPUTED_VALUE"""),"Barangay 1, Malunay, Quezon") -> Barangay 1, Malunay, Quezon | D57: =IFERROR(__xludf.DUMMYFUNCTION("""COMPUTED_VALUE"""),"Anacleto G. Palmero") -> Anacleto G. Palmero | E57: =IFERROR(__xludf.DUMMYFUNCTION("""COMPUTED_VALUE"""),"0930 990 4933") -> 0930 990 4933 | F57: =IFERROR(__xludf.DUMMYFUNCTION("""COMPUTED_VALUE"""),"RCEF 23-08-20 Rebidding") -> RCEF 23-08-20 Rebidding | G57: =IFERROR(__xludf.DUMMYFUNCTION("""COMPUTED_VALUE"""),1.0) -> 1 | H57: =IFERROR(__xludf.DUMMYFUNCTION("""COMPUTED_VALUE"""),17729.0) -> 17729 | I57: =IFERROR(__xludf.DUMMYFUNCTION("""COMPUTED_VALUE"""),"KMC5825 AVRFPV0023") -> KMC5825 AVRFPV0023 | J57: =IFERROR(__xludf.DUMMYFUNCTION("""COMPUTED_VALUE"""),"PTS100263") -> PTS100263 | K57: =IFERROR(__xludf.DUMMYFUNCTION("""COMPUTED_VALUE"""),"R-SERIES 242 PH") -> R-SERIES 242 PH | L57: =IFERROR(__xludf.DUMMYFUNCTION("""COMPUTED_VALUE"""),"LSGW1750 RMP 24020429") -> LSGW1750 RMP 24020429 | M57: =IFERROR(__xludf.DUMMYFUNCTION("""COMPUTED_VALUE"""),"WDP40 RMP 24020250") -> WDP40 RMP 24020250 | O57: =IFERROR(__xludf.DUMMYFUNCTION("""COMPUTED_VALUE"""),"Barangay 1") -> Barangay 1 | P57: =IFERROR(__xludf.DUMMYFUNCTION("""COMPUTED_VALUE"""),"Malunay") -> Malunay | Q57: =IFERROR(__xludf.DUMMYFUNCTION("""COMPUTED_VALUE"""),"Quezon") -> Quezon | R57: =IFERROR(__xludf.DUMMYFUNCTION("""COMPUTED_VALUE"""),"4A") -> 4A
A58: =IFERROR(__xludf.DUMMYFUNCTION("""COMPUTED_VALUE"""),56.0) -> 56 | B58: =IFERROR(__xludf.DUMMYFUNCTION("""COMPUTED_VALUE"""),"BARANGAY SAN LUIS 1 HEALTHY FARMING ASSOCIATION") -> BARANGAY SAN LUIS 1 HEALTHY FARMING ASSOCIATION | C58: =IFERROR(__xludf.DUMMYFUNCTION("""COMPUTED_VALUE"""),"San Luis 1, Guinayangan, Quezon") -> San Luis 1, Guinayangan, Quezon | D58: =IFERROR(__xludf.DUMMYFUNCTION("""COMPUTED_VALUE"""),"Avelino A. Tolentino") -> Avelino A. Tolentino | E58: =IFERROR(__xludf.DUMMYFUNCTION("""COMPUTED_VALUE"""),"0930 704 3885") -> 0930 704 3885 | F58: =IFERROR(__xludf.DUMMYFUNCTION("""COMPUTED_VALUE"""),"RCEF 23-08-20 Rebidding") -> RCEF 23-08-20 Rebidding | G58: =IFERROR(__xludf.DUMMYFUNCTION("""COMPUTED_VALUE"""),1.0) -> 1 | H58: =IFERROR(__xludf.DUMMYFUNCTION("""COMPUTED_VALUE"""),17730.0) -> 17730 | I58: =IFERROR(__xludf.DUMMYFUNCTION("""COMPUTED_VALUE"""),"KMC5825 AKRFPV0308") -> KMC5825 AKRFPV0308 | J58: =IFERROR(__xludf.DUMMYFUNCTION("""COMPUTED_VALUE"""),"RTS100206") -> RTS100206 | K58: =IFERROR(__xludf.DUMMYFUNCTION("""COMPUTED_VALUE"""),"R-SERIES 153 PH") -> R-SERIES 153 PH | L58: =IFERROR(__xludf.DUMMYFUNCTION("""COMPUTED_VALUE"""),"LSGW1750 RMP 24010188") -> LSGW1750 RMP 24010188 | M58: =IFERROR(__xludf.DUMMYFUNCTION("""COMPUTED_VALUE"""),"WDP40 RMP 24020247") -> WDP40 RMP 24020247 | O58: =IFERROR(__xludf.DUMMYFUNCTION("""COMPUTED_VALUE"""),"San Luis 1") -> San Luis 1 | P58: =IFERROR(__xludf.DUMMYFUNCTION("""COMPUTED_VALUE"""),"Guinayangan") -> Guinayangan | Q58: =IFERROR(__xludf.DUMMYFUNCTION("""COMPUTED_VALUE"""),"Quezon") -> Quezon | R58: =IFERROR(__xludf.DUMMYFUNCTION("""COMPUTED_VALUE"""),"4A") -> 4A
A59: =IFERROR(__xludf.DUMMYFUNCTION("""COMPUTED_VALUE"""),57.0) -> 57 | B59: =IFERROR(__xludf.DUMMYFUNCTION("""COMPUTED_VALUE"""),"BARANGAY BUENAVISTA FARMERS ASSOCIATION") -> BARANGAY BUENAVISTA FARMERS ASSOCIATION | C59: =IFERROR(__xludf.DUMMYFUNCTION("""COMPUTED_VALUE"""),"Buenavista, Lopez, Quezon") -> Buenavista, Lopez, Quezon | D59: =IFERROR(__xludf.DUMMYFUNCTION("""COMPUTED_VALUE"""),"Victor S. Pilarca") -> Victor S. Pilarca | E59: =IFERROR(__xludf.DUMMYFUNCTION("""COMPUTED_VALUE"""),"0906 616 3414") -> 0906 616 3414 | F59: =IFERROR(__xludf.DUMMYFUNCTION("""COMPUTED_VALUE"""),"RCEF 23-08-20 Rebidding") -> RCEF 23-08-20 Rebidding | G59: =IFERROR(__xludf.DUMMYFUNCTION("""COMPUTED_VALUE"""),1.0) -> 1 | H59: =IFERROR(__xludf.DUMMYFUNCTION("""COMPUTED_VALUE"""),17731.0) -> 17731 | I59: =IFERROR(__xludf.DUMMYFUNCTION("""COMPUTED_VALUE"""),"KMC5825 AERFPV0271") -> KMC5825 AERFPV0271 | J59: =IFERROR(__xludf.DUMMYFUNCTION("""COMPUTED_VALUE"""),"RTS100110") -> RTS100110 | K59: =IFERROR(__xludf.DUMMYFUNCTION("""COMPUTED_VALUE"""),"R-SERIES 063 PH") -> R-SERIES 063 PH | L59: =IFERROR(__xludf.DUMMYFUNCTION("""COMPUTED_VALUE"""),"LSGW1750 RMP 24010181") -> LSGW1750 RMP 24010181 | M59: =IFERROR(__xludf.DUMMYFUNCTION("""COMPUTED_VALUE"""),"WDP40 RMP 24010112") -> WDP40 RMP 24010112 | O59: =IFERROR(__xludf.DUMMYFUNCTION("""COMPUTED_VALUE"""),"Buenavista") -> Buenavista | P59: =IFERROR(__xludf.DUMMYFUNCTION("""COMPUTED_VALUE"""),"Lopez") -> Lopez | Q59: =IFERROR(__xludf.DUMMYFUNCTION("""COMPUTED_VALUE"""),"Quezon") -> Quezon | R59: =IFERROR(__xludf.DUMMYFUNCTION("""COMPUTED_VALUE"""),"4A") -> 4A
A60: =IFERROR(__xludf.DUMMYFUNCTION("""COMPUTED_VALUE"""),58.0) -> 58 | B60: =IFERROR(__xludf.DUMMYFUNCTION("""COMPUTED_VALUE"""),"SAN ROQUE FARMERS ASSOCIATION") -> SAN ROQUE FARMERS ASSOCIATION | C60: =IFERROR(__xludf.DUMMYFUNCTION("""COMPUTED_VALUE"""),"San Roque, Lopez, Quezon") -> San Roque, Lopez, Quezon | D60: =IFERROR(__xludf.DUMMYFUNCTION("""COMPUTED_VALUE"""),"Rodelito I. Abella") -> Rodelito I. Abella | E60: =IFERROR(__xludf.DUMMYFUNCTION("""COMPUTED_VALUE"""),"0948 038 7844") -> 0948 038 7844 | F60: =IFERROR(__xludf.DUMMYFUNCTION("""COMPUTED_VALUE"""),"RCEF 23-08-20 Rebidding") -> RCEF 23-08-20 Rebidding | G60: =IFERROR(__xludf.DUMMYFUNCTION("""COMPUTED_VALUE"""),1.0) -> 1 | H60: =IFERROR(__xludf.DUMMYFUNCTION("""COMPUTED_VALUE"""),17732.0) -> 17732 | I60: =IFERROR(__xludf.DUMMYFUNCTION("""COMPUTED_VALUE"""),"KMC5825 AARFPV0220") -> KMC5825 AARFPV0220 | J60: =IFERROR(__xludf.DUMMYFUNCTION("""COMPUTED_VALUE"""),"RTS100119") -> RTS100119 | K60: =IFERROR(__xludf.DUMMYFUNCTION("""COMPUTED_VALUE"""),"R-SERIES275 PH") -> R-SERIES275 PH | L60: =IFERROR(__xludf.DUMMYFUNCTION("""COMPUTED_VALUE"""),"LSGW1750 RMP 24010183") -> LSGW1750 RMP 24010183 | M60: =IFERROR(__xludf.DUMMYFUNCTION("""COMPUTED_VALUE"""),"WDP40 RMP 24010109") -> WDP40 RMP 24010109 | O60: =IFERROR(__xludf.DUMMYFUNCTION("""COMPUTED_VALUE"""),"San Roque") -> San Roque | P60: =IFERROR(__xludf.DUMMYFUNCTION("""COMPUTED_VALUE"""),"Lopez") -> Lopez | Q60: =IFERROR(__xludf.DUMMYFUNCTION("""COMPUTED_VALUE"""),"Quezon") -> Quezon | R60: =IFERROR(__xludf.DUMMYFUNCTION("""COMPUTED_VALUE"""),"4A") -> 4A
A61: =IFERROR(__xludf.DUMMYFUNCTION("""COMPUTED_VALUE"""),59.0) -> 59 | B61: =IFERROR(__xludf.DUMMYFUNCTION("""COMPUTED_VALUE"""),"RIMAPI Farmers Association") -> RIMAPI Farmers Association | C61: =IFERROR(__xludf.DUMMYFUNCTION("""COMPUTED_VALUE"""),"Mainit Sur, Perez, Quezon") -> Mainit Sur, Perez, Quezon | D61: =IFERROR(__xludf.DUMMYFUNCTION("""COMPUTED_VALUE"""),"Antonio S. Regodon") -> Antonio S. Regodon | E61: =IFERROR(__xludf.DUMMYFUNCTION("""COMPUTED_VALUE"""),"0917 325 8937 (MAO)") -> 0917 325 8937 (MAO) | F61: =IFERROR(__xludf.DUMMYFUNCTION("""COMPUTED_VALUE"""),"RCEF 23-08-20 Rebidding") -> RCEF 23-08-20 Rebidding | G61: =IFERROR(__xludf.DUMMYFUNCTION("""COMPUTED_VALUE"""),1.0) -> 1 | H61: =IFERROR(__xludf.DUMMYFUNCTION("""COMPUTED_VALUE"""),17733.0) -> 17733 | I61: =IFERROR(__xludf.DUMMYFUNCTION("""COMPUTED_VALUE"""),"KMC5825 ACRFPV0330") -> KMC5825 ACRFPV0330 | J61: =IFERROR(__xludf.DUMMYFUNCTION("""COMPUTED_VALUE"""),"RTS100176") -> RTS100176 | K61: =IFERROR(__xludf.DUMMYFUNCTION("""COMPUTED_VALUE"""),"R-SERIES 155 PH") -> R-SERIES 155 PH | L61: =IFERROR(__xludf.DUMMYFUNCTION("""COMPUTED_VALUE"""),"LSGW1750 RMP 24020430") -> LSGW1750 RMP 24020430 | M61: =IFERROR(__xludf.DUMMYFUNCTION("""COMPUTED_VALUE"""),"WDP40 RMP 24020252") -> WDP40 RMP 24020252 | O61: =IFERROR(__xludf.DUMMYFUNCTION("""COMPUTED_VALUE"""),"Mainit Sur") -> Mainit Sur | P61: =IFERROR(__xludf.DUMMYFUNCTION("""COMPUTED_VALUE"""),"Perez") -> Perez | Q61: =IFERROR(__xludf.DUMMYFUNCTION("""COMPUTED_VALUE"""),"Quezon") -> Quezon | R61: =IFERROR(__xludf.DUMMYFUNCTION("""COMPUTED_VALUE"""),"4A") -> 4A
A62: =IFERROR(__xludf.DUMMYFUNCTION("""COMPUTED_VALUE"""),60.0) -> 60 | B62: =IFERROR(__xludf.DUMMYFUNCTION("""COMPUTED_VALUE"""),"BUKAL FARMERS ASSOCIATION") -> BUKAL FARMERS ASSOCIATION | C62: =IFERROR(__xludf.DUMMYFUNCTION("""COMPUTED_VALUE"""),"Bukal, Tagkawayan, Quezon") -> Bukal, Tagkawayan, Quezon | D62: =IFERROR(__xludf.DUMMYFUNCTION("""COMPUTED_VALUE"""),"Sergio G. Macaraig Jr.") -> Sergio G. Macaraig Jr. | E62: =IFERROR(__xludf.DUMMYFUNCTION("""COMPUTED_VALUE"""),"0909 050 0561") -> 0909 050 0561 | F62: =IFERROR(__xludf.DUMMYFUNCTION("""COMPUTED_VALUE"""),"RCEF 23-08-20 Rebidding") -> RCEF 23-08-20 Rebidding | G62: =IFERROR(__xludf.DUMMYFUNCTION("""COMPUTED_VALUE"""),1.0) -> 1 | H62: =IFERROR(__xludf.DUMMYFUNCTION("""COMPUTED_VALUE"""),17734.0) -> 17734 | I62: =IFERROR(__xludf.DUMMYFUNCTION("""COMPUTED_VALUE"""),"KMC5825 ATRFPV0337") -> KMC5825 ATRFPV0337 | J62: =IFERROR(__xludf.DUMMYFUNCTION("""COMPUTED_VALUE"""),"RTS100175") -> RTS100175 | K62: =IFERROR(__xludf.DUMMYFUNCTION("""COMPUTED_VALUE"""),"R-SERIES 273 PH") -> R-SERIES 273 PH | L62: =IFERROR(__xludf.DUMMYFUNCTION("""COMPUTED_VALUE"""),"LSGW1750 RMP 24020417") -> LSGW1750 RMP 24020417 | M62: =IFERROR(__xludf.DUMMYFUNCTION("""COMPUTED_VALUE"""),"WDP40 RMP 24010135") -> WDP40 RMP 24010135 | O62: =IFERROR(__xludf.DUMMYFUNCTION("""COMPUTED_VALUE"""),"Bukal") -> Bukal | P62: =IFERROR(__xludf.DUMMYFUNCTION("""COMPUTED_VALUE"""),"Tagkawayan") -> Tagkawayan | Q62: =IFERROR(__xludf.DUMMYFUNCTION("""COMPUTED_VALUE"""),"Quezon") -> Quezon | R62: =IFERROR(__xludf.DUMMYFUNCTION("""COMPUTED_VALUE"""),"4A") -> 4A
A63: =IFERROR(__xludf.DUMMYFUNCTION("""COMPUTED_VALUE"""),61.0) -> 61 | B63: =IFERROR(__xludf.DUMMYFUNCTION("""COMPUTED_VALUE"""),"AGOS NG PAG-ASA KATAKIAN IRRIGATORS' ASSOCIATION INCORPORATED") -> AGOS NG PAG-ASA KATAKIAN IRRIGATORS' ASSOCIATION INCORPORATED | C63: =IFERROR(__xludf.DUMMYFUNCTION("""COMPUTED_VALUE"""),"Landing, Tagkawayan, Quezon") -> Landing, Tagkawayan, Quezon | D63: =IFERROR(__xludf.DUMMYFUNCTION("""COMPUTED_VALUE"""),"Leonora T. Mangubat") -> Leonora T. Mangubat | E63: =IFERROR(__xludf.DUMMYFUNCTION("""COMPUTED_VALUE"""),"0998 333 6165") -> 0998 333 6165 | F63: =IFERROR(__xludf.DUMMYFUNCTION("""COMPUTED_VALUE"""),"RCEF 23-08-20 Rebidding") -> RCEF 23-08-20 Rebidding | G63: =IFERROR(__xludf.DUMMYFUNCTION("""COMPUTED_VALUE"""),1.0) -> 1 | H63: =IFERROR(__xludf.DUMMYFUNCTION("""COMPUTED_VALUE"""),17735.0) -> 17735 | I63: =IFERROR(__xludf.DUMMYFUNCTION("""COMPUTED_VALUE"""),"KMC5825 ALRFPV0283") -> KMC5825 ALRFPV0283 | J63: =IFERROR(__xludf.DUMMYFUNCTION("""COMPUTED_VALUE"""),"RTS100130") -> RTS100130 | K63: =IFERROR(__xludf.DUMMYFUNCTION("""COMPUTED_VALUE"""),"R-SERIES 061 PH") -> R-SERIES 061 PH | L63: =IFERROR(__xludf.DUMMYFUNCTION("""COMPUTED_VALUE"""),"LSGW1750 RMP 24010182") -> LSGW1750 RMP 24010182 | M63: =IFERROR(__xludf.DUMMYFUNCTION("""COMPUTED_VALUE"""),"WDP40 RMP 24030294") -> WDP40 RMP 24030294 | O63: =IFERROR(__xludf.DUMMYFUNCTION("""COMPUTED_VALUE"""),"Landing") -> Landing | P63: =IFERROR(__xludf.DUMMYFUNCTION("""COMPUTED_VALUE"""),"Tagkawayan") -> Tagkawayan | Q63: =IFERROR(__xludf.DUMMYFUNCTION("""COMPUTED_VALUE"""),"Quezon") -> Quezon | R63: =IFERROR(__xludf.DUMMYFUNCTION("""COMPUTED_VALUE"""),"4A") -> 4A
A64: =IFERROR(__xludf.DUMMYFUNCTION("""COMPUTED_VALUE"""),62.0) -> 62 | B64: =IFERROR(__xludf.DUMMYFUNCTION("""COMPUTED_VALUE"""),"BARANGAY PAYAPA FARMERS ASSOCIATION") -> BARANGAY PAYAPA FARMERS ASSOCIATION | C64: =IFERROR(__xludf.DUMMYFUNCTION("""COMPUTED_VALUE"""),"Payapa, Tagkawayan, Quezon") -> Payapa, Tagkawayan, Quezon | D64: =IFERROR(__xludf.DUMMYFUNCTION("""COMPUTED_VALUE"""),"Ferdinand R. Aguda") -> Ferdinand R. Aguda | E64: =IFERROR(__xludf.DUMMYFUNCTION("""COMPUTED_VALUE"""),"0939 140 1908 0951 864 2466") -> 0939 140 1908 0951 864 2466 | F64: =IFERROR(__xludf.DUMMYFUNCTION("""COMPUTED_VALUE"""),"RCEF 23-08-20 Rebidding") -> RCEF 23-08-20 Rebidding | G64: =IFERROR(__xludf.DUMMYFUNCTION("""COMPUTED_VALUE"""),1.0) -> 1 | H64: =IFERROR(__xludf.DUMMYFUNCTION("""COMPUTED_VALUE"""),17736.0) -> 17736 | I64: =IFERROR(__xludf.DUMMYFUNCTION("""COMPUTED_VALUE"""),"KMC5825 AHRFPV0205") -> KMC5825 AHRFPV0205 | J64: =IFERROR(__xludf.DUMMYFUNCTION("""COMPUTED_VALUE"""),"RTS100148") -> RTS100148 | K64: =IFERROR(__xludf.DUMMYFUNCTION("""COMPUTED_VALUE"""),"R-SERIES 171 PH") -> R-SERIES 171 PH | L64: =IFERROR(__xludf.DUMMYFUNCTION("""COMPUTED_VALUE"""),"LSGW1750 RMP 24020414") -> LSGW1750 RMP 24020414 | M64: =IFERROR(__xludf.DUMMYFUNCTION("""COMPUTED_VALUE"""),"WDP40 RMP 24020243") -> WDP40 RMP 24020243 | O64: =IFERROR(__xludf.DUMMYFUNCTION("""COMPUTED_VALUE"""),"Payapa") -> Payapa | P64: =IFERROR(__xludf.DUMMYFUNCTION("""COMPUTED_VALUE"""),"Tagkawayan") -> Tagkawayan | Q64: =IFERROR(__xludf.DUMMYFUNCTION("""COMPUTED_VALUE"""),"Quezon") -> Quezon | R64: =IFERROR(__xludf.DUMMYFUNCTION("""COMPUTED_VALUE"""),"4A") -> 4A
A65: =IFERROR(__xludf.DUMMYFUNCTION("""COMPUTED_VALUE"""),63.0) -> 63 | B65: =IFERROR(__xludf.DUMMYFUNCTION("""COMPUTED_VALUE"""),"ALLIANCE OF FARMERS ASSOCIATION OF ORCONUMA (AFAO)") -> ALLIANCE OF FARMERS ASSOCIATION OF ORCONUMA (AFAO) | C65: =IFERROR(__xludf.DUMMYFUNCTION("""COMPUTED_VALUE"""),"Orconuma, Bongabong, Oriental Mindoro") -> Orconuma, Bongabong, Oriental Mindoro | D65: =IFERROR(__xludf.DUMMYFUNCTION("""COMPUTED_VALUE"""),"MAJELINE F. ARENILLO") -> MAJELINE F. ARENILLO | E65: =IFERROR(__xludf.DUMMYFUNCTION("""COMPUTED_VALUE"""),"0905 141 0014") -> 0905 141 0014 | F65: =IFERROR(__xludf.DUMMYFUNCTION("""COMPUTED_VALUE"""),"RCEF 23-08-20 Rebidding") -> RCEF 23-08-20 Rebidding | G65: =IFERROR(__xludf.DUMMYFUNCTION("""COMPUTED_VALUE"""),1.0) -> 1 | H65: =IFERROR(__xludf.DUMMYFUNCTION("""COMPUTED_VALUE"""),17779.0) -> 17779 | I65: =IFERROR(__xludf.DUMMYFUNCTION("""COMPUTED_VALUE"""),"KMC 5825 APPFPV0093") -> KMC 5825 APPFPV0093 | J65: =IFERROR(__xludf.DUMMYFUNCTION("""COMPUTED_VALUE"""),"PTS100080") -> PTS100080 | K65: =IFERROR(__xludf.DUMMYFUNCTION("""COMPUTED_VALUE"""),"R-SERIES 087 PH") -> R-SERIES 087 PH | L65: =IFERROR(__xludf.DUMMYFUNCTION("""COMPUTED_VALUE"""),"LSGW1750-RMP-2312126") -> LSGW1750-RMP-2312126 | M65: =IFERROR(__xludf.DUMMYFUNCTION("""COMPUTED_VALUE"""),"WDP40-RMP-2312032") -> WDP40-RMP-2312032 | O65: =IFERROR(__xludf.DUMMYFUNCTION("""COMPUTED_VALUE"""),"Orconuma") -> Orconuma | P65: =IFERROR(__xludf.DUMMYFUNCTION("""COMPUTED_VALUE"""),"Bongabong") -> Bongabong | Q65: =IFERROR(__xludf.DUMMYFUNCTION("""COMPUTED_VALUE"""),"Oriental Mindoro") -> Oriental Mindoro | R65: =IFERROR(__xludf.DUMMYFUNCTION("""COMPUTED_VALUE"""),"4B") -> 4B
A66: =IFERROR(__xludf.DUMMYFUNCTION("""COMPUTED_VALUE"""),64.0) -> 64 | B66: =IFERROR(__xludf.DUMMYFUNCTION("""COMPUTED_VALUE"""),"NAGKAKAISANG SAMAHAN NG MAGPAPATUBIG NG CAMBUNANG, INC.") -> NAGKAKAISANG SAMAHAN NG MAGPAPATUBIG NG CAMBUNANG, INC. | C66: =IFERROR(__xludf.DUMMYFUNCTION("""COMPUTED_VALUE"""),"Cambunang, Bulalacao, Oriental Mindoro") -> Cambunang, Bulalacao, Oriental Mindoro | D66: =IFERROR(__xludf.DUMMYFUNCTION("""COMPUTED_VALUE"""),"RICHARD D. FABILA") -> RICHARD D. FABILA | E66: =IFERROR(__xludf.DUMMYFUNCTION("""COMPUTED_VALUE"""),"0948 028 7733") -> 0948 028 7733 | F66: =IFERROR(__xludf.DUMMYFUNCTION("""COMPUTED_VALUE"""),"RCEF 23-08-20 Rebidding") -> RCEF 23-08-20 Rebidding | G66: =IFERROR(__xludf.DUMMYFUNCTION("""COMPUTED_VALUE"""),1.0) -> 1 | H66: =IFERROR(__xludf.DUMMYFUNCTION("""COMPUTED_VALUE"""),17780.0) -> 17780 | I66: =IFERROR(__xludf.DUMMYFUNCTION("""COMPUTED_VALUE"""),"KMC5825APPFPV0092") -> KMC5825APPFPV0092 | J66: =IFERROR(__xludf.DUMMYFUNCTION("""COMPUTED_VALUE"""),"PTS100120") -> PTS100120 | K66: =IFERROR(__xludf.DUMMYFUNCTION("""COMPUTED_VALUE"""),"R-SERIES 106 PH") -> R-SERIES 106 PH | L66: =IFERROR(__xludf.DUMMYFUNCTION("""COMPUTED_VALUE"""),"LSGW1750-RMP-2312121") -> LSGW1750-RMP-2312121 | M66: =IFERROR(__xludf.DUMMYFUNCTION("""COMPUTED_VALUE"""),"WDP40-RMP-2312001") -> WDP40-RMP-2312001 | O66: =IFERROR(__xludf.DUMMYFUNCTION("""COMPUTED_VALUE"""),"Cambunang") -> Cambunang | P66: =IFERROR(__xludf.DUMMYFUNCTION("""COMPUTED_VALUE"""),"Bulalacao") -> Bulalacao | Q66: =IFERROR(__xludf.DUMMYFUNCTION("""COMPUTED_VALUE"""),"Oriental Mindoro") -> Oriental Mindoro | R66: =IFERROR(__xludf.DUMMYFUNCTION("""COMPUTED_VALUE"""),"4B") -> 4B
A67: =IFERROR(__xludf.DUMMYFUNCTION("""COMPUTED_VALUE"""),65.0) -> 65 | B67: =IFERROR(__xludf.DUMMYFUNCTION("""COMPUTED_VALUE"""),"SAMAHANG MAGPAPATUBIG NG BALUGO STA. MARIA AT VILLA CELESTIAL INC.") -> SAMAHANG MAGPAPATUBIG NG BALUGO STA. MARIA AT VILLA CELESTIAL INC. | C67: =IFERROR(__xludf.DUMMYFUNCTION("""COMPUTED_VALUE"""),"Balugo, Mansalay, Oriental Mindoro") -> Balugo, Mansalay, Oriental Mindoro | D67: =IFERROR(__xludf.DUMMYFUNCTION("""COMPUTED_VALUE"""),"MARIVIC V. DIONISIO") -> MARIVIC V. DIONISIO | E67: =IFERROR(__xludf.DUMMYFUNCTION("""COMPUTED_VALUE"""),"0975 658 0836") -> 0975 658 0836 | F67: =IFERROR(__xludf.DUMMYFUNCTION("""COMPUTED_VALUE"""),"RCEF 23-08-20 Rebidding") -> RCEF 23-08-20 Rebidding | G67: =IFERROR(__xludf.DUMMYFUNCTION("""COMPUTED_VALUE"""),1.0) -> 1 | H67: =IFERROR(__xludf.DUMMYFUNCTION("""COMPUTED_VALUE"""),17781.0) -> 17781 | I67: =IFERROR(__xludf.DUMMYFUNCTION("""COMPUTED_VALUE"""),"KMC 5825 AJPFPV0159") -> KMC 5825 AJPFPV0159 | J67: =IFERROR(__xludf.DUMMYFUNCTION("""COMPUTED_VALUE"""),"PTS100136") -> PTS100136 | K67: =IFERROR(__xludf.DUMMYFUNCTION("""COMPUTED_VALUE"""),"R-SERIES 095 PH") -> R-SERIES 095 PH | L67: =IFERROR(__xludf.DUMMYFUNCTION("""COMPUTED_VALUE"""),"LSGW1750-RMP-2312095") -> LSGW1750-RMP-2312095 | M67: =IFERROR(__xludf.DUMMYFUNCTION("""COMPUTED_VALUE"""),"WDP40-RMP-2312002") -> WDP40-RMP-2312002 | O67: =IFERROR(__xludf.DUMMYFUNCTION("""COMPUTED_VALUE"""),"Balugo") -> Balugo | P67: =IFERROR(__xludf.DUMMYFUNCTION("""COMPUTED_VALUE"""),"Mansalay") -> Mansalay | Q67: =IFERROR(__xludf.DUMMYFUNCTION("""COMPUTED_VALUE"""),"Oriental Mindoro") -> Oriental Mindoro | R67: =IFERROR(__xludf.DUMMYFUNCTION("""COMPUTED_VALUE"""),"4B") -> 4B
A68: =IFERROR(__xludf.DUMMYFUNCTION("""COMPUTED_VALUE"""),66.0) -> 66 | B68: =IFERROR(__xludf.DUMMYFUNCTION("""COMPUTED_VALUE"""),"TANATANAEN FARMERS IRRIGATOR'S ASSOCIATION, INC.") -> TANATANAEN FARMERS IRRIGATOR'S ASSOCIATION, INC. | C68: =IFERROR(__xludf.DUMMYFUNCTION("""COMPUTED_VALUE"""),"Tanatanaon (Mainland), Dumaran, Palawan") -> Tanatanaon (Mainland), Dumaran, Palawan | D68: =IFERROR(__xludf.DUMMYFUNCTION("""COMPUTED_VALUE"""),"Reden Mark S. Pineda") -> Reden Mark S. Pineda | E68: =IFERROR(__xludf.DUMMYFUNCTION("""COMPUTED_VALUE"""),"0950 608 7527") -> 0950 608 7527 | F68: =IFERROR(__xludf.DUMMYFUNCTION("""COMPUTED_VALUE"""),"RCEF 23-08-20 Rebidding") -> RCEF 23-08-20 Rebidding | G68: =IFERROR(__xludf.DUMMYFUNCTION("""COMPUTED_VALUE"""),1.0) -> 1 | H68: =IFERROR(__xludf.DUMMYFUNCTION("""COMPUTED_VALUE"""),17941.0) -> 17941 | I68: =IFERROR(__xludf.DUMMYFUNCTION("""COMPUTED_VALUE"""),"KMC 5825 ALPFPV0149") -> KMC 5825 ALPFPV0149 | J68: =IFERROR(__xludf.DUMMYFUNCTION("""COMPUTED_VALUE"""),"PTS 100146") -> PTS 100146 | K68: =IFERROR(__xludf.DUMMYFUNCTION("""COMPUTED_VALUE"""),"R-SERIES 136 PH") -> R-SERIES 136 PH | L68: =IFERROR(__xludf.DUMMYFUNCTION("""COMPUTED_VALUE"""),"LSGW1750 RMP 2312054") -> LSGW1750 RMP 2312054 | M68: =IFERROR(__xludf.DUMMYFUNCTION("""COMPUTED_VALUE"""),"WDP40 RMP 2312084") -> WDP40 RMP 2312084 | O68: =IFERROR(__xludf.DUMMYFUNCTION("""COMPUTED_VALUE"""),"Tanatanaon (Mainland)") -> Tanatanaon (Mainland) | P68: =IFERROR(__xludf.DUMMYFUNCTION("""COMPUTED_VALUE"""),"Dumaran") -> Dumaran | Q68: =IFERROR(__xludf.DUMMYFUNCTION("""COMPUTED_VALUE"""),"Palawan") -> Palawan | R68: =IFERROR(__xludf.DUMMYFUNCTION("""COMPUTED_VALUE"""),"4B") -> 4B
A69: =IFERROR(__xludf.DUMMYFUNCTION("""COMPUTED_VALUE"""),67.0) -> 67 | B69: =IFERROR(__xludf.DUMMYFUNCTION("""COMPUTED_VALUE"""),"PUROK CALAPARAN MAGSAYSAY FARMERS ASSOCIATION") -> PUROK CALAPARAN MAGSAYSAY FARMERS ASSOCIATION | C69: =IFERROR(__xludf.DUMMYFUNCTION("""COMPUTED_VALUE"""),"Magsaysay, Dumaran, Palawan") -> Magsaysay, Dumaran, Palawan | D69: =IFERROR(__xludf.DUMMYFUNCTION("""COMPUTED_VALUE"""),"Mecheil Mangalao") -> Mecheil Mangalao | E69: =IFERROR(__xludf.DUMMYFUNCTION("""COMPUTED_VALUE"""),9.128337112E9) -> 9128337112 | F69: =IFERROR(__xludf.DUMMYFUNCTION("""COMPUTED_VALUE"""),"RCEF 23-08-20 Rebidding") -> RCEF 23-08-20 Rebidding | G69: =IFERROR(__xludf.DUMMYFUNCTION("""COMPUTED_VALUE"""),1.0) -> 1 | H69: =IFERROR(__xludf.DUMMYFUNCTION("""COMPUTED_VALUE"""),17942.0) -> 17942 | I69: =IFERROR(__xludf.DUMMYFUNCTION("""COMPUTED_VALUE"""),"KMC 5825 AEPFPV0140") -> KMC 5825 AEPFPV0140 | J69: =IFERROR(__xludf.DUMMYFUNCTION("""COMPUTED_VALUE"""),"PTS 100118") -> PTS 100118 | K69: =IFERROR(__xludf.DUMMYFUNCTION("""COMPUTED_VALUE"""),"R-SERIES 141 PH") -> R-SERIES 141 PH | L69: =IFERROR(__xludf.DUMMYFUNCTION("""COMPUTED_VALUE"""),"LSGW1750 RMP 2312057") -> LSGW1750 RMP 2312057 | M69: =IFERROR(__xludf.DUMMYFUNCTION("""COMPUTED_VALUE"""),"WDP40 RMP 2312093") -> WDP40 RMP 2312093 | O69: =IFERROR(__xludf.DUMMYFUNCTION("""COMPUTED_VALUE"""),"Magsaysay") -> Magsaysay | P69: =IFERROR(__xludf.DUMMYFUNCTION("""COMPUTED_VALUE"""),"Dumaran") -> Dumaran | Q69: =IFERROR(__xludf.DUMMYFUNCTION("""COMPUTED_VALUE"""),"Palawan") -> Palawan | R69: =IFERROR(__xludf.DUMMYFUNCTION("""COMPUTED_VALUE"""),"4B") -> 4B
A70: =IFERROR(__xludf.DUMMYFUNCTION("""COMPUTED_VALUE"""),68.0) -> 68 | B70: =IFERROR(__xludf.DUMMYFUNCTION("""COMPUTED_VALUE"""),"ABERAWAN FARMER'S ASSOCIATION (AFA)") -> ABERAWAN FARMER'S ASSOCIATION (AFA) | C70: =IFERROR(__xludf.DUMMYFUNCTION("""COMPUTED_VALUE"""),"Aberawan, El Nido, Palawan") -> Aberawan, El Nido, Palawan | D70: =IFERROR(__xludf.DUMMYFUNCTION("""COMPUTED_VALUE"""),"Marlon R. Panoncio") -> Marlon R. Panoncio | E70: =IFERROR(__xludf.DUMMYFUNCTION("""COMPUTED_VALUE"""),"0975 55570164") -> 0975 55570164 | F70: =IFERROR(__xludf.DUMMYFUNCTION("""COMPUTED_VALUE"""),"RCEF 23-08-20 Rebidding") -> RCEF 23-08-20 Rebidding | G70: =IFERROR(__xludf.DUMMYFUNCTION("""COMPUTED_VALUE"""),1.0) -> 1 | H70: =IFERROR(__xludf.DUMMYFUNCTION("""COMPUTED_VALUE"""),17943.0) -> 17943 | I70: =IFERROR(__xludf.DUMMYFUNCTION("""COMPUTED_VALUE"""),"KMC 5825 AHPFPV00055") -> KMC 5825 AHPFPV00055 | J70: =IFERROR(__xludf.DUMMYFUNCTION("""COMPUTED_VALUE"""),"PTS 100133") -> PTS 100133 | K70: =IFERROR(__xludf.DUMMYFUNCTION("""COMPUTED_VALUE"""),"R-SERIES 150 PH") -> R-SERIES 150 PH | L70: =IFERROR(__xludf.DUMMYFUNCTION("""COMPUTED_VALUE"""),"LSGW1750 RMP 2312087") -> LSGW1750 RMP 2312087 | M70: =IFERROR(__xludf.DUMMYFUNCTION("""COMPUTED_VALUE"""),"WDP40 RMP 2312094") -> WDP40 RMP 2312094 | O70: =IFERROR(__xludf.DUMMYFUNCTION("""COMPUTED_VALUE"""),"Aberawan") -> Aberawan | P70: =IFERROR(__xludf.DUMMYFUNCTION("""COMPUTED_VALUE"""),"El Nido") -> El Nido | Q70: =IFERROR(__xludf.DUMMYFUNCTION("""COMPUTED_VALUE"""),"Palawan") -> Palawan | R70: =IFERROR(__xludf.DUMMYFUNCTION("""COMPUTED_VALUE"""),"4B") -> 4B
A71: =IFERROR(__xludf.DUMMYFUNCTION("""COMPUTED_VALUE"""),69.0) -> 69 | B71: =IFERROR(__xludf.DUMMYFUNCTION("""COMPUTED_VALUE"""),"SANDOVAL FARMERS ASSOCIATION") -> SANDOVAL FARMERS ASSOCIATION | C71: =IFERROR(__xludf.DUMMYFUNCTION("""COMPUTED_VALUE"""),"Sandoval, Roxas, Palawan") -> Sandoval, Roxas, Palawan | D71: =IFERROR(__xludf.DUMMYFUNCTION("""COMPUTED_VALUE"""),"Philip G. Flores") -> Philip G. Flores | E71: =IFERROR(__xludf.DUMMYFUNCTION("""COMPUTED_VALUE"""),9.261966722E9) -> 9261966722 | F71: =IFERROR(__xludf.DUMMYFUNCTION("""COMPUTED_VALUE"""),"RCEF 23-08-20 Rebidding") -> RCEF 23-08-20 Rebidding | G71: =IFERROR(__xludf.DUMMYFUNCTION("""COMPUTED_VALUE"""),1.0) -> 1 | H71: =IFERROR(__xludf.DUMMYFUNCTION("""COMPUTED_VALUE"""),17944.0) -> 17944 | I71: =IFERROR(__xludf.DUMMYFUNCTION("""COMPUTED_VALUE"""),"KMC 5825 AEPFPV0090") -> KMC 5825 AEPFPV0090 | J71: =IFERROR(__xludf.DUMMYFUNCTION("""COMPUTED_VALUE"""),"PTS 100122") -> PTS 100122 | K71: =IFERROR(__xludf.DUMMYFUNCTION("""COMPUTED_VALUE"""),"R-SERIES 135 PH") -> R-SERIES 135 PH | L71: =IFERROR(__xludf.DUMMYFUNCTION("""COMPUTED_VALUE"""),"LSGW1750 RMP 2312065") -> LSGW1750 RMP 2312065 | M71: =IFERROR(__xludf.DUMMYFUNCTION("""COMPUTED_VALUE"""),"WDP40 RMP 2312098") -> WDP40 RMP 2312098 | O71: =IFERROR(__xludf.DUMMYFUNCTION("""COMPUTED_VALUE"""),"Sandoval") -> Sandoval | P71: =IFERROR(__xludf.DUMMYFUNCTION("""COMPUTED_VALUE"""),"Roxas") -> Roxas | Q71: =IFERROR(__xludf.DUMMYFUNCTION("""COMPUTED_VALUE"""),"Palawan") -> Palawan | R71: =IFERROR(__xludf.DUMMYFUNCTION("""COMPUTED_VALUE"""),"4B") -> 4B
A72: =IFERROR(__xludf.DUMMYFUNCTION("""COMPUTED_VALUE"""),70.0) -> 70 | B72: =IFERROR(__xludf.DUMMYFUNCTION("""COMPUTED_VALUE"""),"PAMUAYAN FARMERS ASSOCIATION") -> PAMUAYAN FARMERS ASSOCIATION | C72: =IFERROR(__xludf.DUMMYFUNCTION("""COMPUTED_VALUE"""),"Barton, San Vicente, Palawan") -> Barton, San Vicente, Palawan | D72: =IFERROR(__xludf.DUMMYFUNCTION("""COMPUTED_VALUE"""),"Joel C. Capindo") -> Joel C. Capindo | E72: =IFERROR(__xludf.DUMMYFUNCTION("""COMPUTED_VALUE"""),9.309127724E9) -> 9309127724 | F72: =IFERROR(__xludf.DUMMYFUNCTION("""COMPUTED_VALUE"""),"RCEF 23-08-20 Rebidding") -> RCEF 23-08-20 Rebidding | G72: =IFERROR(__xludf.DUMMYFUNCTION("""COMPUTED_VALUE"""),1.0) -> 1 | H72: =IFERROR(__xludf.DUMMYFUNCTION("""COMPUTED_VALUE"""),17945.0) -> 17945 | I72: =IFERROR(__xludf.DUMMYFUNCTION("""COMPUTED_VALUE"""),"KMC 5825 ATPFPV0061") -> KMC 5825 ATPFPV0061 | J72: =IFERROR(__xludf.DUMMYFUNCTION("""COMPUTED_VALUE"""),"PTS 100149") -> PTS 100149 | K72: =IFERROR(__xludf.DUMMYFUNCTION("""COMPUTED_VALUE"""),"R-SERIES 129 PH") -> R-SERIES 129 PH | L72: =IFERROR(__xludf.DUMMYFUNCTION("""COMPUTED_VALUE"""),"LSGW1750 RMP 2312069") -> LSGW1750 RMP 2312069 | M72: =IFERROR(__xludf.DUMMYFUNCTION("""COMPUTED_VALUE"""),"WDP40 RMP 2312104") -> WDP40 RMP 2312104 | O72: =IFERROR(__xludf.DUMMYFUNCTION("""COMPUTED_VALUE"""),"Barton") -> Barton | P72: =IFERROR(__xludf.DUMMYFUNCTION("""COMPUTED_VALUE"""),"San Vicente") -> San Vicente | Q72: =IFERROR(__xludf.DUMMYFUNCTION("""COMPUTED_VALUE"""),"Palawan") -> Palawan | R72: =IFERROR(__xludf.DUMMYFUNCTION("""COMPUTED_VALUE"""),"4B") -> 4B
A73: =IFERROR(__xludf.DUMMYFUNCTION("""COMPUTED_VALUE"""),71.0) -> 71 | B73: =IFERROR(__xludf.DUMMYFUNCTION("""COMPUTED_VALUE"""),"SANDOVAL FARMERS ASSOCIATON") -> SANDOVAL FARMERS ASSOCIATON | C73: =IFERROR(__xludf.DUMMYFUNCTION("""COMPUTED_VALUE"""),"Sandoval, Taytay, Palawan") -> Sandoval, Taytay, Palawan | D73: =IFERROR(__xludf.DUMMYFUNCTION("""COMPUTED_VALUE"""),"Isagani L. Repe") -> Isagani L. Repe | E73: =IFERROR(__xludf.DUMMYFUNCTION("""COMPUTED_VALUE"""),9.466248004E9) -> 9466248004 | F73: =IFERROR(__xludf.DUMMYFUNCTION("""COMPUTED_VALUE"""),"RCEF 23-08-20 Rebidding") -> RCEF 23-08-20 Rebidding | G73: =IFERROR(__xludf.DUMMYFUNCTION("""COMPUTED_VALUE"""),1.0) -> 1 | H73: =IFERROR(__xludf.DUMMYFUNCTION("""COMPUTED_VALUE"""),17946.0) -> 17946 | I73: =IFERROR(__xludf.DUMMYFUNCTION("""COMPUTED_VALUE"""),"KMC 5825 APFPV0076") -> KMC 5825 APFPV0076 | J73: =IFERROR(__xludf.DUMMYFUNCTION("""COMPUTED_VALUE"""),"PTS 100060") -> PTS 100060 | K73: =IFERROR(__xludf.DUMMYFUNCTION("""COMPUTED_VALUE"""),"R-SERIES 130 PH") -> R-SERIES 130 PH | L73: =IFERROR(__xludf.DUMMYFUNCTION("""COMPUTED_VALUE"""),"LSGW1750 RMP 2312052") -> LSGW1750 RMP 2312052 | M73: =IFERROR(__xludf.DUMMYFUNCTION("""COMPUTED_VALUE"""),"WDP40 RMP 2312081") -> WDP40 RMP 2312081 | O73: =IFERROR(__xludf.DUMMYFUNCTION("""COMPUTED_VALUE"""),"Sandoval") -> Sandoval | P73: =IFERROR(__xludf.DUMMYFUNCTION("""COMPUTED_VALUE"""),"Taytay") -> Taytay | Q73: =IFERROR(__xludf.DUMMYFUNCTION("""COMPUTED_VALUE"""),"Palawan") -> Palawan | R73: =IFERROR(__xludf.DUMMYFUNCTION("""COMPUTED_VALUE"""),"4B") -> 4B
A74: =IFERROR(__xludf.DUMMYFUNCTION("""COMPUTED_VALUE"""),72.0) -> 72 | B74: =IFERROR(__xludf.DUMMYFUNCTION("""COMPUTED_VALUE"""),"TAYSAY MINAHAW FARMER IRRIGATORS ASSOCIATION, INC.") -> TAYSAY MINAHAW FARMER IRRIGATORS ASSOCIATION, INC. | C74: =IFERROR(__xludf.DUMMYFUNCTION("""COMPUTED_VALUE"""),"Bono-Bono, Bataraza, Palawan") -> Bono-Bono, Bataraza, Palawan | D74: =IFERROR(__xludf.DUMMYFUNCTION("""COMPUTED_VALUE"""),"Eddie N. Sagun") -> Eddie N. Sagun | E74: =IFERROR(__xludf.DUMMYFUNCTION("""COMPUTED_VALUE"""),9.985315419E9) -> 9985315419 | F74: =IFERROR(__xludf.DUMMYFUNCTION("""COMPUTED_VALUE"""),"RCEF 23-08-20 Rebidding") -> RCEF 23-08-20 Rebidding | G74: =IFERROR(__xludf.DUMMYFUNCTION("""COMPUTED_VALUE"""),1.0) -> 1 | H74: =IFERROR(__xludf.DUMMYFUNCTION("""COMPUTED_VALUE"""),17947.0) -> 17947 | I74: =IFERROR(__xludf.DUMMYFUNCTION("""COMPUTED_VALUE"""),"KKC 5825 ALPFPV0104") -> KKC 5825 ALPFPV0104 | J74: =IFERROR(__xludf.DUMMYFUNCTION("""COMPUTED_VALUE"""),"PTS 100072") -> PTS 100072 | K74: =IFERROR(__xludf.DUMMYFUNCTION("""COMPUTED_VALUE"""),"R-SERIES 146 PH") -> R-SERIES 146 PH | L74: =IFERROR(__xludf.DUMMYFUNCTION("""COMPUTED_VALUE"""),"LSGW1750 RMP 2312063") -> LSGW1750 RMP 2312063 | M74: =IFERROR(__xludf.DUMMYFUNCTION("""COMPUTED_VALUE"""),"WDP40 RMP 2312086") -> WDP40 RMP 2312086 | O74: =IFERROR(__xludf.DUMMYFUNCTION("""COMPUTED_VALUE"""),"Bono-Bono") -> Bono-Bono | P74: =IFERROR(__xludf.DUMMYFUNCTION("""COMPUTED_VALUE"""),"Bataraza") -> Bataraza | Q74: =IFERROR(__xludf.DUMMYFUNCTION("""COMPUTED_VALUE"""),"Palawan") -> Palawan | R74: =IFERROR(__xludf.DUMMYFUNCTION("""COMPUTED_VALUE"""),"4B") -> 4B
A75: =IFERROR(__xludf.DUMMYFUNCTION("""COMPUTED_VALUE"""),73.0) -> 73 | B75: =IFERROR(__xludf.DUMMYFUNCTION("""COMPUTED_VALUE"""),"CALASAGUEN DIVISION 4 RICE PRODUCER'S FARMERS ASSOCIATION") -> CALASAGUEN DIVISION 4 RICE PRODUCER'S FARMERS ASSOCIATION | C75: =IFERROR(__xludf.DUMMYFUNCTION("""COMPUTED_VALUE"""),"Calasaguen, Brooke's Point, Palawan") -> Calasaguen, Brooke's Point, Palawan | D75: =IFERROR(__xludf.DUMMYFUNCTION("""COMPUTED_VALUE"""),"Michael B. Buñag") -> Michael B. Buñag | E75: =IFERROR(__xludf.DUMMYFUNCTION("""COMPUTED_VALUE"""),"0963-397-1345") -> 0963-397-1345 | F75: =IFERROR(__xludf.DUMMYFUNCTION("""COMPUTED_VALUE"""),"RCEF 23-08-20 Rebidding") -> RCEF 23-08-20 Rebidding | G75: =IFERROR(__xludf.DUMMYFUNCTION("""COMPUTED_VALUE"""),1.0) -> 1 | H75: =IFERROR(__xludf.DUMMYFUNCTION("""COMPUTED_VALUE"""),17948.0) -> 17948 | I75: =IFERROR(__xludf.DUMMYFUNCTION("""COMPUTED_VALUE"""),"KMC 5825 ACPFPV0057") -> KMC 5825 ACPFPV0057 | J75: =IFERROR(__xludf.DUMMYFUNCTION("""COMPUTED_VALUE"""),"PTS 100139") -> PTS 100139 | K75: =IFERROR(__xludf.DUMMYFUNCTION("""COMPUTED_VALUE"""),"R-SERIES 117 PH") -> R-SERIES 117 PH | L75: =IFERROR(__xludf.DUMMYFUNCTION("""COMPUTED_VALUE"""),"LSGW1750 RMP 2312068") -> LSGW1750 RMP 2312068 | M75: =IFERROR(__xludf.DUMMYFUNCTION("""COMPUTED_VALUE"""),"WDP40 RMP 2312073") -> WDP40 RMP 2312073 | O75: =IFERROR(__xludf.DUMMYFUNCTION("""COMPUTED_VALUE"""),"Calasaguen") -> Calasaguen | P75: =IFERROR(__xludf.DUMMYFUNCTION("""COMPUTED_VALUE"""),"Brooke'S Point") -> Brooke'S Point | Q75: =IFERROR(__xludf.DUMMYFUNCTION("""COMPUTED_VALUE"""),"Palawan") -> Palawan | R75: =IFERROR(__xludf.DUMMYFUNCTION("""COMPUTED_VALUE"""),"4B") -> 4B
A76: =IFERROR(__xludf.DUMMYFUNCTION("""COMPUTED_VALUE"""),74.0) -> 74 | B76: =IFERROR(__xludf.DUMMYFUNCTION("""COMPUTED_VALUE"""),"MACAGUA FARMERS IRRIGATORS' ASSOCIATION INC.") -> MACAGUA FARMERS IRRIGATORS' ASSOCIATION INC. | C76: =IFERROR(__xludf.DUMMYFUNCTION("""COMPUTED_VALUE"""),"Macagua, Brooke's Point, Palawan") -> Macagua, Brooke's Point, Palawan | F76: =IFERROR(__xludf.DUMMYFUNCTION("""COMPUTED_VALUE"""),"RCEF 23-08-20 Rebidding") -> RCEF 23-08-20 Rebidding | G76: =IFERROR(__xludf.DUMMYFUNCTION("""COMPUTED_VALUE"""),1.0) -> 1 | H76: =IFERROR(__xludf.DUMMYFUNCTION("""COMPUTED_VALUE"""),17949.0) -> 17949 | I76: =IFERROR(__xludf.DUMMYFUNCTION("""COMPUTED_VALUE"""),"KMC 5825 AHPFPV0072") -> KMC 5825 AHPFPV0072 | J76: =IFERROR(__xludf.DUMMYFUNCTION("""COMPUTED_VALUE"""),"PTS 100084") -> PTS 100084 | K76: =IFERROR(__xludf.DUMMYFUNCTION("""COMPUTED_VALUE"""),"R-SERIES 120 PH") -> R-SERIES 120 PH | L76: =IFERROR(__xludf.DUMMYFUNCTION("""COMPUTED_VALUE"""),"LSGW1750 RMP 2312048") -> LSGW1750 RMP 2312048 | M76: =IFERROR(__xludf.DUMMYFUNCTION("""COMPUTED_VALUE"""),"WDP40 RMP 2312088") -> WDP40 RMP 2312088 | O76: =IFERROR(__xludf.DUMMYFUNCTION("""COMPUTED_VALUE"""),"Macagua") -> Macagua | P76: =IFERROR(__xludf.DUMMYFUNCTION("""COMPUTED_VALUE"""),"Brooke'S Point") -> Brooke'S Point | Q76: =IFERROR(__xludf.DUMMYFUNCTION("""COMPUTED_VALUE"""),"Palawan") -> Palawan | R76: =IFERROR(__xludf.DUMMYFUNCTION("""COMPUTED_VALUE"""),"4B") -> 4B
A77: =IFERROR(__xludf.DUMMYFUNCTION("""COMPUTED_VALUE"""),75.0) -> 75 | B77: =IFERROR(__xludf.DUMMYFUNCTION("""COMPUTED_VALUE"""),"MALIGAYA MAY PAG-ASA IRRIGATORS ASSOCIATION INC.") -> MALIGAYA MAY PAG-ASA IRRIGATORS ASSOCIATION INC. | C77: =IFERROR(__xludf.DUMMYFUNCTION("""COMPUTED_VALUE"""),"Sandoval, Narra, Palawan") -> Sandoval, Narra, Palawan | D77: =IFERROR(__xludf.DUMMYFUNCTION("""COMPUTED_VALUE"""),"Ruel B. Padilla") -> Ruel B. Padilla | E77: =IFERROR(__xludf.DUMMYFUNCTION("""COMPUTED_VALUE"""),"0938 555 4077") -> 0938 555 4077 | F77: =IFERROR(__xludf.DUMMYFUNCTION("""COMPUTED_VALUE"""),"RCEF 23-08-20 Rebidding") -> RCEF 23-08-20 Rebidding | G77: =IFERROR(__xludf.DUMMYFUNCTION("""COMPUTED_VALUE"""),1.0) -> 1 | H77: =IFERROR(__xludf.DUMMYFUNCTION("""COMPUTED_VALUE"""),17950.0) -> 17950 | I77: =IFERROR(__xludf.DUMMYFUNCTION("""COMPUTED_VALUE"""),"KMC 5825 APPFPV0109") -> KMC 5825 APPFPV0109 | J77: =IFERROR(__xludf.DUMMYFUNCTION("""COMPUTED_VALUE"""),"PTS 100048") -> PTS 100048 | K77: =IFERROR(__xludf.DUMMYFUNCTION("""COMPUTED_VALUE"""),"R-SERIES 143 PH") -> R-SERIES 143 PH | L77: =IFERROR(__xludf.DUMMYFUNCTION("""COMPUTED_VALUE"""),"LSGW1750 RMP 2312062") -> LSGW1750 RMP 2312062 | M77: =IFERROR(__xludf.DUMMYFUNCTION("""COMPUTED_VALUE"""),"WDP40 RMP 2312096") -> WDP40 RMP 2312096 | O77: =IFERROR(__xludf.DUMMYFUNCTION("""COMPUTED_VALUE"""),"Sandoval") -> Sandoval | P77: =IFERROR(__xludf.DUMMYFUNCTION("""COMPUTED_VALUE"""),"Narra") -> Narra | Q77: =IFERROR(__xludf.DUMMYFUNCTION("""COMPUTED_VALUE"""),"Palawan") -> Palawan | R77: =IFERROR(__xludf.DUMMYFUNCTION("""COMPUTED_VALUE"""),"4B") -> 4B
A78: =IFERROR(__xludf.DUMMYFUNCTION("""COMPUTED_VALUE"""),76.0) -> 76 | B78: =IFERROR(__xludf.DUMMYFUNCTION("""COMPUTED_VALUE"""),"MALATGAO QUEZON FARMERS IRRIGATORS' ASSOCIATION, INC.") -> MALATGAO QUEZON FARMERS IRRIGATORS' ASSOCIATION, INC. | C78: =IFERROR(__xludf.DUMMYFUNCTION("""COMPUTED_VALUE"""),"Malatgao, Quezon, Palawan") -> Malatgao, Quezon, Palawan | D78: =IFERROR(__xludf.DUMMYFUNCTION("""COMPUTED_VALUE"""),"Adelan M. Peñalosa") -> Adelan M. Peñalosa | E78: =IFERROR(__xludf.DUMMYFUNCTION("""COMPUTED_VALUE"""),9.978206354E9) -> 9978206354 | F78: =IFERROR(__xludf.DUMMYFUNCTION("""COMPUTED_VALUE"""),"RCEF 23-08-20 Rebidding") -> RCEF 23-08-20 Rebidding | G78: =IFERROR(__xludf.DUMMYFUNCTION("""COMPUTED_VALUE"""),1.0) -> 1 | H78: =IFERROR(__xludf.DUMMYFUNCTION("""COMPUTED_VALUE"""),17951.0) -> 17951 | I78: =IFERROR(__xludf.DUMMYFUNCTION("""COMPUTED_VALUE"""),"KMC 5825 ACPFPV0115") -> KMC 5825 ACPFPV0115 | J78: =IFERROR(__xludf.DUMMYFUNCTION("""COMPUTED_VALUE"""),"PTS 100095") -> PTS 100095 | K78: =IFERROR(__xludf.DUMMYFUNCTION("""COMPUTED_VALUE"""),"R-SERIES 108 PH") -> R-SERIES 108 PH | L78: =IFERROR(__xludf.DUMMYFUNCTION("""COMPUTED_VALUE"""),"LSGW1750 RMP 2312055") -> LSGW1750 RMP 2312055 | M78: =IFERROR(__xludf.DUMMYFUNCTION("""COMPUTED_VALUE"""),"WDP40 RMP 2312090") -> WDP40 RMP 2312090 | O78: =IFERROR(__xludf.DUMMYFUNCTION("""COMPUTED_VALUE"""),"Malatgao") -> Malatgao | P78: =IFERROR(__xludf.DUMMYFUNCTION("""COMPUTED_VALUE"""),"Quezon") -> Quezon | Q78: =IFERROR(__xludf.DUMMYFUNCTION("""COMPUTED_VALUE"""),"Palawan") -> Palawan | R78: =IFERROR(__xludf.DUMMYFUNCTION("""COMPUTED_VALUE"""),"4B") -> 4B
A79: =IFERROR(__xludf.DUMMYFUNCTION("""COMPUTED_VALUE"""),77.0) -> 77 | B79: =IFERROR(__xludf.DUMMYFUNCTION("""COMPUTED_VALUE"""),"SOWANGAN FARMERS IRRIGATORS ' ASSOCIATION INC.") -> SOWANGAN FARMERS IRRIGATORS ' ASSOCIATION INC. | C79: =IFERROR(__xludf.DUMMYFUNCTION("""COMPUTED_VALUE"""),"Sowangan, Quezon, Palawan") -> Sowangan, Quezon, Palawan | D79: =IFERROR(__xludf.DUMMYFUNCTION("""COMPUTED_VALUE"""),"Danilo M. Cezar") -> Danilo M. Cezar | E79: =IFERROR(__xludf.DUMMYFUNCTION("""COMPUTED_VALUE"""),"0910 242 6209/ 0912 225 2230") -> 0910 242 6209/ 0912 225 2230 | F79: =IFERROR(__xludf.DUMMYFUNCTION("""COMPUTED_VALUE"""),"RCEF 23-08-20 Rebidding") -> RCEF 23-08-20 Rebidding | G79: =IFERROR(__xludf.DUMMYFUNCTION("""COMPUTED_VALUE"""),1.0) -> 1 | H79: =IFERROR(__xludf.DUMMYFUNCTION("""COMPUTED_VALUE"""),17952.0) -> 17952 | I79: =IFERROR(__xludf.DUMMYFUNCTION("""COMPUTED_VALUE"""),"KMC 5825 AJPFPV0114") -> KMC 5825 AJPFPV0114 | J79: =IFERROR(__xludf.DUMMYFUNCTION("""COMPUTED_VALUE"""),"PTS 100094") -> PTS 100094 | K79: =IFERROR(__xludf.DUMMYFUNCTION("""COMPUTED_VALUE"""),"R-SERIES 119 PH") -> R-SERIES 119 PH | L79: =IFERROR(__xludf.DUMMYFUNCTION("""COMPUTED_VALUE"""),"LSGW1750 RMP 2312077") -> LSGW1750 RMP 2312077 | M79: =IFERROR(__xludf.DUMMYFUNCTION("""COMPUTED_VALUE"""),"WDP40 RMP 2312095") -> WDP40 RMP 2312095 | O79: =IFERROR(__xludf.DUMMYFUNCTION("""COMPUTED_VALUE"""),"Sowangan") -> Sowangan | P79: =IFERROR(__xludf.DUMMYFUNCTION("""COMPUTED_VALUE"""),"Quezon") -> Quezon | Q79: =IFERROR(__xludf.DUMMYFUNCTION("""COMPUTED_VALUE"""),"Palawan") -> Palawan | R79: =IFERROR(__xludf.DUMMYFUNCTION("""COMPUTED_VALUE"""),"4B") -> 4B
A80: =IFERROR(__xludf.DUMMYFUNCTION("""COMPUTED_VALUE"""),78.0) -> 78 | B80: =IFERROR(__xludf.DUMMYFUNCTION("""COMPUTED_VALUE"""),"SICUD FARMERS ASSOCIATION") -> SICUD FARMERS ASSOCIATION | C80: =IFERROR(__xludf.DUMMYFUNCTION("""COMPUTED_VALUE"""),"Candawaga, Rizal, Palawan") -> Candawaga, Rizal, Palawan | D80: =IFERROR(__xludf.DUMMYFUNCTION("""COMPUTED_VALUE"""),"Rodrigo C. Quiocson") -> Rodrigo C. Quiocson | E80: =IFERROR(__xludf.DUMMYFUNCTION("""COMPUTED_VALUE"""),"0975 202 7209") -> 0975 202 7209 | F80: =IFERROR(__xludf.DUMMYFUNCTION("""COMPUTED_VALUE"""),"RCEF 23-08-20 Rebidding") -> RCEF 23-08-20 Rebidding | G80: =IFERROR(__xludf.DUMMYFUNCTION("""COMPUTED_VALUE"""),1.0) -> 1 | H80: =IFERROR(__xludf.DUMMYFUNCTION("""COMPUTED_VALUE"""),17953.0) -> 17953 | I80: =IFERROR(__xludf.DUMMYFUNCTION("""COMPUTED_VALUE"""),"KMC 5825 AHPFPV0105") -> KMC 5825 AHPFPV0105 | J80: =IFERROR(__xludf.DUMMYFUNCTION("""COMPUTED_VALUE"""),"PTS 100073") -> PTS 100073 | K80: =IFERROR(__xludf.DUMMYFUNCTION("""COMPUTED_VALUE"""),"R-SERIES 107 PH") -> R-SERIES 107 PH | L80: =IFERROR(__xludf.DUMMYFUNCTION("""COMPUTED_VALUE"""),"LSGW1750 RMP 2312090") -> LSGW1750 RMP 2312090 | M80: =IFERROR(__xludf.DUMMYFUNCTION("""COMPUTED_VALUE"""),"WDP40 RMP 2312100") -> WDP40 RMP 2312100 | O80: =IFERROR(__xludf.DUMMYFUNCTION("""COMPUTED_VALUE"""),"Candawaga") -> Candawaga | P80: =IFERROR(__xludf.DUMMYFUNCTION("""COMPUTED_VALUE"""),"Rizal") -> Rizal | Q80: =IFERROR(__xludf.DUMMYFUNCTION("""COMPUTED_VALUE"""),"Palawan") -> Palawan | R80: =IFERROR(__xludf.DUMMYFUNCTION("""COMPUTED_VALUE"""),"4B") -> 4B
A81: =IFERROR(__xludf.DUMMYFUNCTION("""COMPUTED_VALUE"""),79.0) -> 79 | B81: =IFERROR(__xludf.DUMMYFUNCTION("""COMPUTED_VALUE"""),"TAGLOP BULIKAWA FARMERS ASSOCIATION") -> TAGLOP BULIKAWA FARMERS ASSOCIATION | C81: =IFERROR(__xludf.DUMMYFUNCTION("""COMPUTED_VALUE"""),"Canipaan, Rizal, Palawan") -> Canipaan, Rizal, Palawan | D81: =IFERROR(__xludf.DUMMYFUNCTION("""COMPUTED_VALUE"""),"Elmer C. Abes") -> Elmer C. Abes | E81: =IFERROR(__xludf.DUMMYFUNCTION("""COMPUTED_VALUE"""),"0965 355 1181 (Rey Blando)") -> 0965 355 1181 (Rey Blando) | F81: =IFERROR(__xludf.DUMMYFUNCTION("""COMPUTED_VALUE"""),"RCEF 23-08-20 Rebidding") -> RCEF 23-08-20 Rebidding | G81: =IFERROR(__xludf.DUMMYFUNCTION("""COMPUTED_VALUE"""),1.0) -> 1 | H81: =IFERROR(__xludf.DUMMYFUNCTION("""COMPUTED_VALUE"""),17954.0) -> 17954 | I81: =IFERROR(__xludf.DUMMYFUNCTION("""COMPUTED_VALUE"""),"KMC 5825 AAPFPV0148") -> KMC 5825 AAPFPV0148 | J81: =IFERROR(__xludf.DUMMYFUNCTION("""COMPUTED_VALUE"""),"PTS 100113") -> PTS 100113 | K81: =IFERROR(__xludf.DUMMYFUNCTION("""COMPUTED_VALUE"""),"R-SERIES 139 PH") -> R-SERIES 139 PH | L81: =IFERROR(__xludf.DUMMYFUNCTION("""COMPUTED_VALUE"""),"LSGW1750 RMP 2312066") -> LSGW1750 RMP 2312066 | M81: =IFERROR(__xludf.DUMMYFUNCTION("""COMPUTED_VALUE"""),"WDP40 RMP 2312092") -> WDP40 RMP 2312092 | O81: =IFERROR(__xludf.DUMMYFUNCTION("""COMPUTED_VALUE"""),"Canipaan") -> Canipaan | P81: =IFERROR(__xludf.DUMMYFUNCTION("""COMPUTED_VALUE"""),"Rizal") -> Rizal | Q81: =IFERROR(__xludf.DUMMYFUNCTION("""COMPUTED_VALUE"""),"Palawan") -> Palawan | R81: =IFERROR(__xludf.DUMMYFUNCTION("""COMPUTED_VALUE"""),"4B") -> 4B
A82: =IFERROR(__xludf.DUMMYFUNCTION("""COMPUTED_VALUE"""),80.0) -> 80 | B82: =IFERROR(__xludf.DUMMYFUNCTION("""COMPUTED_VALUE"""),"CABAYUGAN FARMERS ASSOCIATION") -> CABAYUGAN FARMERS ASSOCIATION | C82: =IFERROR(__xludf.DUMMYFUNCTION("""COMPUTED_VALUE"""),"Cabayugan, Puerto Princesa City, Palawan") -> Cabayugan, Puerto Princesa City, Palawan | D82: =IFERROR(__xludf.DUMMYFUNCTION("""COMPUTED_VALUE"""),"Louie Joy A. Aungon") -> Louie Joy A. Aungon | E82: =IFERROR(__xludf.DUMMYFUNCTION("""COMPUTED_VALUE"""),"0905 096 0839") -> 0905 096 0839 | F82: =IFERROR(__xludf.DUMMYFUNCTION("""COMPUTED_VALUE"""),"RCEF 23-08-20 Rebidding") -> RCEF 23-08-20 Rebidding | G82: =IFERROR(__xludf.DUMMYFUNCTION("""COMPUTED_VALUE"""),1.0) -> 1 | H82: =IFERROR(__xludf.DUMMYFUNCTION("""COMPUTED_VALUE"""),17955.0) -> 17955 | I82: =IFERROR(__xludf.DUMMYFUNCTION("""COMPUTED_VALUE"""),"KMC 5825 ACPFPV0110") -> KMC 5825 ACPFPV0110 | J82: =IFERROR(__xludf.DUMMYFUNCTION("""COMPUTED_VALUE"""),"PTS 100090") -> PTS 100090 | K82: =IFERROR(__xludf.DUMMYFUNCTION("""COMPUTED_VALUE"""),"R-SERIES 142 PH") -> R-SERIES 142 PH | L82: =IFERROR(__xludf.DUMMYFUNCTION("""COMPUTED_VALUE"""),"LSGW1750 RMP 2312036") -> LSGW1750 RMP 2312036 | M82: =IFERROR(__xludf.DUMMYFUNCTION("""COMPUTED_VALUE"""),"WDP40 RMP 2312091") -> WDP40 RMP 2312091 | O82: =IFERROR(__xludf.DUMMYFUNCTION("""COMPUTED_VALUE"""),"Cabayugan") -> Cabayugan | P82: =IFERROR(__xludf.DUMMYFUNCTION("""COMPUTED_VALUE"""),"Puerto Princesa City") -> Puerto Princesa City | Q82: =IFERROR(__xludf.DUMMYFUNCTION("""COMPUTED_VALUE"""),"Palawan") -> Palawan | R82: =IFERROR(__xludf.DUMMYFUNCTION("""COMPUTED_VALUE"""),"4B") -> 4B
A83: =IFERROR(__xludf.DUMMYFUNCTION("""COMPUTED_VALUE"""),81.0) -> 81 | B83: =IFERROR(__xludf.DUMMYFUNCTION("""COMPUTED_VALUE"""),"SAMAHANG MANUNUBIG NG CULANDANUM FARMERS, ABORLAN, PALAWAN, INC.") -> SAMAHANG MANUNUBIG NG CULANDANUM FARMERS, ABORLAN, PALAWAN, INC. | C83: =IFERROR(__xludf.DUMMYFUNCTION("""COMPUTED_VALUE"""),"Culandanum, Aborlan, Palawan") -> Culandanum, Aborlan, Palawan | D83: =IFERROR(__xludf.DUMMYFUNCTION("""COMPUTED_VALUE"""),"Nestor C. Valmoria") -> Nestor C. Valmoria | E83: =IFERROR(__xludf.DUMMYFUNCTION("""COMPUTED_VALUE"""),"0912 145 7225") -> 0912 145 7225 | F83: =IFERROR(__xludf.DUMMYFUNCTION("""COMPUTED_VALUE"""),"RCEF 23-08-20 Rebidding") -> RCEF 23-08-20 Rebidding | G83: =IFERROR(__xludf.DUMMYFUNCTION("""COMPUTED_VALUE"""),1.0) -> 1 | H83: =IFERROR(__xludf.DUMMYFUNCTION("""COMPUTED_VALUE"""),17956.0) -> 17956 | I83: =IFERROR(__xludf.DUMMYFUNCTION("""COMPUTED_VALUE"""),"KMC 5825 APPFPV00112") -> KMC 5825 APPFPV00112 | J83: =IFERROR(__xludf.DUMMYFUNCTION("""COMPUTED_VALUE"""),"PTS 100055") -> PTS 100055 | K83: =IFERROR(__xludf.DUMMYFUNCTION("""COMPUTED_VALUE"""),"R-SERIES 118 PH") -> R-SERIES 118 PH | L83: =IFERROR(__xludf.DUMMYFUNCTION("""COMPUTED_VALUE"""),"LSGW1750 RMP 2312070") -> LSGW1750 RMP 2312070 | M83: =IFERROR(__xludf.DUMMYFUNCTION("""COMPUTED_VALUE"""),"WDP40 RMP 2312073") -> WDP40 RMP 2312073 | O83: =IFERROR(__xludf.DUMMYFUNCTION("""COMPUTED_VALUE"""),"Culandanum") -> Culandanum | P83: =IFERROR(__xludf.DUMMYFUNCTION("""COMPUTED_VALUE"""),"Aborlan") -> Aborlan | Q83: =IFERROR(__xludf.DUMMYFUNCTION("""COMPUTED_VALUE"""),"Palawan") -> Palawan | R83: =IFERROR(__xludf.DUMMYFUNCTION("""COMPUTED_VALUE"""),"4B") -> 4B
A84: =IFERROR(__xludf.DUMMYFUNCTION("""COMPUTED_VALUE"""),82.0) -> 82 | B84: =IFERROR(__xludf.DUMMYFUNCTION("""COMPUTED_VALUE"""),"AGKAKARUBA IRRIGATORS ASSOCIATION, INC.") -> AGKAKARUBA IRRIGATORS ASSOCIATION, INC. | C84: =IFERROR(__xludf.DUMMYFUNCTION("""COMPUTED_VALUE"""),"Plaridel, Aborlan, Palawan") -> Plaridel, Aborlan, Palawan | D84: =IFERROR(__xludf.DUMMYFUNCTION("""COMPUTED_VALUE"""),"Buenaventura L. Rosario") -> Buenaventura L. Rosario | E84: =IFERROR(__xludf.DUMMYFUNCTION("""COMPUTED_VALUE"""),"0910 764 9489") -> 0910 764 9489 | F84: =IFERROR(__xludf.DUMMYFUNCTION("""COMPUTED_VALUE"""),"RCEF 23-08-20 Rebidding") -> RCEF 23-08-20 Rebidding | G84: =IFERROR(__xludf.DUMMYFUNCTION("""COMPUTED_VALUE"""),1.0) -> 1 | H84: =IFERROR(__xludf.DUMMYFUNCTION("""COMPUTED_VALUE"""),17957.0) -> 17957 | I84: =IFERROR(__xludf.DUMMYFUNCTION("""COMPUTED_VALUE"""),"KMC 5825 ALPFPV0118") -> KMC 5825 ALPFPV0118 | J84: =IFERROR(__xludf.DUMMYFUNCTION("""COMPUTED_VALUE"""),"PTS 100103") -> PTS 100103 | K84: =IFERROR(__xludf.DUMMYFUNCTION("""COMPUTED_VALUE"""),"R-SERIES 149 PH") -> R-SERIES 149 PH | L84: =IFERROR(__xludf.DUMMYFUNCTION("""COMPUTED_VALUE"""),"LSGW1750 RMP 2312089") -> LSGW1750 RMP 2312089 | M84: =IFERROR(__xludf.DUMMYFUNCTION("""COMPUTED_VALUE"""),"WDP40 RMP 2312082") -> WDP40 RMP 2312082 | O84: =IFERROR(__xludf.DUMMYFUNCTION("""COMPUTED_VALUE"""),"Plaridel") -> Plaridel | P84: =IFERROR(__xludf.DUMMYFUNCTION("""COMPUTED_VALUE"""),"Aborlan") -> Aborlan | Q84: =IFERROR(__xludf.DUMMYFUNCTION("""COMPUTED_VALUE"""),"Palawan") -> Palawan | R84: =IFERROR(__xludf.DUMMYFUNCTION("""COMPUTED_VALUE"""),"4B") -> 4B
A85: =IFERROR(__xludf.DUMMYFUNCTION("""COMPUTED_VALUE"""),83.0) -> 83 | B85: =IFERROR(__xludf.DUMMYFUNCTION("""COMPUTED_VALUE"""),"IBATO-IRAAN FARMER'S IRRIGATORS ASSOCIATION, INC.") -> IBATO-IRAAN FARMER'S IRRIGATORS ASSOCIATION, INC. | C85: =IFERROR(__xludf.DUMMYFUNCTION("""COMPUTED_VALUE"""),"Sagpangan, Aborlan, Palawan") -> Sagpangan, Aborlan, Palawan | D85: =IFERROR(__xludf.DUMMYFUNCTION("""COMPUTED_VALUE"""),"Ronie G Baron") -> Ronie G Baron | E85: =IFERROR(__xludf.DUMMYFUNCTION("""COMPUTED_VALUE"""),"0930-902-8777") -> 0930-902-8777 | F85: =IFERROR(__xludf.DUMMYFUNCTION("""COMPUTED_VALUE"""),"RCEF 23-08-20 Rebidding") -> RCEF 23-08-20 Rebidding | G85: =IFERROR(__xludf.DUMMYFUNCTION("""COMPUTED_VALUE"""),1.0) -> 1 | H85: =IFERROR(__xludf.DUMMYFUNCTION("""COMPUTED_VALUE"""),17958.0) -> 17958 | I85: =IFERROR(__xludf.DUMMYFUNCTION("""COMPUTED_VALUE"""),"KMC 5825 AHPFPV0086") -> KMC 5825 AHPFPV0086 | J85: =IFERROR(__xludf.DUMMYFUNCTION("""COMPUTED_VALUE"""),"PTS 100075") -> PTS 100075 | K85: =IFERROR(__xludf.DUMMYFUNCTION("""COMPUTED_VALUE"""),"R-SERIES 144 PH") -> R-SERIES 144 PH | L85: =IFERROR(__xludf.DUMMYFUNCTION("""COMPUTED_VALUE"""),"LSGW1750 RMP 2312067") -> LSGW1750 RMP 2312067 | M85: =IFERROR(__xludf.DUMMYFUNCTION("""COMPUTED_VALUE"""),"WDP40 RMP 2312085") -> WDP40 RMP 2312085 | O85: =IFERROR(__xludf.DUMMYFUNCTION("""COMPUTED_VALUE"""),"Sagpangan") -> Sagpangan | P85: =IFERROR(__xludf.DUMMYFUNCTION("""COMPUTED_VALUE"""),"Aborlan") -> Aborlan | Q85: =IFERROR(__xludf.DUMMYFUNCTION("""COMPUTED_VALUE"""),"Palawan") -> Palawan | R85: =IFERROR(__xludf.DUMMYFUNCTION("""COMPUTED_VALUE"""),"4B") -> 4B
A86: =IFERROR(__xludf.DUMMYFUNCTION("""COMPUTED_VALUE"""),84.0) -> 84 | B86: =IFERROR(__xludf.DUMMYFUNCTION("""COMPUTED_VALUE"""),"PARADISE TELENG FARMERS IRRIGATORS ASSOCIATION INC") -> PARADISE TELENG FARMERS IRRIGATORS ASSOCIATION INC | C86: =IFERROR(__xludf.DUMMYFUNCTION("""COMPUTED_VALUE"""),"Tigman, Aborlan, Palawan") -> Tigman, Aborlan, Palawan | D86: =IFERROR(__xludf.DUMMYFUNCTION("""COMPUTED_VALUE"""),"Lourdez C. Paduga") -> Lourdez C. Paduga | E86: =IFERROR(__xludf.DUMMYFUNCTION("""COMPUTED_VALUE"""),9.750285877E9) -> 9750285877 | F86: =IFERROR(__xludf.DUMMYFUNCTION("""COMPUTED_VALUE"""),"RCEF 23-08-20 Rebidding") -> RCEF 23-08-20 Rebidding | G86: =IFERROR(__xludf.DUMMYFUNCTION("""COMPUTED_VALUE"""),1.0) -> 1 | H86: =IFERROR(__xludf.DUMMYFUNCTION("""COMPUTED_VALUE"""),17959.0) -> 17959 | I86: =IFERROR(__xludf.DUMMYFUNCTION("""COMPUTED_VALUE"""),"KMC 5825 ATPFPV0156") -> KMC 5825 ATPFPV0156 | J86: =IFERROR(__xludf.DUMMYFUNCTION("""COMPUTED_VALUE"""),"PTS 100142") -> PTS 100142 | K86: =IFERROR(__xludf.DUMMYFUNCTION("""COMPUTED_VALUE"""),"R-SERIES 140 PH") -> R-SERIES 140 PH | L86: =IFERROR(__xludf.DUMMYFUNCTION("""COMPUTED_VALUE"""),"LSGW1750 RMP 2312083") -> LSGW1750 RMP 2312083 | M86: =IFERROR(__xludf.DUMMYFUNCTION("""COMPUTED_VALUE"""),"WDP40 RMP 2312083") -> WDP40 RMP 2312083 | O86: =IFERROR(__xludf.DUMMYFUNCTION("""COMPUTED_VALUE"""),"Tigman") -> Tigman | P86: =IFERROR(__xludf.DUMMYFUNCTION("""COMPUTED_VALUE"""),"Aborlan") -> Aborlan | Q86: =IFERROR(__xludf.DUMMYFUNCTION("""COMPUTED_VALUE"""),"Palawan") -> Palawan | R86: =IFERROR(__xludf.DUMMYFUNCTION("""COMPUTED_VALUE"""),"4B") -> 4B
A87: =IFERROR(__xludf.DUMMYFUNCTION("""COMPUTED_VALUE"""),85.0) -> 85 | B87: =IFERROR(__xludf.DUMMYFUNCTION("""COMPUTED_VALUE"""),"SAMAHANG MAGSASAKA NG APORAWAN AT PARADAHAN INC") -> SAMAHANG MAGSASAKA NG APORAWAN AT PARADAHAN INC | C87: =IFERROR(__xludf.DUMMYFUNCTION("""COMPUTED_VALUE"""),"Apo Aporawan, Aborlan, Palawan") -> Apo Aporawan, Aborlan, Palawan | D87: =IFERROR(__xludf.DUMMYFUNCTION("""COMPUTED_VALUE"""),"Renato T. Lopez") -> Renato T. Lopez | E87: =IFERROR(__xludf.DUMMYFUNCTION("""COMPUTED_VALUE"""),9.051981527E9) -> 9051981527 | F87: =IFERROR(__xludf.DUMMYFUNCTION("""COMPUTED_VALUE"""),"RCEF 23-08-20 Rebidding") -> RCEF 23-08-20 Rebidding | G87: =IFERROR(__xludf.DUMMYFUNCTION("""COMPUTED_VALUE"""),1.0) -> 1 | H87: =IFERROR(__xludf.DUMMYFUNCTION("""COMPUTED_VALUE"""),17960.0) -> 17960 | I87: =IFERROR(__xludf.DUMMYFUNCTION("""COMPUTED_VALUE"""),"KMC 5825 ATPFPV0041") -> KMC 5825 ATPFPV0041 | J87: =IFERROR(__xludf.DUMMYFUNCTION("""COMPUTED_VALUE"""),"PTS 100064") -> PTS 100064 | K87: =IFERROR(__xludf.DUMMYFUNCTION("""COMPUTED_VALUE"""),"R-SERIES 145 PH") -> R-SERIES 145 PH | L87: =IFERROR(__xludf.DUMMYFUNCTION("""COMPUTED_VALUE"""),"LSGW1750 RMP 2312049") -> LSGW1750 RMP 2312049 | M87: =IFERROR(__xludf.DUMMYFUNCTION("""COMPUTED_VALUE"""),"WDP40 RMP 2312080") -> WDP40 RMP 2312080 | O87: =IFERROR(__xludf.DUMMYFUNCTION("""COMPUTED_VALUE"""),"Apo Aporawan") -> Apo Aporawan | P87: =IFERROR(__xludf.DUMMYFUNCTION("""COMPUTED_VALUE"""),"Aborlan") -> Aborlan | Q87: =IFERROR(__xludf.DUMMYFUNCTION("""COMPUTED_VALUE"""),"Palawan") -> Palawan | R87: =IFERROR(__xludf.DUMMYFUNCTION("""COMPUTED_VALUE"""),"4B") -> 4B
A88: =IFERROR(__xludf.DUMMYFUNCTION("""COMPUTED_VALUE"""),86.0) -> 86 | B88: =IFERROR(__xludf.DUMMYFUNCTION("""COMPUTED_VALUE"""),"MUNICIPAL LOCAL GOVERNMENT UNIT OF LOOC") -> MUNICIPAL LOCAL GOVERNMENT UNIT OF LOOC | C88: =IFERROR(__xludf.DUMMYFUNCTION("""COMPUTED_VALUE"""),"POBLACION GUITNA, LOOC, OCCIDENTAL MINDORO") -> POBLACION GUITNA, LOOC, OCCIDENTAL MINDORO | D88: =IFERROR(__xludf.DUMMYFUNCTION("""COMPUTED_VALUE"""),"Hon. Marlon Dela Torre") -> Hon. Marlon Dela Torre | E88: =IFERROR(__xludf.DUMMYFUNCTION("""COMPUTED_VALUE"""),"0999 758 7240") -> 0999 758 7240 | F88: =IFERROR(__xludf.DUMMYFUNCTION("""COMPUTED_VALUE"""),"RCEF 23-08-20 Rebidding") -> RCEF 23-08-20 Rebidding | G88: =IFERROR(__xludf.DUMMYFUNCTION("""COMPUTED_VALUE"""),1.0) -> 1 | H88: =IFERROR(__xludf.DUMMYFUNCTION("""COMPUTED_VALUE"""),18891.0) -> 18891 | I88: =IFERROR(__xludf.DUMMYFUNCTION("""COMPUTED_VALUE"""),"KMC5825AVRFPV0345") -> KMC5825AVRFPV0345 | J88: =IFERROR(__xludf.DUMMYFUNCTION("""COMPUTED_VALUE"""),"RTS100238") -> RTS100238 | K88: =IFERROR(__xludf.DUMMYFUNCTION("""COMPUTED_VALUE"""),"R-SERIES-022PH") -> R-SERIES-022PH | L88: =IFERROR(__xludf.DUMMYFUNCTION("""COMPUTED_VALUE"""),"LSGW 1750 RMP 24020431") -> LSGW 1750 RMP 24020431 | M88: =IFERROR(__xludf.DUMMYFUNCTION("""COMPUTED_VALUE"""),"WDP40 RMP 24020222") -> WDP40 RMP 24020222 | O88: =IFERROR(__xludf.DUMMYFUNCTION("""COMPUTED_VALUE"""),"Poblacion Guitna") -> Poblacion Guitna | P88: =IFERROR(__xludf.DUMMYFUNCTION("""COMPUTED_VALUE"""),"Looc") -> Looc | Q88: =IFERROR(__xludf.DUMMYFUNCTION("""COMPUTED_VALUE"""),"Occidental Mindoro") -> Occidental Mindoro | R88: =IFERROR(__xludf.DUMMYFUNCTION("""COMPUTED_VALUE"""),"4B") -> 4B
A89: =IFERROR(__xludf.DUMMYFUNCTION("""COMPUTED_VALUE"""),87.0) -> 87 | B89: =IFERROR(__xludf.DUMMYFUNCTION("""COMPUTED_VALUE"""),"BRGY. VIGO-DANGAY FARMERS IRRIGATORS ASSOCIATION INC.") -> BRGY. VIGO-DANGAY FARMERS IRRIGATORS ASSOCIATION INC. | C89: =IFERROR(__xludf.DUMMYFUNCTION("""COMPUTED_VALUE"""),"VIGO, LUBANG, OCCIDENTAL MINDORO") -> VIGO, LUBANG, OCCIDENTAL MINDORO | D89: =IFERROR(__xludf.DUMMYFUNCTION("""COMPUTED_VALUE"""),"Abelardo P. De Lemos, Jr.") -> Abelardo P. De Lemos, Jr. | E89: =IFERROR(__xludf.DUMMYFUNCTION("""COMPUTED_VALUE"""),"0999 423 2211") -> 0999 423 2211 | F89: =IFERROR(__xludf.DUMMYFUNCTION("""COMPUTED_VALUE"""),"RCEF 23-08-20 Rebidding") -> RCEF 23-08-20 Rebidding | G89: =IFERROR(__xludf.DUMMYFUNCTION("""COMPUTED_VALUE"""),1.0) -> 1 | H89: =IFERROR(__xludf.DUMMYFUNCTION("""COMPUTED_VALUE"""),18892.0) -> 18892 | I89: =IFERROR(__xludf.DUMMYFUNCTION("""COMPUTED_VALUE"""),"KMC5825AJRFPV0438") -> KMC5825AJRFPV0438 | J89: =IFERROR(__xludf.DUMMYFUNCTION("""COMPUTED_VALUE"""),"RTS100221") -> RTS100221 | K89: =IFERROR(__xludf.DUMMYFUNCTION("""COMPUTED_VALUE"""),"R SERIES 133PH") -> R SERIES 133PH | L89: =IFERROR(__xludf.DUMMYFUNCTION("""COMPUTED_VALUE"""),"LSGW 1750 RMP 24020411") -> LSGW 1750 RMP 24020411 | M89: =IFERROR(__xludf.DUMMYFUNCTION("""COMPUTED_VALUE"""),"WDP40 RMP 24020223") -> WDP40 RMP 24020223 | O89: =IFERROR(__xludf.DUMMYFUNCTION("""COMPUTED_VALUE"""),"Vigo") -> Vigo | P89: =IFERROR(__xludf.DUMMYFUNCTION("""COMPUTED_VALUE"""),"Lubang") -> Lubang | Q89: =IFERROR(__xludf.DUMMYFUNCTION("""COMPUTED_VALUE"""),"Occidental Mindoro") -> Occidental Mindoro | R89: =IFERROR(__xludf.DUMMYFUNCTION("""COMPUTED_VALUE"""),"4B") -> 4B
A90: =IFERROR(__xludf.DUMMYFUNCTION("""COMPUTED_VALUE"""),88.0) -> 88 | B90: =IFERROR(__xludf.DUMMYFUNCTION("""COMPUTED_VALUE"""),"CORON FARMER'S FEDERATION") -> CORON FARMER'S FEDERATION | C90: =IFERROR(__xludf.DUMMYFUNCTION("""COMPUTED_VALUE"""),"Borac, Coron, Palawan") -> Borac, Coron, Palawan | D90: =IFERROR(__xludf.DUMMYFUNCTION("""COMPUTED_VALUE"""),"Numeriano Echague") -> Numeriano Echague | E90: =IFERROR(__xludf.DUMMYFUNCTION("""COMPUTED_VALUE"""),"0975 848 5785") -> 0975 848 5785 | F90: =IFERROR(__xludf.DUMMYFUNCTION("""COMPUTED_VALUE"""),"RCEF 23-08-20 Rebidding") -> RCEF 23-08-20 Rebidding | G90: =IFERROR(__xludf.DUMMYFUNCTION("""COMPUTED_VALUE"""),1.0) -> 1 | I90: =IFERROR(__xludf.DUMMYFUNCTION("""COMPUTED_VALUE"""),"KMC5825 AARFPY0394") -> KMC5825 AARFPY0394 | J90: =IFERROR(__xludf.DUMMYFUNCTION("""COMPUTED_VALUE"""),"RTS100299") -> RTS100299 | K90: =IFERROR(__xludf.DUMMYFUNCTION("""COMPUTED_VALUE"""),"R-SERIES 403 PH") -> R-SERIES 403 PH | L90: =IFERROR(__xludf.DUMMYFUNCTION("""COMPUTED_VALUE"""),"LSGW 1750 RMP 24020531") -> LSGW 1750 RMP 24020531 | M90: =IFERROR(__xludf.DUMMYFUNCTION("""COMPUTED_VALUE"""),"WDP40 RMP 24020248") -> WDP40 RMP 24020248 | O90: =IFERROR(__xludf.DUMMYFUNCTION("""COMPUTED_VALUE"""),"Borac") -> Borac | P90: =IFERROR(__xludf.DUMMYFUNCTION("""COMPUTED_VALUE"""),"Coron") -> Coron | Q90: =IFERROR(__xludf.DUMMYFUNCTION("""COMPUTED_VALUE"""),"Palawan") -> Palawan | R90: =IFERROR(__xludf.DUMMYFUNCTION("""COMPUTED_VALUE"""),"4B") -> 4B
A91: =IFERROR(__xludf.DUMMYFUNCTION("""COMPUTED_VALUE"""),89.0) -> 89 | B91: =IFERROR(__xludf.DUMMYFUNCTION("""COMPUTED_VALUE"""),"KULTIHAN-KAMPUKLO-TUBUHAN-POOK (KTTP) FARMERS ASSOCIATION") -> KULTIHAN-KAMPUKLO-TUBUHAN-POOK (KTTP) FARMERS ASSOCIATION | C91: =IFERROR(__xludf.DUMMYFUNCTION("""COMPUTED_VALUE"""),"Buenavista West, Candelaria, Quezon") -> Buenavista West, Candelaria, Quezon | D91: =IFERROR(__xludf.DUMMYFUNCTION("""COMPUTED_VALUE"""),"Eladio C. Mercado") -> Eladio C. Mercado | E91: =IFERROR(__xludf.DUMMYFUNCTION("""COMPUTED_VALUE"""),"0951 731 5092") -> 0951 731 5092 | F91: =IFERROR(__xludf.DUMMYFUNCTION("""COMPUTED_VALUE"""),"RCEF 23-08-20 Rebidding") -> RCEF 23-08-20 Rebidding | G91: =IFERROR(__xludf.DUMMYFUNCTION("""COMPUTED_VALUE"""),1.0) -> 1 | I91: =IFERROR(__xludf.DUMMYFUNCTION("""COMPUTED_VALUE"""),"KMC5825AERFPV0352") -> KMC5825AERFPV0352 | J91: =IFERROR(__xludf.DUMMYFUNCTION("""COMPUTED_VALUE"""),"RTS100232") -> RTS100232 | K91: =IFERROR(__xludf.DUMMYFUNCTION("""COMPUTED_VALUE"""),"R SERIES 439 PH") -> R SERIES 439 PH | L91: =IFERROR(__xludf.DUMMYFUNCTION("""COMPUTED_VALUE"""),"LSGW 1750 RMP 24020481") -> LSGW 1750 RMP 24020481 | M91: =IFERROR(__xludf.DUMMYFUNCTION("""COMPUTED_VALUE"""),"WDP 40 RMP 24020239") -> WDP 40 RMP 24020239 | O91: =IFERROR(__xludf.DUMMYFUNCTION("""COMPUTED_VALUE"""),"Buenavista West") -> Buenavista West | P91: =IFERROR(__xludf.DUMMYFUNCTION("""COMPUTED_VALUE"""),"Candelaria") -> Candelaria | Q91: =IFERROR(__xludf.DUMMYFUNCTION("""COMPUTED_VALUE"""),"Quezon") -> Quezon | R91: =IFERROR(__xludf.DUMMYFUNCTION("""COMPUTED_VALUE"""),"4A") -> 4A
A92: =IFERROR(__xludf.DUMMYFUNCTION("""COMPUTED_VALUE"""),90.0) -> 90 | B92: =IFERROR(__xludf.DUMMYFUNCTION("""COMPUTED_VALUE"""),"THE FARMERS OF LUNA AGRICULTURE COOPERATIVE") -> THE FARMERS OF LUNA AGRICULTURE COOPERATIVE | C92: =IFERROR(__xludf.DUMMYFUNCTION("""COMPUTED_VALUE"""),"Centro 2, Luna, Isabela") -> Centro 2, Luna, Isabela | D92: =IFERROR(__xludf.DUMMYFUNCTION("""COMPUTED_VALUE"""),"Edgar A. Diniega") -> Edgar A. Diniega | E92: =IFERROR(__xludf.DUMMYFUNCTION("""COMPUTED_VALUE"""),9.656732717E9) -> 9656732717 | F92: =IFERROR(__xludf.DUMMYFUNCTION("""COMPUTED_VALUE"""),"RCEF 23-09-21 Rebidding") -> RCEF 23-09-21 Rebidding | G92: =IFERROR(__xludf.DUMMYFUNCTION("""COMPUTED_VALUE"""),9.0) -> 9 | H92: =IFERROR(__xludf.DUMMYFUNCTION("""COMPUTED_VALUE"""),17369.0) -> 17369 | I92: =IFERROR(__xludf.DUMMYFUNCTION("""COMPUTED_VALUE"""),"KMC 5825 ACPFPV0034") -> KMC 5825 ACPFPV0034 | J92: =IFERROR(__xludf.DUMMYFUNCTION("""COMPUTED_VALUE"""),"PTS100004") -> PTS100004 | K92: =IFERROR(__xludf.DUMMYFUNCTION("""COMPUTED_VALUE"""),"HL 22R005") -> HL 22R005 | L92: =IFERROR(__xludf.DUMMYFUNCTION("""COMPUTED_VALUE"""),"WR LSGW 0019") -> WR LSGW 0019 | M92: =IFERROR(__xludf.DUMMYFUNCTION("""COMPUTED_VALUE"""),"WDP40 RMP 24010055") -> WDP40 RMP 24010055 | O92: =IFERROR(__xludf.DUMMYFUNCTION("""COMPUTED_VALUE"""),"Centro 2") -> Centro 2 | P92: =IFERROR(__xludf.DUMMYFUNCTION("""COMPUTED_VALUE"""),"Luna") -> Luna | Q92: =IFERROR(__xludf.DUMMYFUNCTION("""COMPUTED_VALUE"""),"Isabela") -> Isabela | R92: =IFERROR(__xludf.DUMMYFUNCTION("""COMPUTED_VALUE"""),2.0) -> 2
A93: =IFERROR(__xludf.DUMMYFUNCTION("""COMPUTED_VALUE"""),91.0) -> 91 | B93: =IFERROR(__xludf.DUMMYFUNCTION("""COMPUTED_VALUE"""),"BARANGAY CABANNUNGAN FARMERS ASSOCIATION") -> BARANGAY CABANNUNGAN FARMERS ASSOCIATION | C93: =IFERROR(__xludf.DUMMYFUNCTION("""COMPUTED_VALUE"""),"Cabannungan 2nd, City of Ilagan, Isabela") -> Cabannungan 2nd, City of Ilagan, Isabela | D93: =IFERROR(__xludf.DUMMYFUNCTION("""COMPUTED_VALUE"""),"Christopher M. Siriban") -> Christopher M. Siriban | E93: =IFERROR(__xludf.DUMMYFUNCTION("""COMPUTED_VALUE"""),"0935-762-0492") -> 0935-762-0492 | F93: =IFERROR(__xludf.DUMMYFUNCTION("""COMPUTED_VALUE"""),"RCEF 23-09-21 Rebidding") -> RCEF 23-09-21 Rebidding | G93: =IFERROR(__xludf.DUMMYFUNCTION("""COMPUTED_VALUE"""),9.0) -> 9 | H93: =IFERROR(__xludf.DUMMYFUNCTION("""COMPUTED_VALUE"""),17370.0) -> 17370 | I93: =IFERROR(__xludf.DUMMYFUNCTION("""COMPUTED_VALUE"""),"KMC 5825 AEPFPV0025") -> KMC 5825 AEPFPV0025 | J93: =IFERROR(__xludf.DUMMYFUNCTION("""COMPUTED_VALUE"""),"PTS100038") -> PTS100038 | K93: =IFERROR(__xludf.DUMMYFUNCTION("""COMPUTED_VALUE"""),"HL 22R010") -> HL 22R010 | L93: =IFERROR(__xludf.DUMMYFUNCTION("""COMPUTED_VALUE"""),"WR LSGW 0020") -> WR LSGW 0020 | M93: =IFERROR(__xludf.DUMMYFUNCTION("""COMPUTED_VALUE"""),"WDP40 RMP 24010050") -> WDP40 RMP 24010050 | O93: =IFERROR(__xludf.DUMMYFUNCTION("""COMPUTED_VALUE"""),"Cabannungan 2Nd") -> Cabannungan 2Nd | P93: =IFERROR(__xludf.DUMMYFUNCTION("""COMPUTED_VALUE"""),"City Of Ilagan") -> City Of Ilagan | Q93: =IFERROR(__xludf.DUMMYFUNCTION("""COMPUTED_VALUE"""),"Isabela") -> Isabela | R93: =IFERROR(__xludf.DUMMYFUNCTION("""COMPUTED_VALUE"""),2.0) -> 2
A94: =IFERROR(__xludf.DUMMYFUNCTION("""COMPUTED_VALUE"""),92.0) -> 92 | B94: =IFERROR(__xludf.DUMMYFUNCTION("""COMPUTED_VALUE"""),"NGABANGAB RESOURCES FARMERS ASSOCIATION") -> NGABANGAB RESOURCES FARMERS ASSOCIATION | C94: =IFERROR(__xludf.DUMMYFUNCTION("""COMPUTED_VALUE"""),"NGABANGAB, PASUQUIN, ILOCOS NORTE") -> NGABANGAB, PASUQUIN, ILOCOS NORTE | D94: =IFERROR(__xludf.DUMMYFUNCTION("""COMPUTED_VALUE"""),"#N/A") -> #N/A | E94: =IFERROR(__xludf.DUMMYFUNCTION("""COMPUTED_VALUE"""),"#N/A") -> #N/A | F94: =IFERROR(__xludf.DUMMYFUNCTION("""COMPUTED_VALUE"""),"RCEF 23-09-21 Rebidding") -> RCEF 23-09-21 Rebidding | G94: =IFERROR(__xludf.DUMMYFUNCTION("""COMPUTED_VALUE"""),2.0) -> 2 | H94: =IFERROR(__xludf.DUMMYFUNCTION("""COMPUTED_VALUE"""),17404.0) -> 17404 | I94: =IFERROR(__xludf.DUMMYFUNCTION("""COMPUTED_VALUE"""),"KMC5825 APPFPV0031") -> KMC5825 APPFPV0031 | J94: =IFERROR(__xludf.DUMMYFUNCTION("""COMPUTED_VALUE"""),"RTS 1000016") -> RTS 1000016 | K94: =IFERROR(__xludf.DUMMYFUNCTION("""COMPUTED_VALUE"""),"R-SERIES-012 PH") -> R-SERIES-012 PH | L94: =IFERROR(__xludf.DUMMYFUNCTION("""COMPUTED_VALUE"""),"LSGW -1750 -RMP- 24010121") -> LSGW -1750 -RMP- 24010121 | M94: =IFERROR(__xludf.DUMMYFUNCTION("""COMPUTED_VALUE"""),"WDP 0019") -> WDP 0019 | O94: =IFERROR(__xludf.DUMMYFUNCTION("""COMPUTED_VALUE"""),"Ngabangab") -> Ngabangab | P94: =IFERROR(__xludf.DUMMYFUNCTION("""COMPUTED_VALUE"""),"Pasuquin") -> Pasuquin | Q94: =IFERROR(__xludf.DUMMYFUNCTION("""COMPUTED_VALUE"""),"Ilocos Norte") -> Ilocos Norte | R94: =IFERROR(__xludf.DUMMYFUNCTION("""COMPUTED_VALUE"""),1.0) -> 1
A95: =IFERROR(__xludf.DUMMYFUNCTION("""COMPUTED_VALUE"""),93.0) -> 93 | B95: =IFERROR(__xludf.DUMMYFUNCTION("""COMPUTED_VALUE"""),"PANINAAN-DAYA FARMERS ASSOCIATION INC.") -> PANINAAN-DAYA FARMERS ASSOCIATION INC. | C95: =IFERROR(__xludf.DUMMYFUNCTION("""COMPUTED_VALUE"""),"PANINAAN, BACARRA, ILOCOS NORTE") -> PANINAAN, BACARRA, ILOCOS NORTE | D95: =IFERROR(__xludf.DUMMYFUNCTION("""COMPUTED_VALUE"""),"Antonio T. Lomotan") -> Antonio T. Lomotan | E95: =IFERROR(__xludf.DUMMYFUNCTION("""COMPUTED_VALUE"""),"0927-933-7043") -> 0927-933-7043 | F95: =IFERROR(__xludf.DUMMYFUNCTION("""COMPUTED_VALUE"""),"RCEF 23-09-21 Rebidding") -> RCEF 23-09-21 Rebidding | G95: =IFERROR(__xludf.DUMMYFUNCTION("""COMPUTED_VALUE"""),2.0) -> 2 | H95: =IFERROR(__xludf.DUMMYFUNCTION("""COMPUTED_VALUE"""),17405.0) -> 17405 | I95: =IFERROR(__xludf.DUMMYFUNCTION("""COMPUTED_VALUE"""),"KMC5825 AKPFPV0016") -> KMC5825 AKPFPV0016 | J95: =IFERROR(__xludf.DUMMYFUNCTION("""COMPUTED_VALUE"""),"RTS 1000017") -> RTS 1000017 | K95: =IFERROR(__xludf.DUMMYFUNCTION("""COMPUTED_VALUE"""),"RSERIES-014PH") -> RSERIES-014PH | L95: =IFERROR(__xludf.DUMMYFUNCTION("""COMPUTED_VALUE"""),"LSGW -1750 -RMP- 24010126") -> LSGW -1750 -RMP- 24010126 | M95: =IFERROR(__xludf.DUMMYFUNCTION("""COMPUTED_VALUE"""),"WDP 0020") -> WDP 0020 | O95: =IFERROR(__xludf.DUMMYFUNCTION("""COMPUTED_VALUE"""),"Paninaan") -> Paninaan | P95: =IFERROR(__xludf.DUMMYFUNCTION("""COMPUTED_VALUE"""),"Bacarra") -> Bacarra | Q95: =IFERROR(__xludf.DUMMYFUNCTION("""COMPUTED_VALUE"""),"Ilocos Norte") -> Ilocos Norte | R95: =IFERROR(__xludf.DUMMYFUNCTION("""COMPUTED_VALUE"""),1.0) -> 1
A96: =IFERROR(__xludf.DUMMYFUNCTION("""COMPUTED_VALUE"""),94.0) -> 94 | B96: =IFERROR(__xludf.DUMMYFUNCTION("""COMPUTED_VALUE"""),"62A NAVOTAS FARMERS ASSOCIATION INCORPORATED") -> 62A NAVOTAS FARMERS ASSOCIATION INCORPORATED | C96: =IFERROR(__xludf.DUMMYFUNCTION("""COMPUTED_VALUE"""),"62A- NAVOTAS NORTH, LAOAG CITY, ILOCOS NORTE") -> 62A- NAVOTAS NORTH, LAOAG CITY, ILOCOS NORTE | D96: =IFERROR(__xludf.DUMMYFUNCTION("""COMPUTED_VALUE"""),"#N/A") -> #N/A | E96: =IFERROR(__xludf.DUMMYFUNCTION("""COMPUTED_VALUE"""),"#N/A") -> #N/A | F96: =IFERROR(__xludf.DUMMYFUNCTION("""COMPUTED_VALUE"""),"RCEF 23-09-21 Rebidding") -> RCEF 23-09-21 Rebidding | G96: =IFERROR(__xludf.DUMMYFUNCTION("""COMPUTED_VALUE"""),2.0) -> 2 | H96: =IFERROR(__xludf.DUMMYFUNCTION("""COMPUTED_VALUE"""),17406.0) -> 17406 | I96: =IFERROR(__xludf.DUMMYFUNCTION("""COMPUTED_VALUE"""),"KMC5825 ALPFPV0006") -> KMC5825 ALPFPV0006 | J96: =IFERROR(__xludf.DUMMYFUNCTION("""COMPUTED_VALUE"""),"RTS 100007") -> RTS 100007 | K96: =IFERROR(__xludf.DUMMYFUNCTION("""COMPUTED_VALUE"""),"HL 22R009") -> HL 22R009 | L96: =IFERROR(__xludf.DUMMYFUNCTION("""COMPUTED_VALUE"""),"LSGW -1750 -RMP- 24010209") -> LSGW -1750 -RMP- 24010209 | M96: =IFERROR(__xludf.DUMMYFUNCTION("""COMPUTED_VALUE"""),"WDP 0021") -> WDP 0021 | O96: =IFERROR(__xludf.DUMMYFUNCTION("""COMPUTED_VALUE"""),"62A- Navotas North") -> 62A- Navotas North | P96: =IFERROR(__xludf.DUMMYFUNCTION("""COMPUTED_VALUE"""),"Laoag City") -> Laoag City | Q96: =IFERROR(__xludf.DUMMYFUNCTION("""COMPUTED_VALUE"""),"Ilocos Norte") -> Ilocos Norte | R96: =IFERROR(__xludf.DUMMYFUNCTION("""COMPUTED_VALUE"""),1.0) -> 1
A97: =IFERROR(__xludf.DUMMYFUNCTION("""COMPUTED_VALUE"""),95.0) -> 95 | B97: =IFERROR(__xludf.DUMMYFUNCTION("""COMPUTED_VALUE"""),"MAKALIGAYA IRRIGATORS ASSOCIATION INC.") -> MAKALIGAYA IRRIGATORS ASSOCIATION INC. | C97: =IFERROR(__xludf.DUMMYFUNCTION("""COMPUTED_VALUE"""),"Maligaya, Science City of Munoz, Nueva Ecija") -> Maligaya, Science City of Munoz, Nueva Ecija | D97: =IFERROR(__xludf.DUMMYFUNCTION("""COMPUTED_VALUE"""),"Ben Gagelonia") -> Ben Gagelonia | E97: =IFERROR(__xludf.DUMMYFUNCTION("""COMPUTED_VALUE"""),"0995-945-0742") -> 0995-945-0742 | F97: =IFERROR(__xludf.DUMMYFUNCTION("""COMPUTED_VALUE"""),"RCEF 23-09-21 Rebidding") -> RCEF 23-09-21 Rebidding | G97: =IFERROR(__xludf.DUMMYFUNCTION("""COMPUTED_VALUE"""),3.0) -> 3 | H97: =IFERROR(__xludf.DUMMYFUNCTION("""COMPUTED_VALUE"""),17524.0) -> 17524 | I97: =IFERROR(__xludf.DUMMYFUNCTION("""COMPUTED_VALUE"""),"KMC 5825 AKPFPV0001") -> KMC 5825 AKPFPV0001 | J97: =IFERROR(__xludf.DUMMYFUNCTION("""COMPUTED_VALUE"""),"PTS100001") -> PTS100001 | K97: =IFERROR(__xludf.DUMMYFUNCTION("""COMPUTED_VALUE"""),"R-SERIES 002PH") -> R-SERIES 002PH | L97: =IFERROR(__xludf.DUMMYFUNCTION("""COMPUTED_VALUE"""),"LSGW-RMP-2312174") -> LSGW-RMP-2312174 | M97: =IFERROR(__xludf.DUMMYFUNCTION("""COMPUTED_VALUE"""),"WDP-40-RMP-24010031") -> WDP-40-RMP-24010031 | O97: =IFERROR(__xludf.DUMMYFUNCTION("""COMPUTED_VALUE"""),"Maligaya") -> Maligaya | P97: =IFERROR(__xludf.DUMMYFUNCTION("""COMPUTED_VALUE"""),"Science City Of Munoz") -> Science City Of Munoz | Q97: =IFERROR(__xludf.DUMMYFUNCTION("""COMPUTED_VALUE"""),"Nueva Ecija") -> Nueva Ecija | R97: =IFERROR(__xludf.DUMMYFUNCTION("""COMPUTED_VALUE"""),3.0) -> 3
A98: =IFERROR(__xludf.DUMMYFUNCTION("""COMPUTED_VALUE"""),96.0) -> 96 | B98: =IFERROR(__xludf.DUMMYFUNCTION("""COMPUTED_VALUE"""),"MARAGOL IRRIGATORS ASSOCIATION INC.") -> MARAGOL IRRIGATORS ASSOCIATION INC. | C98: =IFERROR(__xludf.DUMMYFUNCTION("""COMPUTED_VALUE"""),"Maragol, Science City of Munoz, Nueva Ecija") -> Maragol, Science City of Munoz, Nueva Ecija | D98: =IFERROR(__xludf.DUMMYFUNCTION("""COMPUTED_VALUE"""),"Romulo Baustista") -> Romulo Baustista | E98: =IFERROR(__xludf.DUMMYFUNCTION("""COMPUTED_VALUE"""),"0929-468-5455") -> 0929-468-5455 | F98: =IFERROR(__xludf.DUMMYFUNCTION("""COMPUTED_VALUE"""),"RCEF 23-09-21 Rebidding") -> RCEF 23-09-21 Rebidding | G98: =IFERROR(__xludf.DUMMYFUNCTION("""COMPUTED_VALUE"""),3.0) -> 3 | H98: =IFERROR(__xludf.DUMMYFUNCTION("""COMPUTED_VALUE"""),17525.0) -> 17525 | I98: =IFERROR(__xludf.DUMMYFUNCTION("""COMPUTED_VALUE"""),"KMC 5825 AEPFPV0011") -> KMC 5825 AEPFPV0011 | J98: =IFERROR(__xludf.DUMMYFUNCTION("""COMPUTED_VALUE"""),"PTS100029") -> PTS100029 | K98: =IFERROR(__xludf.DUMMYFUNCTION("""COMPUTED_VALUE"""),"R-SERIES 021PH") -> R-SERIES 021PH | L98: =IFERROR(__xludf.DUMMYFUNCTION("""COMPUTED_VALUE"""),"LSGW1750 RMP 24010225") -> LSGW1750 RMP 24010225 | M98: =IFERROR(__xludf.DUMMYFUNCTION("""COMPUTED_VALUE"""),"WDP40 RMP 24050626") -> WDP40 RMP 24050626 | O98: =IFERROR(__xludf.DUMMYFUNCTION("""COMPUTED_VALUE"""),"Maragol") -> Maragol | P98: =IFERROR(__xludf.DUMMYFUNCTION("""COMPUTED_VALUE"""),"Science City Of Munoz") -> Science City Of Munoz | Q98: =IFERROR(__xludf.DUMMYFUNCTION("""COMPUTED_VALUE"""),"Nueva Ecija") -> Nueva Ecija | R98: =IFERROR(__xludf.DUMMYFUNCTION("""COMPUTED_VALUE"""),3.0) -> 3
A99: =IFERROR(__xludf.DUMMYFUNCTION("""COMPUTED_VALUE"""),97.0) -> 97 | B99: =IFERROR(__xludf.DUMMYFUNCTION("""COMPUTED_VALUE"""),"TRY ME AGRICULTURE COOPERATIVE (TMAC)") -> TRY ME AGRICULTURE COOPERATIVE (TMAC) | C99: =IFERROR(__xludf.DUMMYFUNCTION("""COMPUTED_VALUE"""),"Poblacion West, Science City of Munoz, Nueva Ecija") -> Poblacion West, Science City of Munoz, Nueva Ecija | D99: =IFERROR(__xludf.DUMMYFUNCTION("""COMPUTED_VALUE"""),"Sofronio G. Padua") -> Sofronio G. Padua | E99: =IFERROR(__xludf.DUMMYFUNCTION("""COMPUTED_VALUE"""),"0917-988-2079") -> 0917-988-2079 | F99: =IFERROR(__xludf.DUMMYFUNCTION("""COMPUTED_VALUE"""),"RCEF 23-09-21 Rebidding") -> RCEF 23-09-21 Rebidding | G99: =IFERROR(__xludf.DUMMYFUNCTION("""COMPUTED_VALUE"""),3.0) -> 3 | H99: =IFERROR(__xludf.DUMMYFUNCTION("""COMPUTED_VALUE"""),17526.0) -> 17526 | I99: =IFERROR(__xludf.DUMMYFUNCTION("""COMPUTED_VALUE"""),"KMC 5825 ATPFPV0027") -> KMC 5825 ATPFPV0027 | J99: =IFERROR(__xludf.DUMMYFUNCTION("""COMPUTED_VALUE"""),"PTS100024") -> PTS100024 | K99: =IFERROR(__xludf.DUMMYFUNCTION("""COMPUTED_VALUE"""),"R-SERIES 004PH") -> R-SERIES 004PH | L99: =IFERROR(__xludf.DUMMYFUNCTION("""COMPUTED_VALUE"""),"LSGW1750 RMP 24020416") -> LSGW1750 RMP 24020416 | M99: =IFERROR(__xludf.DUMMYFUNCTION("""COMPUTED_VALUE"""),"WDP40 RMP 24050633") -> WDP40 RMP 24050633 | O99: =IFERROR(__xludf.DUMMYFUNCTION("""COMPUTED_VALUE"""),"Poblacion West") -> Poblacion West | P99: =IFERROR(__xludf.DUMMYFUNCTION("""COMPUTED_VALUE"""),"Science City Of Munoz") -> Science City Of Munoz | Q99: =IFERROR(__xludf.DUMMYFUNCTION("""COMPUTED_VALUE"""),"Nueva Ecija") -> Nueva Ecija | R99: =IFERROR(__xludf.DUMMYFUNCTION("""COMPUTED_VALUE"""),3.0) -> 3
A100: =IFERROR(__xludf.DUMMYFUNCTION("""COMPUTED_VALUE"""),98.0) -> 98 | B100: =IFERROR(__xludf.DUMMYFUNCTION("""COMPUTED_VALUE"""),"LA PAZ FARMERS ASSOCIATION") -> LA PAZ FARMERS ASSOCIATION | C100: =IFERROR(__xludf.DUMMYFUNCTION("""COMPUTED_VALUE"""),"La Paz, Magalang, PAMPANGA") -> La Paz, Magalang, PAMPANGA | D100: =IFERROR(__xludf.DUMMYFUNCTION("""COMPUTED_VALUE"""),"ROLANDO P. BARTOLO") -> ROLANDO P. BARTOLO | E100: =IFERROR(__xludf.DUMMYFUNCTION("""COMPUTED_VALUE"""),"0926-188-3530") -> 0926-188-3530 | F100: =IFERROR(__xludf.DUMMYFUNCTION("""COMPUTED_VALUE"""),"RCEF 23-09-21 Rebidding") -> RCEF 23-09-21 Rebidding | G100: =IFERROR(__xludf.DUMMYFUNCTION("""COMPUTED_VALUE"""),3.0) -> 3 | H100: =IFERROR(__xludf.DUMMYFUNCTION("""COMPUTED_VALUE"""),17782.0) -> 17782 | I100: =IFERROR(__xludf.DUMMYFUNCTION("""COMPUTED_VALUE"""),"KMC5825 AAPFPV0151") -> KMC5825 AAPFPV0151 | J100: =IFERROR(__xludf.DUMMYFUNCTION("""COMPUTED_VALUE"""),"PTS100089") -> PTS100089 | K100: =IFERROR(__xludf.DUMMYFUNCTION("""COMPUTED_VALUE"""),"R-SERIES 090PH") -> R-SERIES 090PH | L100: =IFERROR(__xludf.DUMMYFUNCTION("""COMPUTED_VALUE"""),"LSGW1750-RMP-2312030") -> LSGW1750-RMP-2312030 | M100: =IFERROR(__xludf.DUMMYFUNCTION("""COMPUTED_VALUE"""),"WDP40-RMP-2312013") -> WDP40-RMP-2312013 | O100: =IFERROR(__xludf.DUMMYFUNCTION("""COMPUTED_VALUE"""),"La Paz") -> La Paz | P100: =IFERROR(__xludf.DUMMYFUNCTION("""COMPUTED_VALUE"""),"Magalang") -> Magalang | Q100: =IFERROR(__xludf.DUMMYFUNCTION("""COMPUTED_VALUE"""),"Pampanga") -> Pampanga | R100: =IFERROR(__xludf.DUMMYFUNCTION("""COMPUTED_VALUE"""),3.0) -> 3
...

Sheet MONITORING
A1: NO | B1: Recipient | C1: Address | E1: RECIPIENT | F1: ADDRESS | G1: BRGY | H1: CITY /TOWN | I1: PROVINCE | J1: CONTACT | K1: CP NUMBER | L1: {=XLOOKUP($A1,'Recipients REF'!$A:$A,'Recipients REF'!F:F,"",0)} -> Project REF | M1: LOT | N1: {=XLOOKUP($A1,'Recipients REF'!$A:$A,'Recipients REF'!H:H,"",0)} -> DR NO. | O1: Tractor | Q1: {=XLOOKUP($A1,'Recipients REF'!$A:$A,'Recipients REF'!I:I,"",0)} -> Tractor SN | R1: {=XLOOKUP($A1,'Recipients REF'!$A:$A,'Recipients REF'!J:J,"",0)} -> Tractor EN | S1: Front Loader | U1: {=XLOOKUP($A1,'Recipients REF'!$A:$A,'Recipients REF'!K:K,"",0)} -> Front Loader SN | V1: Rotavator | X1: {=XLOOKUP($A1,'Recipients REF'!$A:$A,'Recipients REF'!L:L,"",0)} -> Rotavator SN | Y1: Disc Plow | AA1: {=XLOOKUP($A1,'Recipients REF'!$A:$A,'Recipients REF'!M:M,"",0)} -> Disc Plow SN | AC1: IN-CHARGE | AD1: GPS IMEI (OLD) | AE1: GPS IMEI | AF1: GPS SIM CARD NUMBER | AG1: DATE OF VISIT | AI1: 2024 | AJ1: 2024
I2: GROUPINGS | O2: Brand | P2: Model | S2: Brand | T2: Model | V2: Brand | W2: Model | Y2: Brand | Z2: Model | AI2: GPS IMEI | AJ2: GPS SIM CARD NUMBER
A3: 300 | B3: Aquino Cluster Farmers Association | C3: Aquino, Ibajay, AKLAN | E3: =PROPER(B3) -> Aquino Cluster Farmers Association | F3: =PROPER(C3) -> Aquino, Ibajay, Aklan | G3: =PROPER(TRIM(LEFT(F3,FIND(",",F3)-1))) -> Aquino | H3: =PROPER(TRIM(MID(F3,FIND(",",F3)+1,FIND(",",F3,FIND(",",F3)+1)-FIND(",",F3)-1))) -> Ibajay | I3: =PROPER(TRIM(RIGHT(F3,LEN(F3)-FIND(",",F3,FIND(",",F3)+1)))) -> Aklan | J3: {=XLOOKUP($E3,'Recipients REF'!$B:$B,'Recipients REF'!D:D,"",0)} -> Sermundo Conan | K3: {=XLOOKUP($E3,'Recipients REF'!$B:$B,'Recipients REF'!E:E,"",0)} -> 0910-874-4791 | L3: {=XLOOKUP($A3,'Recipients REF'!$A:$A,'Recipients REF'!F:F,"",0)} -> RCEF 23-09-21 Rebidding | M3: {=XLOOKUP($A3,'Recipients REF'!$A:$A,'Recipients REF'!G:G,"",0)} -> 4 | N3: {=XLOOKUP($A3,'Recipients REF'!$A:$A,'Recipients REF'!H:H,"",0)} -> 18898 | O3: TYM | P3: 5825R | Q3: {=XLOOKUP($A3,'Recipients REF'!$A:$A,'Recipients REF'!I:I,"",0)} -> KMC5825 AHRFPV0303 | R3: {=XLOOKUP($A3,'Recipients REF'!$A:$A,'Recipients REF'!J:J,"",0)} -> RTS100189 | S3: HANIL | T3: HL25 | U3: {=XLOOKUP($A3,'Recipients REF'!$A:$A,'Recipients REF'!K:K,"",0)} -> R-SERIES 042 PH | V3: WECAN | W3: LSGW1750 | X3: {=XLOOKUP($A3,'Recipients REF'!$A:$A,'Recipients REF'!L:L,"",0)} -> LSGW1750 RMP 24020425 | Y3: WECAN | Z3: WDP40 | AA3: {=XLOOKUP($A3,'Recipients REF'!$A:$A,'Recipients REF'!M:M,"",0)} -> WDP40 RMP 24030385 | AI3: {=XLOOKUP($E3,Sheet11!$D:$D,Sheet11!$X:$X,"",0)} | AJ3: {=XLOOKUP($E3,Sheet11!$D:$D,Sheet11!$Y:$Y,"",0)}
A4: 301 | B4: Laguinbanua Integrated Farmers Association | C4: Laguinbanua, Ibajay, AKLAN | E4: =PROPER(B4) -> Laguinbanua Integrated Farmers Association | F4: =PROPER(C4) -> Laguinbanua, Ibajay, Aklan | G4: =PROPER(TRIM(LEFT(F4,FIND(",",F4)-1))) -> Laguinbanua | H4: =PROPER(TRIM(MID(F4,FIND(",",F4)+1,FIND(",",F4,FIND(",",F4)+1)-FIND(",",F4)-1))) -> Ibajay | I4: =PROPER(TRIM(RIGHT(F4,LEN(F4)-FIND(",",F4,FIND(",",F4)+1)))) -> Aklan | J4: {=XLOOKUP($E4,'Recipients REF'!$B:$B,'Recipients REF'!D:D,"",0)} -> Chevy Fernandez | K4: {=XLOOKUP($E4,'Recipients REF'!$B:$B,'Recipients REF'!E:E,"",0)} -> 0919-241-3021 | L4: {=XLOOKUP($A4,'Recipients REF'!$A:$A,'Recipients REF'!F:F,"",0)} -> RCEF 23-09-21 Rebidding | M4: {=XLOOKUP($A4,'Recipients REF'!$A:$A,'Recipients REF'!G:G,"",0)} -> 4 | N4: {=XLOOKUP($A4,'Recipients REF'!$A:$A,'Recipients REF'!H:H,"",0)} -> 18899 | O4: TYM | P4: 5825R | Q4: {=XLOOKUP($A4,'Recipients REF'!$A:$A,'Recipients REF'!I:I,"",0)} -> KMC5825 ALRFPV0393 | R4: {=XLOOKUP($A4,'Recipients REF'!$A:$A,'Recipients REF'!J:J,"",0)} -> RTS100304 | S4: HANIL | T4: HL25 | U4: {=XLOOKUP($A4,'Recipients REF'!$A:$A,'Recipients REF'!K:K,"",0)} -> R-SERIES 035 PH | V4: WECAN | W4: LSGW1750 | X4: {=XLOOKUP($A4,'Recipients REF'!$A:$A,'Recipients REF'!L:L,"",0)} -> LSGW1750 RMP 24020477 | Y4: WECAN | Z4: WDP40 | AA4: {=XLOOKUP($A4,'Recipients REF'!$A:$A,'Recipients REF'!M:M,"",0)} -> WDP40 RMP 24030340 | AI4: {=XLOOKUP($E4,Sheet11!$D:$D,Sheet11!$X:$X,"",0)} | AJ4: {=XLOOKUP($E4,Sheet11!$D:$D,Sheet11!$Y:$Y,"",0)}
A5: 302 | B5: AGCAWILAN-SILAKAT NONOK FARMERS CLUSTER ASSOCIATION | C5: Agcawilan, Lezo, AKLAN | E5: =PROPER(B5) -> Agcawilan-Silakat Nonok Farmers Cluster Association | F5: =PROPER(C5) -> Agcawilan, Lezo, Aklan | G5: =PROPER(TRIM(LEFT(F5,FIND(",",F5)-1))) -> Agcawilan | H5: =PROPER(TRIM(MID(F5,FIND(",",F5)+1,FIND(",",F5,FIND(",",F5)+1)-FIND(",",F5)-1))) -> Lezo | I5: =PROPER(TRIM(RIGHT(F5,LEN(F5)-FIND(",",F5,FIND(",",F5)+1)))) -> Aklan | J5: {=XLOOKUP($E5,'Recipients REF'!$B:$B,'Recipients REF'!D:D,"",0)} -> MARIO Z. ZAULDA | K5: {=XLOOKUP($E5,'Recipients REF'!$B:$B,'Recipients REF'!E:E,"",0)} -> 0951-208-9996 | L5: {=XLOOKUP($A5,'Recipients REF'!$A:$A,'Recipients REF'!F:F,"",0)} -> RCEF 23-09-21 Rebidding | M5: {=XLOOKUP($A5,'Recipients REF'!$A:$A,'Recipients REF'!G:G,"",0)} -> 4 | N5: {=XLOOKUP($A5,'Recipients REF'!$A:$A,'Recipients REF'!H:H,"",0)} -> 18900 | O5: TYM | P5: 5825R | Q5: {=XLOOKUP($A5,'Recipients REF'!$A:$A,'Recipients REF'!I:I,"",0)} -> KMC5825 ACRFPV0327 | R5: {=XLOOKUP($A5,'Recipients REF'!$A:$A,'Recipients REF'!J:J,"",0)} -> RTS100167 | S5: HANIL | T5: HL25 | U5: {=XLOOKUP($A5,'Recipients REF'!$A:$A,'Recipients REF'!K:K,"",0)} -> R-SERIES 019 PH | V5: WECAN | W5: LSGW1750 | X5: {=XLOOKUP($A5,'Recipients REF'!$A:$A,'Recipients REF'!L:L,"",0)} -> LSGW1750 RMP 24020460 | Y5: WECAN | Z5: WDP40 | AA5: {=XLOOKUP($A5,'Recipients REF'!$A:$A,'Recipients REF'!M:M,"",0)} -> WDP40 RMP 24030363 | AI5: {=XLOOKUP($E5,Sheet11!$D:$D,Sheet11!$X:$X,"",0)} | AJ5: {=XLOOKUP($E5,Sheet11!$D:$D,Sheet11!$Y:$Y,"",0)}
A6: 303 | B6: Lezo Multi-purpose Cooperative | C6: Poblacion, Lezo, AKLAN | E6: =PROPER(B6) -> Lezo Multi-Purpose Cooperative | F6: =PROPER(C6) -> Poblacion, Lezo, Aklan | G6: =PROPER(TRIM(LEFT(F6,FIND(",",F6)-1))) -> Poblacion | H6: =PROPER(TRIM(MID(F6,FIND(",",F6)+1,FIND(",",F6,FIND(",",F6)+1)-FIND(",",F6)-1))) -> Lezo | I6: =PROPER(TRIM(RIGHT(F6,LEN(F6)-FIND(",",F6,FIND(",",F6)+1)))) -> Aklan | J6: {=XLOOKUP($E6,'Recipients REF'!$B:$B,'Recipients REF'!D:D,"",0)} -> Emelinda R. Dela Cruz | K6: {=XLOOKUP($E6,'Recipients REF'!$B:$B,'Recipients REF'!E:E,"",0)} -> 0918-957-2998 | L6: {=XLOOKUP($A6,'Recipients REF'!$A:$A,'Recipients REF'!F:F,"",0)} -> RCEF 23-09-21 Rebidding | M6: {=XLOOKUP($A6,'Recipients REF'!$A:$A,'Recipients REF'!G:G,"",0)} -> 4 | N6: {=XLOOKUP($A6,'Recipients REF'!$A:$A,'Recipients REF'!H:H,"",0)} -> 18901 | O6: TYM | P6: 5825R | Q6: {=XLOOKUP($A6,'Recipients REF'!$A:$A,'Recipients REF'!I:I,"",0)} -> KMC5825 ATRFPV0421 | R6: {=XLOOKUP($A6,'Recipients REF'!$A:$A,'Recipients REF'!J:J,"",0)} -> RTS100327 | S6: HANIL | T6: HL25 | U6: {=XLOOKUP($A6,'Recipients REF'!$A:$A,'Recipients REF'!K:K,"",0)} -> R-SERIES 125 PH | V6: WECAN | W6: LSGW1750 | X6: {=XLOOKUP($A6,'Recipients REF'!$A:$A,'Recipients REF'!L:L,"",0)} -> LSGW1750 RMP 24020486 | Y6: WECAN | Z6: WDP40 | AA6: {=XLOOKUP($A6,'Recipients REF'!$A:$A,'Recipients REF'!M:M,"",0)} -> WDP40 RMP 24030342 | AI6: {=XLOOKUP($E6,Sheet11!$D:$D,Sheet11!$X:$X,"",0)} | AJ6: {=XLOOKUP($E6,Sheet11!$D:$D,Sheet11!$Y:$Y,"",0)}
A7: 304 | B7: DTC-PRO Farmers Irrigators' Association, Inc. | C7: Dumga, Makato, AKLAN | E7: =PROPER(B7) -> Dtc-Pro Farmers Irrigators' Association, Inc. | F7: =PROPER(C7) -> Dumga, Makato, Aklan | G7: =PROPER(TRIM(LEFT(F7,FIND(",",F7)-1))) -> Dumga | H7: =PROPER(TRIM(MID(F7,FIND(",",F7)+1,FIND(",",F7,FIND(",",F7)+1)-FIND(",",F7)-1))) -> Makato | I7: =PROPER(TRIM(RIGHT(F7,LEN(F7)-FIND(",",F7,FIND(",",F7)+1)))) -> Aklan | J7: {=XLOOKUP($E7,'Recipients REF'!$B:$B,'Recipients REF'!D:D,"",0)} -> Ramon Togoto | K7: {=XLOOKUP($E7,'Recipients REF'!$B:$B,'Recipients REF'!E:E,"",0)} -> 0909-929-3299 | L7: {=XLOOKUP($A7,'Recipients REF'!$A:$A,'Recipients REF'!F:F,"",0)} -> RCEF 23-09-21 Rebidding | M7: {=XLOOKUP($A7,'Recipients REF'!$A:$A,'Recipients REF'!G:G,"",0)} -> 4 | N7: {=XLOOKUP($A7,'Recipients REF'!$A:$A,'Recipients REF'!H:H,"",0)} -> 18902 | O7: TYM | P7: 5825R | Q7: {=XLOOKUP($A7,'Recipients REF'!$A:$A,'Recipients REF'!I:I,"",0)} -> KMC5825 AHRFPV0463 | R7: {=XLOOKUP($A7,'Recipients REF'!$A:$A,'Recipients REF'!J:J,"",0)} -> RTS100376 | S7: HANIL | T7: HL25 | U7: {=XLOOKUP($A7,'Recipients REF'!$A:$A,'Recipients REF'!K:K,"",0)} -> R-SERIES 274 PH | V7: WECAN | W7: LSGW1750 | X7: {=XLOOKUP($A7,'Recipients REF'!$A:$A,'Recipients REF'!L:L,"",0)} -> LSGW1750 RMP 24020489 | Y7: WECAN | Z7: WDP40 | AA7: {=XLOOKUP($A7,'Recipients REF'!$A:$A,'Recipients REF'!M:M,"",0)} -> WDP40 RMP 24040397 | AI7: {=XLOOKUP($E7,Sheet11!$D:$D,Sheet11!$X:$X,"",0)} | AJ7: {=XLOOKUP($E7,Sheet11!$D:$D,Sheet11!$Y:$Y,"",0)}
A8: 305 | B8: Navitas Farmer's Association (NFA) | C8: Navitas, Malinao, AKLAN | E8: =PROPER(B8) -> Navitas Farmer'S Association (Nfa) | F8: =PROPER(C8) -> Navitas, Malinao, Aklan | G8: =PROPER(TRIM(LEFT(F8,FIND(",",F8)-1))) -> Navitas | H8: =PROPER(TRIM(MID(F8,FIND(",",F8)+1,FIND(",",F8,FIND(",",F8)+1)-FIND(",",F8)-1))) -> Malinao | I8: =PROPER(TRIM(RIGHT(F8,LEN(F8)-FIND(",",F8,FIND(",",F8)+1)))) -> Aklan | J8: {=XLOOKUP($E8,'Recipients REF'!$B:$B,'Recipients REF'!D:D,"",0)} -> Rose Melinda Odorita | K8: {=XLOOKUP($E8,'Recipients REF'!$B:$B,'Recipients REF'!E:E,"",0)} -> 0946-380-6871 | L8: {=XLOOKUP($A8,'Recipients REF'!$A:$A,'Recipients REF'!F:F,"",0)} -> RCEF 23-09-21 Rebidding | M8: {=XLOOKUP($A8,'Recipients REF'!$A:$A,'Recipients REF'!G:G,"",0)} -> 4 | N8: {=XLOOKUP($A8,'Recipients REF'!$A:$A,'Recipients REF'!H:H,"",0)} -> 18903 | O8: TYM | P8: 5825R | Q8: {=XLOOKUP($A8,'Recipients REF'!$A:$A,'Recipients REF'!I:I,"",0)} -> KMC5825AHRFPV0379 | R8: {=XLOOKUP($A8,'Recipients REF'!$A:$A,'Recipients REF'!J:J,"",0)} -> RTS100263 | S8: HANIL | T8: HL25 | U8: {=XLOOKUP($A8,'Recipients REF'!$A:$A,'Recipients REF'!K:K,"",0)} -> R-SERIES 120 PH | V8: WECAN | W8: LSGW1750 | X8: {=XLOOKUP($A8,'Recipients REF'!$A:$A,'Recipients REF'!L:L,"",0)} -> LSGW1750 RMP 24020459 | Y8: WECAN | Z8: WDP40 | AA8: {=XLOOKUP($A8,'Recipients REF'!$A:$A,'Recipients REF'!M:M,"",0)} -> WDP40 RMP 24010120 | AI8: {=XLOOKUP($E8,Sheet11!$D:$D,Sheet11!$X:$X,"",0)} | AJ8: {=XLOOKUP($E8,Sheet11!$D:$D,Sheet11!$Y:$Y,"",0)}
A9: 306 | B9: Solido Cluster Farmers Association | C9: Solido, Nabas, AKLAN | E9: =PROPER(B9) -> Solido Cluster Farmers Association | F9: =PROPER(C9) -> Solido, Nabas, Aklan | G9: =PROPER(TRIM(LEFT(F9,FIND(",",F9)-1))) -> Solido | H9: =PROPER(TRIM(MID(F9,FIND(",",F9)+1,FIND(",",F9,FIND(",",F9)+1)-FIND(",",F9)-1))) -> Nabas | I9: =PROPER(TRIM(RIGHT(F9,LEN(F9)-FIND(",",F9,FIND(",",F9)+1)))) -> Aklan | J9: {=XLOOKUP($E9,'Recipients REF'!$B:$B,'Recipients REF'!D:D,"",0)} -> Felix Dubrico | K9: {=XLOOKUP($E9,'Recipients REF'!$B:$B,'Recipients REF'!E:E,"",0)} -> 0907-602-9968 | L9: {=XLOOKUP($A9,'Recipients REF'!$A:$A,'Recipients REF'!F:F,"",0)} -> RCEF 23-09-21 Rebidding | M9: {=XLOOKUP($A9,'Recipients REF'!$A:$A,'Recipients REF'!G:G,"",0)} -> 4 | N9: {=XLOOKUP($A9,'Recipients REF'!$A:$A,'Recipients REF'!H:H,"",0)} -> 18904 | O9: TYM | P9: 5825R | Q9: {=XLOOKUP($A9,'Recipients REF'!$A:$A,'Recipients REF'!I:I,"",0)} -> KMC5825 AKRFPV0325 | R9: {=XLOOKUP($A9,'Recipients REF'!$A:$A,'Recipients REF'!J:J,"",0)} -> RTS100168 | S9: HANIL | T9: HL25 | U9: {=XLOOKUP($A9,'Recipients REF'!$A:$A,'Recipients REF'!K:K,"",0)} -> R-SERIES 060 PH | V9: WECAN | W9: LSGW1750 | X9: {=XLOOKUP($A9,'Recipients REF'!$A:$A,'Recipients REF'!L:L,"",0)} -> LSGW1750 RMP 24020483 | Y9: WECAN | Z9: WDP40 | AA9: {=XLOOKUP($A9,'Recipients REF'!$A:$A,'Recipients REF'!M:M,"",0)} -> WDP40 RMP 24040464 | AI9: {=XLOOKUP($E9,Sheet11!$D:$D,Sheet11!$X:$X,"",0)} | AJ9: {=XLOOKUP($E9,Sheet11!$D:$D,Sheet11!$Y:$Y,"",0)}
A10: 307 | B10: INTEGRATED BARANGAYS OF NUMANCIA MULTI-PURPOSE COOPERATIVE (IBON MPC) | C10: Pusiw, Numancia, AKLAN | E10: =PROPER(B10) -> Integrated Barangays Of Numancia Multi-Purpose Cooperative (Ibon Mpc) | F10: =PROPER(C10) -> Pusiw, Numancia, Aklan | G10: =PROPER(TRIM(LEFT(F10,FIND(",",F10)-1))) -> Pusiw | H10: =PROPER(TRIM(MID(F10,FIND(",",F10)+1,FIND(",",F10,FIND(",",F10)+1)-FIND(",",F10)-1))) -> Numancia | I10: =PROPER(TRIM(RIGHT(F10,LEN(F10)-FIND(",",F10,FIND(",",F10)+1)))) -> Aklan | J10: {=XLOOKUP($E10,'Recipients REF'!$B:$B,'Recipients REF'!D:D,"",0)} -> Stineli F. Barrios | K10: {=XLOOKUP($E10,'Recipients REF'!$B:$B,'Recipients REF'!E:E,"",0)} -> 0948-151-6655 | L10: {=XLOOKUP($A10,'Recipients REF'!$A:$A,'Recipients REF'!F:F,"",0)} -> RCEF 23-09-21 Rebidding | M10: {=XLOOKUP($A10,'Recipients REF'!$A:$A,'Recipients REF'!G:G,"",0)} -> 4 | N10: {=XLOOKUP($A10,'Recipients REF'!$A:$A,'Recipients REF'!H:H,"",0)} -> 18905 | O10: TYM | P10: 5825R | Q10: {=XLOOKUP($A10,'Recipients REF'!$A:$A,'Recipients REF'!I:I,"",0)} -> KMC5825 AHRFPV0396 | R10: {=XLOOKUP($A10,'Recipients REF'!$A:$A,'Recipients REF'!J:J,"",0)} -> RTS100291 | S10: HANIL | T10: HL25 | U10: {=XLOOKUP($A10,'Recipients REF'!$A:$A,'Recipients REF'!K:K,"",0)} -> R-SERIES 016 PH | V10: WECAN | W10: LSGW1750 | X10: {=XLOOKUP($A10,'Recipients REF'!$A:$A,'Recipients REF'!L:L,"",0)} -> LSGW1750 RMP 24020478 | Y10: WECAN | Z10: WDP40 | AA10: {=XLOOKUP($A10,'Recipients REF'!$A:$A,'Recipients REF'!M:M,"",0)} -> WDP40 RMP 24010123 | AI10: {=XLOOKUP($E10,Sheet11!$D:$D,Sheet11!$X:$X,"",0)} | AJ10: {=XLOOKUP($E10,Sheet11!$D:$D,Sheet11!$Y:$Y,"",0)}
A11: 308 | B11: Laguinbanua West Farmers Association | C11: Laguinbanua West, Numancia, AKLAN | E11: =PROPER(B11) -> Laguinbanua West Farmers Association | F11: =PROPER(C11) -> Laguinbanua West, Numancia, Aklan | G11: =PROPER(TRIM(LEFT(F11,FIND(",",F11)-1))) -> Laguinbanua West | H11: =PROPER(TRIM(MID(F11,FIND(",",F11)+1,FIND(",",F11,FIND(",",F11)+1)-FIND(",",F11)-1))) -> Numancia | I11: =PROPER(TRIM(RIGHT(F11,LEN(F11)-FIND(",",F11,FIND(",",F11)+1)))) -> Aklan | J11: {=XLOOKUP($E11,'Recipients REF'!$B:$B,'Recipients REF'!D:D,"",0)} -> Leonarda B. De Miguel | K11: {=XLOOKUP($E11,'Recipients REF'!$B:$B,'Recipients REF'!E:E,"",0)} -> 0918-448-2414 | L11: {=XLOOKUP($A11,'Recipients REF'!$A:$A,'Recipients REF'!F:F,"",0)} -> RCEF 23-09-21 Rebidding | M11: {=XLOOKUP($A11,'Recipients REF'!$A:$A,'Recipients REF'!G:G,"",0)} -> 4 | N11: {=XLOOKUP($A11,'Recipients REF'!$A:$A,'Recipients REF'!H:H,"",0)} -> 18906 | O11: TYM | P11: 5825R | Q11: {=XLOOKUP($A11,'Recipients REF'!$A:$A,'Recipients REF'!I:I,"",0)} -> KMC5825 ALRFPV0381 | R11: {=XLOOKUP($A11,'Recipients REF'!$A:$A,'Recipients REF'!J:J,"",0)} -> RTS100249 | S11: HANIL | T11: HL25 | U11: {=XLOOKUP($A11,'Recipients REF'!$A:$A,'Recipients REF'!K:K,"",0)} -> R-SERIES 007 PH | V11: WECAN | W11: LSGW1750 | X11: {=XLOOKUP($A11,'Recipients REF'!$A:$A,'Recipients REF'!L:L,"",0)} -> LSGW1750 RMP 24020476 | Y11: WECAN | Z11: WDP40 | AA11: {=XLOOKUP($A11,'Recipients REF'!$A:$A,'Recipients REF'!M:M,"",0)} -> WDP40 RMP 24010113 | AI11: {=XLOOKUP($E11,Sheet11!$D:$D,Sheet11!$X:$X,"",0)} | AJ11: {=XLOOKUP($E11,Sheet11!$D:$D,Sheet11!$Y:$Y,"",0)}
A12: 382 | B12: Dalipdip Integrated Farmers Association | C12: Dalipdip, Altavas, AKLAN | E12: =PROPER(B12) -> Dalipdip Integrated Farmers Association | F12: =PROPER(C12) -> Dalipdip, Altavas, Aklan | G12: =PROPER(TRIM(LEFT(F12,FIND(",",F12)-1))) -> Dalipdip | H12: =PROPER(TRIM(MID(F12,FIND(",",F12)+1,FIND(",",F12,FIND(",",F12)+1)-FIND(",",F12)-1))) -> Altavas | I12: =PROPER(TRIM(RIGHT(F12,LEN(F12)-FIND(",",F12,FIND(",",F12)+1)))) -> Aklan | J12: {=XLOOKUP($E12,'Recipients REF'!$B:$B,'Recipients REF'!D:D,"",0)} -> Reynaldo G. Gallo | K12: {=XLOOKUP($E12,'Recipients REF'!$B:$B,'Recipients REF'!E:E,"",0)} -> 0921-882-9361 | L12: {=XLOOKUP($A12,'Recipients REF'!$A:$A,'Recipients REF'!F:F,"",0)} -> RCEF 23-09-21 Rebidding | M12: {=XLOOKUP($A12,'Recipients REF'!$A:$A,'Recipients REF'!G:G,"",0)} -> 4 | N12: {=XLOOKUP($A12,'Recipients REF'!$A:$A,'Recipients REF'!H:H,"",0)} -> 19040 | O12: TYM | P12: 5825R | Q12: {=XLOOKUP($A12,'Recipients REF'!$A:$A,'Recipients REF'!I:I,"",0)} -> KMC5825ALRFPV0543 | R12: {=XLOOKUP($A12,'Recipients REF'!$A:$A,'Recipients REF'!J:J,"",0)} -> RTS100446 | S12: HANIL | T12: HL25 | U12: {=XLOOKUP($A12,'Recipients REF'!$A:$A,'Recipients REF'!K:K,"",0)} -> WR-SERIES 766 PH | V12: WECAN | W12: LSGW1750 | X12: {=XLOOKUP($A12,'Recipients REF'!$A:$A,'Recipients REF'!L:L,"",0)} -> LSGW1750 RMP 24040657 | Y12: WECAN | Z12: WDP40 | AA12: {=XLOOKUP($A12,'Recipients REF'!$A:$A,'Recipients REF'!M:M,"",0)} -> WDP40 RMP 24040414 | AI12: {=XLOOKUP($E12,Sheet11!$D:$D,Sheet11!$X:$X,"",0)} -> 869066060243228 | AJ12: {=XLOOKUP($E12,Sheet11!$D:$D,Sheet11!$Y:$Y,"",0)} -> 9083571281
A13: 383 | B13: Mabais Tagaytay Bantayan Farmer’s Association | C13: Feliciano, Balete, AKLAN | E13: =PROPER(B13) -> Mabais Tagaytay Bantayan Farmer’S Association | F13: =PROPER(C13) -> Feliciano, Balete, Aklan | G13: =PROPER(TRIM(LEFT(F13,FIND(",",F13)-1))) -> Feliciano | H13: =PROPER(TRIM(MID(F13,FIND(",",F13)+1,FIND(",",F13,FIND(",",F13)+1)-FIND(",",F13)-1))) -> Balete | I13: =PROPER(TRIM(RIGHT(F13,LEN(F13)-FIND(",",F13,FIND(",",F13)+1)))) -> Aklan | J13: {=XLOOKUP($E13,'Recipients REF'!$B:$B,'Recipients REF'!D:D,"",0)} -> Raul Birol | K13: {=XLOOKUP($E13,'Recipients REF'!$B:$B,'Recipients REF'!E:E,"",0)} -> 0909-855-9889 | L13: {=XLOOKUP($A13,'Recipients REF'!$A:$A,'Recipients REF'!F:F,"",0)} -> RCEF 23-09-21 Rebidding | M13: {=XLOOKUP($A13,'Recipients REF'!$A:$A,'Recipients REF'!G:G,"",0)} -> 4 | N13: {=XLOOKUP($A13,'Recipients REF'!$A:$A,'Recipients REF'!H:H,"",0)} -> 19041 | O13: TYM | P13: 5825R | Q13: {=XLOOKUP($A13,'Recipients REF'!$A:$A,'Recipients REF'!I:I,"",0)} -> KMC5825ALRFPV0644 | R13: {=XLOOKUP($A13,'Recipients REF'!$A:$A,'Recipients REF'!J:J,"",0)} -> RTS100210 | S13: HANIL | T13: HL25 | U13: {=XLOOKUP($A13,'Recipients REF'!$A:$A,'Recipients REF'!K:K,"",0)} -> WR-SERIES 796 PH | V13: WECAN | W13: LSGW1750 | X13: {=XLOOKUP($A13,'Recipients REF'!$A:$A,'Recipients REF'!L:L,"",0)} -> LSGW1750 RMP 24040652 | Y13: WECAN | Z13: WDP40 | AA13: {=XLOOKUP($A13,'Recipients REF'!$A:$A,'Recipients REF'!M:M,"",0)} -> WDP40 RMP 24040398 | AI13: {=XLOOKUP($E13,Sheet11!$D:$D,Sheet11!$X:$X,"",0)} -> 869066060241339 | AJ13: {=XLOOKUP($E13,Sheet11!$D:$D,Sheet11!$Y:$Y,"",0)} -> 9083147120
A14: 384 | B14: ESTANCIA FARMERS' ASSOCIATION | C14: Estancia, Kalibo, AKLAN | E14: =PROPER(B14) -> Estancia Farmers' Association | F14: =PROPER(C14) -> Estancia, Kalibo, Aklan | G14: =PROPER(TRIM(LEFT(F14,FIND(",",F14)-1))) -> Estancia | H14: =PROPER(TRIM(MID(F14,FIND(",",F14)+1,FIND(",",F14,FIND(",",F14)+1)-FIND(",",F14)-1))) -> Kalibo | I14: =PROPER(TRIM(RIGHT(F14,LEN(F14)-FIND(",",F14,FIND(",",F14)+1)))) -> Aklan | J14: {=XLOOKUP($E14,'Recipients REF'!$B:$B,'Recipients REF'!D:D,"",0)} -> CEZAR F. ICABANDI | K14: {=XLOOKUP($E14,'Recipients REF'!$B:$B,'Recipients REF'!E:E,"",0)} -> 0950-272-6806 | L14: {=XLOOKUP($A14,'Recipients REF'!$A:$A,'Recipients REF'!F:F,"",0)} -> RCEF 23-09-21 Rebidding | M14: {=XLOOKUP($A14,'Recipients REF'!$A:$A,'Recipients REF'!G:G,"",0)} -> 4 | N14: {=XLOOKUP($A14,'Recipients REF'!$A:$A,'Recipients REF'!H:H,"",0)} -> 19042 | O14: TYM | P14: 5825R | Q14: {=XLOOKUP($A14,'Recipients REF'!$A:$A,'Recipients REF'!I:I,"",0)} -> KMC5825AKRFPV0566 | R14: {=XLOOKUP($A14,'Recipients REF'!$A:$A,'Recipients REF'!J:J,"",0)} -> RTS100229 | S14: HANIL | T14: HL25 | U14: {=XLOOKUP($A14,'Recipients REF'!$A:$A,'Recipients REF'!K:K,"",0)} -> WR-SERIES 767 PH | V14: WECAN | W14: LSGW1750 | X14: {=XLOOKUP($A14,'Recipients REF'!$A:$A,'Recipients REF'!L:L,"",0)} -> LSGW1750 RMP 24040660 | Y14: WECAN | Z14: WDP40 | AA14: {=XLOOKUP($A14,'Recipients REF'!$A:$A,'Recipients REF'!M:M,"",0)} -> WDP40 RMP 24040402 | AI14: {=XLOOKUP($E14,Sheet11!$D:$D,Sheet11!$X:$X,"",0)} -> 869066060245983 | AJ14: {=XLOOKUP($E14,Sheet11!$D:$D,Sheet11!$Y:$Y,"",0)} -> 9084547669
... A83: 622 | B83: Cupang West Multipurpose Cooperative | C83: Cupang West, Balanga City, BATAAN | E83: =PROPER(B83) -> Cupang West Multipurpose Cooperative | F83: =PROPER(C83) -> Cupang West, Balanga City, Bataan | G83: =PROPER(TRIM(LEFT(F83,FIND(",",F83)-1))) -> Cupang West | H83: =PROPER(TRIM(MID(F83,FIND(",",F83)+1,FIND(",",F83,FIND(",",F83)+1)-FIND(",",F83)-1))) -> Balanga City | I83: =PROPER(TRIM(RIGHT(F83,LEN(F83)-FIND(",",F83,FIND(",",F83)+1)))) -> Bataan | J83: {=XLOOKUP($E83,'Recipients REF'!$B:$B,'Recipients REF'!D:D,"",0)} -> Estrella De Guzman | K83: {=XLOOKUP($E83,'Recipients REF'!$B:$B,'Recipients REF'!E:E,"",0)} -> 0998-390-8488 | L83: {=XLOOKUP($A83,'Recipients REF'!$A:$A,'Recipients REF'!F:F,"",0)} -> RCEF 25-03-05 | M83: {=XLOOKUP($A83,'Recipients REF'!$A:$A,'Recipients REF'!G:G,"",0)} -> 5 | N83: {=XLOOKUP($A83,'Recipients REF'!$A:$A,'Recipients REF'!H:H,"",0)} -> 26212 & 27652 | O83: TYM | P83: 5825R | Q83: {=XLOOKUP($A83,'Recipients REF'!$A:$A,'Recipients REF'!I:I,"",0)} -> KMC5825 AASFPV0160 | R83: {=XLOOKUP($A83,'Recipients REF'!$A:$A,'Recipients REF'!J:J,"",0)} -> STS100158 | S83: HANIL | T83: HL25 | U83: {=XLOOKUP($A83,'Recipients REF'!$A:$A,'Recipients REF'!K:K,"",0)} -> R-SERIES 324PH | V83: WECAN | W83: LSGW1750 | X83: {=XLOOKUP($A83,'Recipients REF'!$A:$A,'Recipients REF'!L:L,"",0)} -> 25080378 | Y83: WECAN | Z83: WDP40 | AA83: {=XLOOKUP($A83,'Recipients REF'!$A:$A,'Recipients REF'!M:M,"",0)} -> 25080806 | AI83: {=XLOOKUP($E83,Sheet11!$D:$D,Sheet11!$X:$X,"",0)} | AJ83: {=XLOOKUP($E83,Sheet11!$D:$D,Sheet11!$Y:$Y,"",0)}
A84: 878 | B84: NASUGBU BATANGAS CENTRAL IRRIGATORS ASSOCIATION INC. | C84: Putat, Nasugbu, BATANGAS | E84: =PROPER(B84) -> Nasugbu Batangas Central Irrigators Association Inc. | F84: =PROPER(C84) -> Putat, Nasugbu, Batangas | G84: =PROPER(TRIM(LEFT(F84,FIND(",",F84)-1))) -> Putat | H84: =PROPER(TRIM(MID(F84,FIND(",",F84)+1,FIND(",",F84,FIND(",",F84)+1)-FIND(",",F84)-1))) -> Nasugbu | I84: =PROPER(TRIM(RIGHT(F84,LEN(F84)-FIND(",",F84,FIND(",",F84)+1)))) -> Batangas | J84: {=XLOOKUP($E84,'Recipients REF'!$B:$B,'Recipients REF'!D:D,"",0)} -> Walter C. Dueñas | K84: {=XLOOKUP($E84,'Recipients REF'!$B:$B,'Recipients REF'!E:E,"",0)} -> 9175415178 | L84: {=XLOOKUP($A84,'Recipients REF'!$A:$A,'Recipients REF'!F:F,"",0)} -> RCEF 25-03-05 | M84: {=XLOOKUP($A84,'Recipients REF'!$A:$A,'Recipients REF'!G:G,"",0)} -> 7 | N84: {=XLOOKUP($A84,'Recipients REF'!$A:$A,'Recipients REF'!H:H,"",0)} -> 26879 & 27921 | O84: TYM | P84: 5825R | Q84: {=XLOOKUP($A84,'Recipients REF'!$A:$A,'Recipients REF'!I:I,"",0)} -> KMC5825 AVSFPV0304 | R84: {=XLOOKUP($A84,'Recipients REF'!$A:$A,'Recipients REF'!J:J,"",0)} -> STS100295 | S84: HANIL | T84: HL25 | U84: {=XLOOKUP($A84,'Recipients REF'!$A:$A,'Recipients REF'!K:K,"",0)} -> WR-SERIES 1357PH | V84: WECAN | W84: LSGW1750 | X84: {=XLOOKUP($A84,'Recipients REF'!$A:$A,'Recipients REF'!L:L,"",0)} -> 2510851 | Y84: WECAN | Z84: WDP40 | AA84: {=XLOOKUP($A84,'Recipients REF'!$A:$A,'Recipients REF'!M:M,"",0)} -> 25121440 | AE84: 869066063806120 | AF84: 4252300210177928 | AI84: {=XLOOKUP($E84,Sheet11!$D:$D,Sheet11!$X:$X,"",0)} | AJ84: {=XLOOKUP($E84,Sheet11!$D:$D,Sheet11!$Y:$Y,"",0)}
A85: 879 | B85: MAVALOR FARMERS ASSOCIATION | C85: Mavalor, Rosario, BATANGAS | E85: =PROPER(B85) -> Mavalor Farmers Association | F85: =PROPER(C85) -> Mavalor, Rosario, Batangas | G85: =PROPER(TRIM(LEFT(F85,FIND(",",F85)-1))) -> Mavalor | H85: =PROPER(TRIM(MID(F85,FIND(",",F85)+1,FIND(",",F85,FIND(",",F85)+1)-FIND(",",F85)-1))) -> Rosario | I85: =PROPER(TRIM(RIGHT(F85,LEN(F85)-FIND(",",F85,FIND(",",F85)+1)))) -> Batangas | J85: {=XLOOKUP($E85,'Recipients REF'!$B:$B,'Recipients REF'!D:D,"",0)} -> Hilarion D. Marasigan | K85: {=XLOOKUP($E85,'Recipients REF'!$B:$B,'Recipients REF'!E:E,"",0)} -> 9289584869 | L85: {=XLOOKUP($A85,'Recipients REF'!$A:$A,'Recipients REF'!F:F,"",0)} -> RCEF 25-03-05 | M85: {=XLOOKUP($A85,'Recipients REF'!$A:$A,'Recipients REF'!G:G,"",0)} -> 7 | N85: {=XLOOKUP($A85,'Recipients REF'!$A:$A,'Recipients REF'!H:H,"",0)} -> 26880 & 27922 | O85: TYM | P85: 5825R | Q85: {=XLOOKUP($A85,'Recipients REF'!$A:$A,'Recipients REF'!I:I,"",0)} -> KMC5825 AASFPV0305 | R85: {=XLOOKUP($A85,'Recipients REF'!$A:$A,'Recipients REF'!J:J,"",0)} -> STS100310 | S85: HANIL | T85: HL25 | U85: {=XLOOKUP($A85,'Recipients REF'!$A:$A,'Recipients REF'!K:K,"",0)} -> WR-SERIES 1358PH | V85: WECAN | W85: LSGW1750 | X85: {=XLOOKUP($A85,'Recipients REF'!$A:$A,'Recipients REF'!L:L,"",0)} -> 2510844 | Y85: WECAN | Z85: WDP40 | AA85: {=XLOOKUP($A85,'Recipients REF'!$A:$A,'Recipients REF'!M:M,"",0)} -> 25121441 | AE85: 869066063796792 | AF85: 4252300210177787 | AI85: {=XLOOKUP($E85,Sheet11!$D:$D,Sheet11!$X:$X,"",0)} | AJ85: {=XLOOKUP($E85,Sheet11!$D:$D,Sheet11!$Y:$Y,"",0)}
A86: 935 | B86: Municipal Local Government Unit of Naval | C86: Padre Inocentes Garcia (Pob.), Naval, BILIRAN | E86: =PROPER(B86) -> Municipal Local Government Unit Of Naval | F86: =PROPER(C86) -> Padre Inocentes Garcia (Pob.), Naval, Biliran | G86: =PROPER(TRIM(LEFT(F86,FIND(",",F86)-1))) -> Padre Inocentes Garcia (Pob.) | H86: =PROPER(TRIM(MID(F86,FIND(",",F86)+1,FIND(",",F86,FIND(",",F86)+1)-FIND(",",F86)-1))) -> Naval | I86: =PROPER(TRIM(RIGHT(F86,LEN(F86)-FIND(",",F86,FIND(",",F86)+1)))) -> Biliran | J86: {=XLOOKUP($E86,'Recipients REF'!$B:$B,'Recipients REF'!D:D,"",0)} -> Laurence Mangco | K86: {=XLOOKUP($E86,'Recipients REF'!$B:$B,'Recipients REF'!E:E,"",0)} -> 9754781351 | L86: {=XLOOKUP($A86,'Recipients REF'!$A:$A,'Recipients REF'!F:F,"",0)} -> RCEF 25-03-05 | M86: {=XLOOKUP($A86,'Recipients REF'!$A:$A,'Recipients REF'!G:G,"",0)} -> 7 | N86: {=XLOOKUP($A86,'Recipients REF'!$A:$A,'Recipients REF'!H:H,"",0)} -> 26936 & 27978 | O86: TYM | P86: 5825R | Q86: {=XLOOKUP($A86,'Recipients REF'!$A:$A,'Recipients REF'!I:I,"",0)} -> KMC5825 ALSFPV0449 | R86: {=XLOOKUP($A86,'Recipients REF'!$A:$A,'Recipients REF'!J:J,"",0)} -> STS100326 | S86: HANIL | T86: HL25 | U86: {=XLOOKUP($A86,'Recipients REF'!$A:$A,'Recipients REF'!K:K,"",0)} -> R-SERIES 215PH | V86: WECAN | W86: LSGW1750 | X86: {=XLOOKUP($A86,'Recipients REF'!$A:$A,'Recipients REF'!L:L,"",0)} -> 25090459 | Y86: WECAN | Z86: WDP40 | AA86: {=XLOOKUP($A86,'Recipients REF'!$A:$A,'Recipients REF'!M:M,"",0)} -> 25121361 | AI86: {=XLOOKUP($E86,Sheet11!$D:$D,Sheet11!$X:$X,"",0)} | AJ86: {=XLOOKUP($E86,Sheet11!$D:$D,Sheet11!$Y:$Y,"",0)}
A87: 924 | B87: Camba-ol Progreso Irrigators Association Inc. | C87: Progreso, Alicia, BOHOL | E87: =PROPER(B87) -> Camba-Ol Progreso Irrigators Association Inc. | F87: =PROPER(C87) -> Progreso, Alicia, Bohol | G87: =PROPER(TRIM(LEFT(F87,FIND(",",F87)-1))) -> Progreso | H87: =PROPER(TRIM(MID(F87,FIND(",",F87)+1,FIND(",",F87,FIND(",",F87)+1)-FIND(",",F87)-1))) -> Alicia | I87: =PROPER(TRIM(RIGHT(F87,LEN(F87)-FIND(",",F87,FIND(",",F87)+1)))) -> Bohol | J87: {=XLOOKUP($E87,'Recipients REF'!$B:$B,'Recipients REF'!D:D,"",0)} -> Hilario B. Quinlog | K87: {=XLOOKUP($E87,'Recipients REF'!$B:$B,'Recipients REF'!E:E,"",0)} -> 0938-949-2435 | L87: {=XLOOKUP($A87,'Recipients REF'!$A:$A,'Recipients REF'!F:F,"",0)} -> RCEF 25-03-05 | M87: {=XLOOKUP($A87,'Recipients REF'!$A:$A,'Recipients REF'!G:G,"",0)} -> 7 | N87: {=XLOOKUP($A87,'Recipients REF'!$A:$A,'Recipients REF'!H:H,"",0)} -> 26925 & 27967 | O87: TYM | P87: 5825R | Q87: {=XLOOKUP($A87,'Recipients REF'!$A:$A,'Recipients REF'!I:I,"",0)} -> KMC5825 AHSFPV0341 | R87: {=XLOOKUP($A87,'Recipients REF'!$A:$A,'Recipients REF'!J:J,"",0)} -> STS100364 | S87: HANIL | T87: HL25 | U87: {=XLOOKUP($A87,'Recipients REF'!$A:$A,'Recipients REF'!K:K,"",0)} -> WR-SERIES 1371PH | V87: WECAN | W87: LSGW1750 | X87: {=XLOOKUP($A87,'Recipients REF'!$A:$A,'Recipients REF'!L:L,"",0)} -> 25080336 | Y87: WECAN | Z87: WDP40 | AA87: {=XLOOKUP($A87,'Recipients REF'!$A:$A,'Recipients REF'!M:M,"",0)} -> 25121350 | AI87: {=XLOOKUP($E87,Sheet11!$D:$D,Sheet11!$X:$X,"",0)} | AJ87: {=XLOOKUP($E87,Sheet11!$D:$D,Sheet11!$Y:$Y,"",0)}
A88: 913 | B88: CATIGBIAN IRRIGATORS' ASSOCIATION, INC. | C88: Catigbian, Buenavista, BOHOL | E88: =PROPER(B88) -> Catigbian Irrigators' Association, Inc. | F88: =PROPER(C88) -> Catigbian, Buenavista, Bohol | G88: =PROPER(TRIM(LEFT(F88,FIND(",",F88)-1))) -> Catigbian | H88: =PROPER(TRIM(MID(F88,FIND(",",F88)+1,FIND(",",F88,FIND(",",F88)+1)-FIND(",",F88)-1))) -> Buenavista | I88: =PROPER(TRIM(RIGHT(F88,LEN(F88)-FIND(",",F88,FIND(",",F88)+1)))) -> Bohol | J88: {=XLOOKUP($E88,'Recipients REF'!$B:$B,'Recipients REF'!D:D,"",0)} -> Adriano Membreve | K88: {=XLOOKUP($E88,'Recipients REF'!$B:$B,'Recipients REF'!E:E,"",0)} -> 0968-612-1666 | L88: {=XLOOKUP($A88,'Recipients REF'!$A:$A,'Recipients REF'!F:F,"",0)} -> RCEF 25-03-05 | M88: {=XLOOKUP($A88,'Recipients REF'!$A:$A,'Recipients REF'!G:G,"",0)} -> 7 | N88: {=XLOOKUP($A88,'Recipients REF'!$A:$A,'Recipients REF'!H:H,"",0)} -> 26914 & 27956 | O88: TYM | P88: 5825R | Q88: {=XLOOKUP($A88,'Recipients REF'!$A:$A,'Recipients REF'!I:I,"",0)} -> KMC5825 AKSFPV0251 | R88: {=XLOOKUP($A88,'Recipients REF'!$A:$A,'Recipients REF'!J:J,"",0)} -> STS100259 | S88: HANIL | T88: HL25 | U88: {=XLOOKUP($A88,'Recipients REF'!$A:$A,'Recipients REF'!K:K,"",0)} -> WR-SERIES 1360PH | V88: WECAN | W88: LSGW1750 | X88: {=XLOOKUP($A88,'Recipients REF'!$A:$A,'Recipients REF'!L:L,"",0)} -> 25080341 | Y88: WECAN | Z88: WDP40 | AA88: {=XLOOKUP($A88,'Recipients REF'!$A:$A,'Recipients REF'!M:M,"",0)} -> 25121339 | AI88: {=XLOOKUP($E88,Sheet11!$D:$D,Sheet11!$X:$X,"",0)} | AJ88: {=XLOOKUP($E88,Sheet11!$D:$D,Sheet11!$Y:$Y,"",0)}
A89: 914 | B89: NAGKAHUGPONG MAG-UUMA SA CAWAG (NMC) | C89: Cawag, Buenavista, BOHOL | E89: =PROPER(B89) -> Nagkahugpong Mag-Uuma Sa Cawag (Nmc) | F89: =PROPER(C89) -> Cawag, Buenavista, Bohol | G89: =PROPER(TRIM(LEFT(F89,FIND(",",F89)-1))) -> Cawag | H89: =PROPER(TRIM(MID(F89,FIND(",",F89)+1,FIND(",",F89,FIND(",",F89)+1)-FIND(",",F89)-1))) -> Buenavista | I89: =PROPER(TRIM(RIGHT(F89,LEN(F89)-FIND(",",F89,FIND(",",F89)+1)))) -> Bohol | J89: {=XLOOKUP($E89,'Recipients REF'!$B:$B,'Recipients REF'!D:D,"",0)} -> Enemesio T. Degamo Jr. | K89: {=XLOOKUP($E89,'Recipients REF'!$B:$B,'Recipients REF'!E:E,"",0)} -> 0906-141-9886 | L89: {=XLOOKUP($A89,'Recipients REF'!$A:$A,'Recipients REF'!F:F,"",0)} -> RCEF 25-03-05 | M89: {=XLOOKUP($A89,'Recipients REF'!$A:$A,'Recipients REF'!G:G,"",0)} -> 7 | N89: {=XLOOKUP($A89,'Recipients REF'!$A:$A,'Recipients REF'!H:H,"",0)} -> 26915 & 27957 | O89: TYM | P89: 5825R | Q89: {=XLOOKUP($A89,'Recipients REF'!$A:$A,'Recipients REF'!I:I,"",0)} -> KMC5825 AVSFPV0254 | R89: {=XLOOKUP($A89,'Recipients REF'!$A:$A,'Recipients REF'!J:J,"",0)} -> STS100276 | S89: HANIL | T89: HL25 | U89: {=XLOOKUP($A89,'Recipients REF'!$A:$A,'Recipients REF'!K:K,"",0)} -> WR-SERIES 1361PH | V89: WECAN | W89: LSGW1750 | X89: {=XLOOKUP($A89,'Recipients REF'!$A:$A,'Recipients REF'!L:L,"",0)} -> 25080306 | Y89: WECAN | Z89: WDP40 | AA89: {=XLOOKUP($A89,'Recipients REF'!$A:$A,'Recipients REF'!M:M,"",0)} -> 25121340 | AI89: {=XLOOKUP($E89,Sheet11!$D:$D,Sheet11!$X:$X,"",0)} | AJ89: {=XLOOKUP($E89,Sheet11!$D:$D,Sheet11!$Y:$Y,"",0)}
A90: 925 | B90: FAITH FARMERS ASSOCIATION | C90: Montesuerte, Carmen, BOHOL | E90: =PROPER(B90) -> Faith Farmers Association | F90: =PROPER(C90) -> Montesuerte, Carmen, Bohol | G90: =PROPER(TRIM(LEFT(F90,FIND(",",F90)-1))) -> Montesuerte | H90: =PROPER(TRIM(MID(F90,FIND(",",F90)+1,FIND(",",F90,FIND(",",F90)+1)-FIND(",",F90)-1))) -> Carmen | I90: =PROPER(TRIM(RIGHT(F90,LEN(F90)-FIND(",",F90,FIND(",",F90)+1)))) -> Bohol | J90: {=XLOOKUP($E90,'Recipients REF'!$B:$B,'Recipients REF'!D:D,"",0)} -> Nerie J. Asucan | K90: {=XLOOKUP($E90,'Recipients REF'!$B:$B,'Recipients REF'!E:E,"",0)} -> 0916-124-3390 | L90: {=XLOOKUP($A90,'Recipients REF'!$A:$A,'Recipients REF'!F:F,"",0)} -> RCEF 25-03-05 | M90: {=XLOOKUP($A90,'Recipients REF'!$A:$A,'Recipients REF'!G:G,"",0)} -> 7 | N90: {=XLOOKUP($A90,'Recipients REF'!$A:$A,'Recipients REF'!H:H,"",0)} -> 26926 & 27968 | O90: TYM | P90: 5825R | Q90: {=XLOOKUP($A90,'Recipients REF'!$A:$A,'Recipients REF'!I:I,"",0)} -> KMC5825 AKSFPV0332 | R90: {=XLOOKUP($A90,'Recipients REF'!$A:$A,'Recipients REF'!J:J,"",0)} -> STS100347 | S90: HANIL | T90: HL25 | U90: {=XLOOKUP($A90,'Recipients REF'!$A:$A,'Recipients REF'!K:K,"",0)} -> WR-SERIES 1372PH | V90: WECAN | W90: LSGW1750 | X90: {=XLOOKUP($A90,'Recipients REF'!$A:$A,'Recipients REF'!L:L,"",0)} -> 25090466 | Y90: WECAN | Z90: WDP40 | AA90: {=XLOOKUP($A90,'Recipients REF'!$A:$A,'Recipients REF'!M:M,"",0)} -> 25121351 | AI90: {=XLOOKUP($E90,Sheet11!$D:$D,Sheet11!$X:$X,"",0)} | AJ90: {=XLOOKUP($E90,Sheet11!$D:$D,Sheet11!$Y:$Y,"",0)}
A91: 912 | B91: CAUSWAGAN NORTE CATIGBIAN FARMERS AGRICULTURE COOPERATIVE (CANCAFAC) | C91: Causwagan Norte, Catigbian, BOHOL | E91: =PROPER(B91) -> Causwagan Norte Catigbian Farmers Agriculture Cooperative (Cancafac) | F91: =PROPER(C91) -> Causwagan Norte, Catigbian, Bohol | G91: =PROPER(TRIM(LEFT(F91,FIND(",",F91)-1))) -> Causwagan Norte | H91: =PROPER(TRIM(MID(F91,FIND(",",F91)+1,FIND(",",F91,FIND(",",F91)+1)-FIND(",",F91)-1))) -> Catigbian | I91: =PROPER(TRIM(RIGHT(F91,LEN(F91)-FIND(",",F91,FIND(",",F91)+1)))) -> Bohol | J91: {=XLOOKUP($E91,'Recipients REF'!$B:$B,'Recipients REF'!D:D,"",0)} -> Leonila G. Buhawe | K91: {=XLOOKUP($E91,'Recipients REF'!$B:$B,'Recipients REF'!E:E,"",0)} -> 0909-197-6464 | L91: {=XLOOKUP($A91,'Recipients REF'!$A:$A,'Recipients REF'!F:F,"",0)} -> RCEF 25-03-05 | M91: {=XLOOKUP($A91,'Recipients REF'!$A:$A,'Recipients REF'!G:G,"",0)} -> 7 | N91: {=XLOOKUP($A91,'Recipients REF'!$A:$A,'Recipients REF'!H:H,"",0)} -> 26913 & 27955 | O91: TYM | P91: 5825R | Q91: {=XLOOKUP($A91,'Recipients REF'!$A:$A,'Recipients REF'!I:I,"",0)} -> KMC5825 ALSFPV0290 | R91: {=XLOOKUP($A91,'Recipients REF'!$A:$A,'Recipients REF'!J:J,"",0)} -> STS100288 | S91: HANIL | T91: HL25 | U91: {=XLOOKUP($A91,'Recipients REF'!$A:$A,'Recipients REF'!K:K,"",0)} -> WR-SERIES 1359PH | V91: WECAN | W91: LSGW1750 | X91: {=XLOOKUP($A91,'Recipients REF'!$A:$A,'Recipients REF'!L:L,"",0)} -> 25090467 | Y91: WECAN | Z91: WDP40 | AA91: {=XLOOKUP($A91,'Recipients REF'!$A:$A,'Recipients REF'!M:M,"",0)} -> 25121338 | AI91: {=XLOOKUP($E91,Sheet11!$D:$D,Sheet11!$X:$X,"",0)} | AJ91: {=XLOOKUP($E91,Sheet11!$D:$D,Sheet11!$Y:$Y,"",0)}
A92: 915 | B92: DANAHAW FARMERS ASSOCIATION (DAFA) | C92: Danahao, Clarin, BOHOL | E92: =PROPER(B92) -> Danahaw Farmers Association (Dafa) | F92: =PROPER(C92) -> Danahao, Clarin, Bohol | G92: =PROPER(TRIM(LEFT(F92,FIND(",",F92)-1))) -> Danahao | H92: =PROPER(TRIM(MID(F92,FIND(",",F92)+1,FIND(",",F92,FIND(",",F92)+1)-FIND(",",F92)-1))) -> Clarin | I92: =PROPER(TRIM(RIGHT(F92,LEN(F92)-FIND(",",F92,FIND(",",F92)+1)))) -> Bohol | J92: {=XLOOKUP($E92,'Recipients REF'!$B:$B,'Recipients REF'!D:D,"",0)} -> Julieto C. Infesto | K92: {=XLOOKUP($E92,'Recipients REF'!$B:$B,'Recipients REF'!E:E,"",0)} -> 0912-532-6739 | L92: {=XLOOKUP($A92,'Recipients REF'!$A:$A,'Recipients REF'!F:F,"",0)} -> RCEF 25-03-05 | M92: {=XLOOKUP($A92,'Recipients REF'!$A:$A,'Recipients REF'!G:G,"",0)} -> 7 | N92: {=XLOOKUP($A92,'Recipients REF'!$A:$A,'Recipients REF'!H:H,"",0)} -> 26916 & 27958 | O92: TYM | P92: 5825R | Q92: {=XLOOKUP($A92,'Recipients REF'!$A:$A,'Recipients REF'!I:I,"",0)} -> KMC5825 AJSFPV0171 | R92: {=XLOOKUP($A92,'Recipients REF'!$A:$A,'Recipients REF'!J:J,"",0)} -> STS100198 | S92: HANIL | T92: HL25 | U92: {=XLOOKUP($A92,'Recipients REF'!$A:$A,'Recipients REF'!K:K,"",0)} -> WR-SERIES 1362PH | V92: WECAN | W92: LSGW1750 | X92: {=XLOOKUP($A92,'Recipients REF'!$A:$A,'Recipients REF'!L:L,"",0)} -> 25080326 | Y92: WECAN | Z92: WDP40 | AA92: {=XLOOKUP($A92,'Recipients REF'!$A:$A,'Recipients REF'!M:M,"",0)} -> 25121341 | AI92: {=XLOOKUP($E92,Sheet11!$D:$D,Sheet11!$X:$X,"",0)} | AJ92: {=XLOOKUP($E92,Sheet11!$D:$D,Sheet11!$Y:$Y,"",0)}
A93: 916 | B93: POB-CAN CLARIN IRRIGATORS ASSOCIATION INC | C93: Candajec, Clarin, BOHOL | E93: =PROPER(B93) -> Pob-Can Clarin Irrigators Association Inc | F93: =PROPER(C93) -> Candajec, Clarin, Bohol | G93: =PROPER(TRIM(LEFT(F93,FIND(",",F93)-1))) -> Candajec | H93: =PROPER(TRIM(MID(F93,FIND(",",F93)+1,FIND(",",F93,FIND(",",F93)+1)-FIND(",",F93)-1))) -> Clarin | I93: =PROPER(TRIM(RIGHT(F93,LEN(F93)-FIND(",",F93,FIND(",",F93)+1)))) -> Bohol | J93: {=XLOOKUP($E93,'Recipients REF'!$B:$B,'Recipients REF'!D:D,"",0)} -> Maxima Z. Pelesores | K93: {=XLOOKUP($E93,'Recipients REF'!$B:$B,'Recipients REF'!E:E,"",0)} -> 0970-524-8113 | L93: {=XLOOKUP($A93,'Recipients REF'!$A:$A,'Recipients REF'!F:F,"",0)} -> RCEF 25-03-05 | M93: {=XLOOKUP($A93,'Recipients REF'!$A:$A,'Recipients REF'!G:G,"",0)} -> 7 | N93: {=XLOOKUP($A93,'Recipients REF'!$A:$A,'Recipients REF'!H:H,"",0)} -> 26917 & 27959 | O93: TYM | P93: 5825R | Q93: {=XLOOKUP($A93,'Recipients REF'!$A:$A,'Recipients REF'!I:I,"",0)} -> KMC5825 AVSFPV0208 | R93: {=XLOOKUP($A93,'Recipients REF'!$A:$A,'Recipients REF'!J:J,"",0)} -> STS100300 | S93: HANIL | T93: HL25 | U93: {=XLOOKUP($A93,'Recipients REF'!$A:$A,'Recipients REF'!K:K,"",0)} -> WR-SERIES 1363PH | V93: WECAN | W93: LSGW1750 | X93: {=XLOOKUP($A93,'Recipients REF'!$A:$A,'Recipients REF'!L:L,"",0)} -> 25090468 | Y93: WECAN | Z93: WDP40 | AA93: {=XLOOKUP($A93,'Recipients REF'!$A:$A,'Recipients REF'!M:M,"",0)} -> 25121342 | AI93: {=XLOOKUP($E93,Sheet11!$D:$D,Sheet11!$X:$X,"",0)} | AJ93: {=XLOOKUP($E93,Sheet11!$D:$D,Sheet11!$Y:$Y,"",0)}
